Workbook

Sheet All WH Stock Status
H1: Monthly Demand | M1: Critical Items
B2: Category | C2: Item Code | D2: Item Description | E2: Packing | F2: UOM | G2: Conversion | H2: QTY in Pack | I2: QTY in Unit | J2: Lead Time | K2: Reordering Point | L2: WH Stocks | M2: Coverage/Day | N2: 0rder Status | O2: Criticality | R2: Category | S2: Stock Status
A3: 168 | B3: طباعة وتغليف - Packaging | C3: PM-00638 | D3: Caramelized Pecan Paper Box 1 PCS (New ID) | علبة بيكان مكرمل ورقية | E3: 1 Box X 600 | F3: Box | G3: 0.0016666667 | H3: =VLOOKUP($C3,'Master File June-26'!$C$3:$L$670,6,0) -> 13 | I3: =VLOOKUP($C3,'Master File June-26'!$C$3:$L$670,7,0) -> 7800 | J3: =VLOOKUP($C3,'Master File June-26'!$C$3:$L$670,8,0) -> 14 | K3: =VLOOKUP($C3,'Master File June-26'!$C$3:$L$670,9,0) -> 3900 | L3: =VLOOKUP($C3,'Master File June-26'!$C$3:$L$670,10,0) -> 0 | M3: =IFERROR((L3/I3*30),0) -> 0 | N3: =IF(M3<J3,"ORDER NOW","IN STOCK") -> ORDER NOW | O3: =IF(M3<J3,"CRITICAL","FOLLOW UP DELIVERY") -> CRITICAL | S3: =IF(L3<K3,0,1) -> 0
A4: 94 | B4: طباعة وتغليف - Packaging | C4: PM-00200 | D4: Season Paper cup Double 12 Oz ( BREEHANT ) كوب ورقي 12 اونصه تصميم موسمي ( بريهانت ) | E4: 1 Box X 500 | F4: Box | G4: 0.002 | H4: =VLOOKUP($C4,'Master File June-26'!$C$3:$L$670,6,0) -> 8 | I4: =VLOOKUP($C4,'Master File June-26'!$C$3:$L$670,7,0) -> 4000 | J4: =VLOOKUP($C4,'Master File June-26'!$C$3:$L$670,8,0) -> 14 | K4: =VLOOKUP($C4,'Master File June-26'!$C$3:$L$670,9,0) -> 2000 | L4: =VLOOKUP($C4,'Master File June-26'!$C$3:$L$670,10,0) -> 19000 | M4: =IFERROR((L4/I4*30),0) -> 142.5 | N4: =IF(M4<J4,"ORDER NOW","IN STOCK") -> IN STOCK | O4: =IF(M4<J4,"CRITICAL","FOLLOW UP DELIVERY") -> FOLLOW UP DELIVERY | R4: B | S4: =IF(L4<K4,0,1) -> 1
A5: 54 | B5: طباعة وتغليف - Packaging | C5: PM-00669 | D5: سليف ايس تي خوخ | E5: 1 Box X 1200 Pcs | F5: Box | G5: =1/1200 -> 0.00083333333 | H5: =VLOOKUP($C5,'Master File June-26'!$C$3:$L$670,6,0) -> 10 | I5: =VLOOKUP($C5,'Master File June-26'!$C$3:$L$670,7,0) -> 12000 | J5: =VLOOKUP($C5,'Master File June-26'!$C$3:$L$670,8,0) -> 14 | K5: =VLOOKUP($C5,'Master File June-26'!$C$3:$L$670,9,0) -> 6000 | L5: =VLOOKUP($C5,'Master File June-26'!$C$3:$L$670,10,0) -> 0 | M5: =IFERROR((L5/I5*30),0) -> 0 | N5: =IF(M5<J5,"ORDER NOW","IN STOCK") -> ORDER NOW | O5: =IF(M5<J5,"CRITICAL","FOLLOW UP DELIVERY") -> CRITICAL | R5: A | S5: =IF(L5<K5,0,1) -> 0
A6: 178 | B6: طباعة وتغليف - Packaging | C6: PM-00043 | D6: كيس بلاستيك ضبابي مطبوع مع استيكر اغلاق 10 كيلو (التاندو)Printed foggy plastic bag with sticker closure (Tando) | E6: Box | F6: Box | G6: 1 | H6: =VLOOKUP($C6,'Master File June-26'!$C$3:$L$670,6,0) -> 8 | I6: =VLOOKUP($C6,'Master File June-26'!$C$3:$L$670,7,0) -> 3840 | J6: =VLOOKUP($C6,'Master File June-26'!$C$3:$L$670,8,0) -> 14 | K6: =VLOOKUP($C6,'Master File June-26'!$C$3:$L$670,9,0) -> 1920 | L6: =VLOOKUP($C6,'Master File June-26'!$C$3:$L$670,10,0) -> 0 | M6: =IFERROR((L6/I6*30),0) -> 0 | N6: =IF(M6<J6,"ORDER NOW","IN STOCK") -> ORDER NOW | O6: =IF(M6<J6,"CRITICAL","FOLLOW UP DELIVERY") -> CRITICAL | S6: =IF(L6<K6,0,1) -> 0
A7: 93 | B7: طباعة وتغليف - Packaging | C7: PM-00653 | D7: Cup 7 oz double wide Seasnal ( Breehant ) - كوب 7 اونص دبل فتحة واسعه موسمى ( بريهانت ) | E7: 1 Box 20 Pack X 25 Pcs | F7: Box | G7: 0.002 | H7: =VLOOKUP($C7,'Master File June-26'!$C$3:$L$670,6,0) -> 150 | I7: =VLOOKUP($C7,'Master File June-26'!$C$3:$L$670,7,0) -> 75000 | J7: =VLOOKUP($C7,'Master File June-26'!$C$3:$L$670,8,0) -> 14 | K7: =VLOOKUP($C7,'Master File June-26'!$C$3:$L$670,9,0) -> 37500 | L7: =VLOOKUP($C7,'Master File June-26'!$C$3:$L$670,10,0) -> 0 | M7: =IFERROR((L7/I7*30),0) -> 0 | N7: =IF(M7<J7,"ORDER NOW","IN STOCK") -> ORDER NOW | O7: =IF(M7<J7,"CRITICAL","FOLLOW UP DELIVERY") -> CRITICAL | R7: B | S7: =IF(L7<K7,0,1) -> 0
A8: 173 | B8: طباعة وتغليف - Packaging | C8: PM-00296 | D8: Aluminium foil قصدير | E8: Box | F8: Box | G8: 1 | H8: =VLOOKUP($C8,'Master File June-26'!$C$3:$L$670,6,0) -> 2 | I8: =VLOOKUP($C8,'Master File June-26'!$C$3:$L$670,7,0) -> 2 | J8: =VLOOKUP($C8,'Master File June-26'!$C$3:$L$670,8,0) -> 14 | K8: =VLOOKUP($C8,'Master File June-26'!$C$3:$L$670,9,0) -> 1 | L8: =VLOOKUP($C8,'Master File June-26'!$C$3:$L$670,10,0) -> 0 | M8: =IFERROR((L8/I8*30),0) -> 0 | N8: =IF(M8<J8,"ORDER NOW","IN STOCK") -> ORDER NOW | O8: =IF(M8<J8,"CRITICAL","FOLLOW UP DELIVERY") -> CRITICAL | S8: =IF(L8<K8,0,1) -> 0
A9: 539 | B9: Dry Goods - منتجات جافة | C9: RM-00502 | D9: Sugar Jaggery Vijay سكر جاجيري مدور | E9: Box | F9: Box | G9: 1 | H9: =VLOOKUP($C9,'Master File June-26'!$C$3:$L$670,6,0) -> 2 | I9: =VLOOKUP($C9,'Master File June-26'!$C$3:$L$670,7,0) -> 2 | J9: =VLOOKUP($C9,'Master File June-26'!$C$3:$L$670,8,0) -> 14 | K9: =VLOOKUP($C9,'Master File June-26'!$C$3:$L$670,9,0) -> 1 | L9: =VLOOKUP($C9,'Master File June-26'!$C$3:$L$670,10,0) -> 0 | M9: =IFERROR((L9/I9*30),0) -> 0 | N9: =IF(M9<J9,"ORDER NOW","IN STOCK") -> ORDER NOW | O9: =IF(M9<J9,"CRITICAL","FOLLOW UP DELIVERY") -> CRITICAL | S9: =IF(L9<K9,0,1) -> 0
A10: 557 | B10: Dry Goods - منتجات جافة | C10: RM-00206 | D10: Mehran red pepper فلفل أحمر مهران | E10: Box | F10: Box | G10: 1 | H10: =VLOOKUP($C10,'Master File June-26'!$C$3:$L$670,6,0) -> 1 | I10: =VLOOKUP($C10,'Master File June-26'!$C$3:$L$670,7,0) -> 1 | J10: =VLOOKUP($C10,'Master File June-26'!$C$3:$L$670,8,0) -> 14 | K10: =VLOOKUP($C10,'Master File June-26'!$C$3:$L$670,9,0) -> 0.5 | L10: =VLOOKUP($C10,'Master File June-26'!$C$3:$L$670,10,0) -> 0 | M10: =IFERROR((L10/I10*30),0) -> 0 | N10: =IF(M10<J10,"ORDER NOW","IN STOCK") -> ORDER NOW | O10: =IF(M10<J10,"CRITICAL","FOLLOW UP DELIVERY") -> CRITICAL | S10: =IF(L10<K10,0,1) -> 0
A11: 64 | B11: طباعة وتغليف - Packaging | C11: PM-00139 | D11: كرت الاسبريسو نمق (سان اجناسيو) Espresso card (San Ignacio) | E11: 1 Bundle X 500 pcs | F11: bundel | G11: 0.002 | H11: =VLOOKUP($C11,'Master File June-26'!$C$3:$L$670,6,0) -> 5.5 | I11: =VLOOKUP($C11,'Master File June-26'!$C$3:$L$670,7,0) -> 2750 | J11: =VLOOKUP($C11,'Master File June-26'!$C$3:$L$670,8,0) -> 14 | K11: =VLOOKUP($C11,'Master File June-26'!$C$3:$L$670,9,0) -> 1375 | L11: =VLOOKUP($C11,'Master File June-26'!$C$3:$L$670,10,0) -> 0 | M11: =IFERROR((L11/I11*30),0) -> 0 | N11: =IF(M11<J11,"ORDER NOW","IN STOCK") -> ORDER NOW | O11: =IF(M11<J11,"CRITICAL","FOLLOW UP DELIVERY") -> CRITICAL | R11: A | S11: =IF(L11<K11,0,1) -> 0
A12: 651 | C12: RM-00677 | D12: مايونيز قودي / Goody Mayonnaise | E12: Pcs | G12: 1 | H12: =VLOOKUP($C12,'Master File June-26'!$C$3:$L$670,6,0) -> 13 | I12: =VLOOKUP($C12,'Master File June-26'!$C$3:$L$670,7,0) -> 195 | J12: =VLOOKUP($C12,'Master File June-26'!$C$3:$L$670,8,0) -> 14 | K12: =VLOOKUP($C12,'Master File June-26'!$C$3:$L$670,9,0) -> 97.5 | L12: =VLOOKUP($C12,'Master File June-26'!$C$3:$L$670,10,0) -> 211.44 | M12: =IFERROR((L12/I12*30),0) -> 32.529231 | N12: =IF(M12<J12,"ORDER NOW","IN STOCK") -> IN STOCK | O12: =IF(M12<J12,"CRITICAL","FOLLOW UP DELIVERY") -> FOLLOW UP DELIVERY | S12: =IF(L12<K12,0,1) -> 1
A13: 398 | B13: Dry Goods - منتجات جافة | C13: RM-00677 | D13: مايونيز قودي / Goody Mayonnaise | E13: 1 Box X 4 Pcs X 3.75 | F13: Box | G13: =1/15 -> 0.066666667 | H13: =VLOOKUP($C13,'Master File June-26'!$C$3:$L$670,6,0) -> 13 | I13: =VLOOKUP($C13,'Master File June-26'!$C$3:$L$670,7,0) -> 195 | J13: =VLOOKUP($C13,'Master File June-26'!$C$3:$L$670,8,0) -> 14 | K13: =VLOOKUP($C13,'Master File June-26'!$C$3:$L$670,9,0) -> 97.5 | L13: =VLOOKUP($C13,'Master File June-26'!$C$3:$L$670,10,0) -> 211.44 | M13: =IFERROR((L13/I13*30),0) -> 32.529231 | N13: =IF(M13<J13,"ORDER NOW","IN STOCK") -> IN STOCK | O13: =IF(M13<J13,"CRITICAL","FOLLOW UP DELIVERY") -> FOLLOW UP DELIVERY | S13: =IF(L13<K13,0,1) -> 1
A14: 354 | B14: Dry Goods - منتجات جافة | C14: RM-00415 | D14: جوز البيكان | Pecan nuts | E14: 1 Bag X 13.6 Kg | F14: bag | G14: 0.076923077 | H14: =VLOOKUP($C14,'Master File June-26'!$C$3:$L$670,6,0) -> 89.5 | I14: =VLOOKUP($C14,'Master File June-26'!$C$3:$L$670,7,0) -> 1163.5 | J14: =VLOOKUP($C14,'Master File June-26'!$C$3:$L$670,8,0) -> 14 | K14: =VLOOKUP($C14,'Master File June-26'!$C$3:$L$670,9,0) -> 581.75 | L14: =VLOOKUP($C14,'Master File June-26'!$C$3:$L$670,10,0) -> 0 | M14: =IFERROR((L14/I14*30),0) -> 0 | N14: =IF(M14<J14,"ORDER NOW","IN STOCK") -> ORDER NOW | O14: =IF(M14<J14,"CRITICAL","FOLLOW UP DELIVERY") -> CRITICAL | S14: =IF(L14<K14,0,1) -> 0
A15: 516 | B15: Dry Goods - منتجات جافة | C15: RM-00421 | D15: Coconut powder | جوز الهند بودر | E15: 1 BAG X X 7 KG | F15: bag | G15: 0.14285714 | H15: =VLOOKUP($C15,'Master File June-26'!$C$3:$L$670,6,0) -> 43 | I15: =VLOOKUP($C15,'Master File June-26'!$C$3:$L$670,7,0) -> 301 | J15: =VLOOKUP($C15,'Master File June-26'!$C$3:$L$670,8,0) -> 14 | K15: =VLOOKUP($C15,'Master File June-26'!$C$3:$L$670,9,0) -> 150.5 | L15: =VLOOKUP($C15,'Master File June-26'!$C$3:$L$670,10,0) -> 0 | M15: =IFERROR((L15/I15*30),0) -> 0 | N15: =IF(M15<J15,"ORDER NOW","IN STOCK") -> ORDER NOW | O15: =IF(M15<J15,"CRITICAL","FOLLOW UP DELIVERY") -> CRITICAL | S15: =IF(L15<K15,0,1) -> 0
A16: 491 | B16: Dry Goods - منتجات جافة | C16: RM-00183 | D16: Ketchup Tomato كاتشب | E16: 1 Box X 10pcs X 570 grm | F16: Box | G16: 0.1754386 | H16: =VLOOKUP($C16,'Master File June-26'!$C$3:$L$670,6,0) -> 4 | I16: =VLOOKUP($C16,'Master File June-26'!$C$3:$L$670,7,0) -> 22.8 | J16: =VLOOKUP($C16,'Master File June-26'!$C$3:$L$670,8,0) -> 14 | K16: =VLOOKUP($C16,'Master File June-26'!$C$3:$L$670,9,0) -> 11.4 | L16: =VLOOKUP($C16,'Master File June-26'!$C$3:$L$670,10,0) -> 23.94 | M16: =IFERROR((L16/I16*30),0) -> 31.5 | N16: =IF(M16<J16,"ORDER NOW","IN STOCK") -> IN STOCK | O16: =IF(M16<J16,"CRITICAL","FOLLOW UP DELIVERY") -> FOLLOW UP DELIVERY | S16: =IF(L16<K16,0,1) -> 1
A17: 543 | B17: FROZEN ITEMS - منتجات مجمدة | C17: RM-00018 | D17: جبن شيدر انجليزي Irish Mild yellow cheddar Cheese | E17: KG | F17: Pcs | G17: 1 | H17: =VLOOKUP($C17,'Master File June-26'!$C$3:$L$670,6,0) -> 13 | I17: =VLOOKUP($C17,'Master File June-26'!$C$3:$L$670,7,0) -> 13 | J17: =VLOOKUP($C17,'Master File June-26'!$C$3:$L$670,8,0) -> 14 | K17: =VLOOKUP($C17,'Master File June-26'!$C$3:$L$670,9,0) -> 6.5 | L17: =VLOOKUP($C17,'Master File June-26'!$C$3:$L$670,10,0) -> 0 | M17: =IFERROR((L17/I17*30),0) -> 0 | N17: =IF(M17<J17,"ORDER NOW","IN STOCK") -> ORDER NOW | O17: =IF(M17<J17,"CRITICAL","FOLLOW UP DELIVERY") -> CRITICAL | S17: =IF(L17<K17,0,1) -> 0
A18: 390 | B18: Dry Goods - منتجات جافة | C18: RM-00681 | D18: معبوج تمر هندي / Tamrind | E18: 1 Pcs X 500 G | F18: Pcs | G18: 2 | H18: =VLOOKUP($C18,'Master File June-26'!$C$3:$L$670,6,0) -> 44 | I18: =VLOOKUP($C18,'Master File June-26'!$C$3:$L$670,7,0) -> 22 | J18: =VLOOKUP($C18,'Master File June-26'!$C$3:$L$670,8,0) -> 14 | K18: =VLOOKUP($C18,'Master File June-26'!$C$3:$L$670,9,0) -> 11 | L18: =VLOOKUP($C18,'Master File June-26'!$C$3:$L$670,10,0) -> 0 | M18: =IFERROR((L18/I18*30),0) -> 0 | N18: =IF(M18<J18,"ORDER NOW","IN STOCK") -> ORDER NOW | O18: =IF(M18<J18,"CRITICAL","FOLLOW UP DELIVERY") -> CRITICAL | S18: =IF(L18<K18,0,1) -> 0
A19: 495 | B19: Dry Goods - منتجات جافة | C19: RM-00423 | D19: Hazelnut بندق | E19: 1 Bag X 10 Kg | F19: Box | G19: 0.1 | H19: =VLOOKUP($C19,'Master File June-26'!$C$3:$L$670,6,0) -> 120 | I19: =VLOOKUP($C19,'Master File June-26'!$C$3:$L$670,7,0) -> 1200 | J19: =VLOOKUP($C19,'Master File June-26'!$C$3:$L$670,8,0) -> 14 | K19: =VLOOKUP($C19,'Master File June-26'!$C$3:$L$670,9,0) -> 600 | L19: =VLOOKUP($C19,'Master File June-26'!$C$3:$L$670,10,0) -> 0 | M19: =IFERROR((L19/I19*30),0) -> 0 | N19: =IF(M19<J19,"ORDER NOW","IN STOCK") -> ORDER NOW | O19: =IF(M19<J19,"CRITICAL","FOLLOW UP DELIVERY") -> CRITICAL | S19: =IF(L19<K19,0,1) -> 0
A20: 273 | B20: طباعة وتغليف - Packaging | C20: CO-00467 | D20: Glass cup 65ml كوب زجاج 65 ملي لتقديم المياه الغازية | E20: 1 Box X 6 Pcs | F20: Box | G20: 0.16666667 | H20: =VLOOKUP($C20,'Master File June-26'!$C$3:$L$670,6,0) -> 22 | I20: =VLOOKUP($C20,'Master File June-26'!$C$3:$L$670,7,0) -> 132 | J20: =VLOOKUP($C20,'Master File June-26'!$C$3:$L$670,8,0) -> 14 | K20: =VLOOKUP($C20,'Master File June-26'!$C$3:$L$670,9,0) -> 66 | L20: =VLOOKUP($C20,'Master File June-26'!$C$3:$L$670,10,0) -> 36 | M20: =IFERROR((L20/I20*30),0) -> 8.1818182 | N20: =IF(M20<J20,"ORDER NOW","IN STOCK") -> ORDER NOW | O20: =IF(M20<J20,"CRITICAL","FOLLOW UP DELIVERY") -> CRITICAL | S20: =IF(L20<K20,0,1) -> 0
A21: 386 | B21: Dry Goods - منتجات جافة | C21: RM-00439 | D21: Unroasted peanuts | فول سوداني | E21: 1 Bag X 10 Kg | F21: bag | G21: 0.1 | H21: =VLOOKUP($C21,'Master File June-26'!$C$3:$L$670,6,0) -> 9.5 | I21: =VLOOKUP($C21,'Master File June-26'!$C$3:$L$670,7,0) -> 95 | J21: =VLOOKUP($C21,'Master File June-26'!$C$3:$L$670,8,0) -> 14 | K21: =VLOOKUP($C21,'Master File June-26'!$C$3:$L$670,9,0) -> 47.5 | L21: =VLOOKUP($C21,'Master File June-26'!$C$3:$L$670,10,0) -> 20 | M21: =IFERROR((L21/I21*30),0) -> 6.3157895 | N21: =IF(M21<J21,"ORDER NOW","IN STOCK") -> ORDER NOW | O21: =IF(M21<J21,"CRITICAL","FOLLOW UP DELIVERY") -> CRITICAL | S21: =IF(L21<K21,0,1) -> 0
A22: 58 | B22: طباعة وتغليف - Packaging | C22: PM-00528 | D22: كوب فخار 200 مل - محفور بشعار من الداخل والخارج - قليز شفاف مطفي | E22: Pcs. | F22: Pcs | G22: 1 | H22: =VLOOKUP($C22,'Master File June-26'!$C$3:$L$670,6,0) -> 20 | I22: =VLOOKUP($C22,'Master File June-26'!$C$3:$L$670,7,0) -> 20 | J22: =VLOOKUP($C22,'Master File June-26'!$C$3:$L$670,8,0) -> 30 | K22: =VLOOKUP($C22,'Master File June-26'!$C$3:$L$670,9,0) -> 21.428571 | L22: =VLOOKUP($C22,'Master File June-26'!$C$3:$L$670,10,0) -> 0 | M22: =IFERROR((L22/I22*30),0) -> 0 | N22: =IF(M22<J22,"ORDER NOW","IN STOCK") -> ORDER NOW | O22: =IF(M22<J22,"CRITICAL","FOLLOW UP DELIVERY") -> CRITICAL | R22: A | S22: =IF(L22<K22,0,1) -> 0
A23: 380 | B23: Dry Goods - منتجات جافة | C23: RM-00006 | D23: Goody Creamy Peanut Butte | قودي زبدة الفول السوداني الناعمة | E23: 12pcs x 1 kg | F23: Pcs | G23: 0.083333333 | H23: =VLOOKUP($C23,'Master File June-26'!$C$3:$L$670,6,0) -> 55 | I23: =VLOOKUP($C23,'Master File June-26'!$C$3:$L$670,7,0) -> 660 | J23: =VLOOKUP($C23,'Master File June-26'!$C$3:$L$670,8,0) -> 14 | K23: =VLOOKUP($C23,'Master File June-26'!$C$3:$L$670,9,0) -> 330 | L23: =VLOOKUP($C23,'Master File June-26'!$C$3:$L$670,10,0) -> 6.2 | M23: =IFERROR((L23/I23*30),0) -> 0.28181818 | N23: =IF(M23<J23,"ORDER NOW","IN STOCK") -> ORDER NOW | O23: =IF(M23<J23,"CRITICAL","FOLLOW UP DELIVERY") -> CRITICAL | S23: =IF(L23<K23,0,1) -> 0
A24: 395 | B24: Dry Goods - منتجات جافة | C24: RM-00175 | D24: ORIG RANCH SAUCE | صوص الرانش | E24: 1X6X530 GM (3.8 KG) | F24: KG | G24: =1/3.8 -> 0.26315789 | H24: =VLOOKUP($C24,'Master File June-26'!$C$3:$L$670,6,0) -> 16 | I24: =VLOOKUP($C24,'Master File June-26'!$C$3:$L$670,7,0) -> 60.8 | J24: =VLOOKUP($C24,'Master File June-26'!$C$3:$L$670,8,0) -> 14 | K24: =VLOOKUP($C24,'Master File June-26'!$C$3:$L$670,9,0) -> 30.4 | L24: =VLOOKUP($C24,'Master File June-26'!$C$3:$L$670,10,0) -> 0 | M24: =IFERROR((L24/I24*30),0) -> 0 | N24: =IF(M24<J24,"ORDER NOW","IN STOCK") -> ORDER NOW | O24: =IF(M24<J24,"CRITICAL","FOLLOW UP DELIVERY") -> CRITICAL | S24: =IF(L24<K24,0,1) -> 0
A25: 343 | B25: Beverage - مشروبات | C25: RM-00320 | D25: صوص جوز البيكان VARIEGATO NOCE PECAN | E25: 1 Ctn. X 2 Tin X 5kg | F25: Ctn | G25: 0.1 | H25: =VLOOKUP($C25,'Master File June-26'!$C$3:$L$670,6,0) -> 143 | I25: =VLOOKUP($C25,'Master File June-26'!$C$3:$L$670,7,0) -> 1430 | J25: =VLOOKUP($C25,'Master File June-26'!$C$3:$L$670,8,0) -> 14 | K25: =VLOOKUP($C25,'Master File June-26'!$C$3:$L$670,9,0) -> 715 | L25: =VLOOKUP($C25,'Master File June-26'!$C$3:$L$670,10,0) -> 650 | M25: =IFERROR((L25/I25*30),0) -> 13.636364 | N25: =IF(M25<J25,"ORDER NOW","IN STOCK") -> ORDER NOW | O25: =IF(M25<J25,"CRITICAL","FOLLOW UP DELIVERY") -> CRITICAL | S25: =IF(L25<K25,0,1) -> 0
A26: 22 | B26: طباعة وتغليف - Packaging | C26: PM-00251 | D26: 4 Oz Sauce Cup plasticعلبة صوص 4 اونصه بلاستيك | E26: 1 Box X 20 Pack X 100 Pcs | F26: Box | G26: 0.0005 | H26: =VLOOKUP($C26,'Master File June-26'!$C$3:$L$670,6,0) -> 145.5 | I26: =VLOOKUP($C26,'Master File June-26'!$C$3:$L$670,7,0) -> 291000 | J26: =VLOOKUP($C26,'Master File June-26'!$C$3:$L$670,8,0) -> 14 | K26: =VLOOKUP($C26,'Master File June-26'!$C$3:$L$670,9,0) -> 145500 | L26: =VLOOKUP($C26,'Master File June-26'!$C$3:$L$670,10,0) -> 65500 | M26: =IFERROR((L26/I26*30),0) -> 6.7525773 | N26: =IF(M26<J26,"ORDER NOW","IN STOCK") -> ORDER NOW | O26: =IF(M26<J26,"CRITICAL","FOLLOW UP DELIVERY") -> CRITICAL | R26: A | S26: =IF(L26<K26,0,1) -> 0
A27: 70 | B27: طباعة وتغليف - Packaging | C27: PM-00261 | D27: Baking Paper 60*40 ورق خبازة 60*40 | E27: 1 Box X 500 Pcs. / 1 Box X 1000 Pcs. | F27: Box | G27: 0.002 | H27: =VLOOKUP($C27,'Master File June-26'!$C$3:$L$670,6,0) -> 100 | I27: =VLOOKUP($C27,'Master File June-26'!$C$3:$L$670,7,0) -> 50000 | J27: =VLOOKUP($C27,'Master File June-26'!$C$3:$L$670,8,0) -> 14 | K27: =VLOOKUP($C27,'Master File June-26'!$C$3:$L$670,9,0) -> 25000 | L27: =VLOOKUP($C27,'Master File June-26'!$C$3:$L$670,10,0) -> 44000 | M27: =IFERROR((L27/I27*30),0) -> 26.4 | N27: =IF(M27<J27,"ORDER NOW","IN STOCK") -> IN STOCK | O27: =IF(M27<J27,"CRITICAL","FOLLOW UP DELIVERY") -> FOLLOW UP DELIVERY | R27: A | S27: =IF(L27<K27,0,1) -> 1
A28: 102 | B28: طباعة وتغليف - Packaging | C28: PM-00357 | D28: Pomegranate Iced Tea Sticker ( breehant ) ستيكر شاي مثلج بالرمان (بريهانت) | E28: 1 bundle X 500 PCS | F28: bundel | G28: 0.002 | H28: =VLOOKUP($C28,'Master File June-26'!$C$3:$L$670,6,0) -> 16 | I28: =VLOOKUP($C28,'Master File June-26'!$C$3:$L$670,7,0) -> 8000 | J28: =VLOOKUP($C28,'Master File June-26'!$C$3:$L$670,8,0) -> 14 | K28: =VLOOKUP($C28,'Master File June-26'!$C$3:$L$670,9,0) -> 4000 | L28: =VLOOKUP($C28,'Master File June-26'!$C$3:$L$670,10,0) -> 3000 | M28: =IFERROR((L28/I28*30),0) -> 11.25 | N28: =IF(M28<J28,"ORDER NOW","IN STOCK") -> ORDER NOW | O28: =IF(M28<J28,"CRITICAL","FOLLOW UP DELIVERY") -> CRITICAL | R28: A | S28: =IF(L28<K28,0,1) -> 0
A29: 602 | B29: Beverage - مشروبات | C29: SF-00154 | D29: Monin PEACH TEA Syrup 1L مونین شراب شاي الخوخ 1لتر | E29: 1 Box X 6 Bottle X 1 Ltr | F29: Box | G29: =1/6 -> 0.16666667 | H29: =VLOOKUP($C29,'Master File June-26'!$C$3:$L$670,6,0) -> 5.5 | I29: =VLOOKUP($C29,'Master File June-26'!$C$3:$L$670,7,0) -> 33 | J29: =VLOOKUP($C29,'Master File June-26'!$C$3:$L$670,8,0) -> 14 | K29: =VLOOKUP($C29,'Master File June-26'!$C$3:$L$670,9,0) -> 16.5 | L29: =VLOOKUP($C29,'Master File June-26'!$C$3:$L$670,10,0) -> 0 | M29: =IFERROR((L29/I29*30),0) -> 0 | N29: =IF(M29<J29,"ORDER NOW","IN STOCK") -> ORDER NOW | O29: =IF(M29<J29,"CRITICAL","FOLLOW UP DELIVERY") -> CRITICAL | S29: =IF(L29<K29,0,1) -> 0
A30: 358 | B30: Beverage - مشروبات | C30: RM-00582 | D30: Syrup Mango Teisseireسيروب المانجو | E30: 1 Box X 6 Bottle X 1 Ltr | F30: Box | G30: 0.16666667 | H30: =VLOOKUP($C30,'Master File June-26'!$C$3:$L$670,6,0) -> 5.5 | I30: =VLOOKUP($C30,'Master File June-26'!$C$3:$L$670,7,0) -> 33 | J30: =VLOOKUP($C30,'Master File June-26'!$C$3:$L$670,8,0) -> 14 | K30: =VLOOKUP($C30,'Master File June-26'!$C$3:$L$670,9,0) -> 16.5 | L30: =VLOOKUP($C30,'Master File June-26'!$C$3:$L$670,10,0) -> 0 | M30: =IFERROR((L30/I30*30),0) -> 0 | N30: =IF(M30<J30,"ORDER NOW","IN STOCK") -> ORDER NOW | O30: =IF(M30<J30,"CRITICAL","FOLLOW UP DELIVERY") -> CRITICAL | S30: =IF(L30<K30,0,1) -> 0
A31: 401 | B31: Beverage - مشروبات / Dairy | C31: RM-00508 | D31: Condensed milkحليب مكثف | E31: 1 Box X 24 Pcs. X 1 Kilo | F31: Box | G31: 0.041666667 | H31: =VLOOKUP($C31,'Master File June-26'!$C$3:$L$670,6,0) -> 56 | I31: =VLOOKUP($C31,'Master File June-26'!$C$3:$L$670,7,0) -> 1344 | J31: =VLOOKUP($C31,'Master File June-26'!$C$3:$L$670,8,0) -> 14 | K31: =VLOOKUP($C31,'Master File June-26'!$C$3:$L$670,9,0) -> 672 | L31: =VLOOKUP($C31,'Master File June-26'!$C$3:$L$670,10,0) -> 5884.8 | M31: =IFERROR((L31/I31*30),0) -> 131.35714 | N31: =IF(M31<J31,"ORDER NOW","IN STOCK") -> IN STOCK | O31: =IF(M31<J31,"CRITICAL","FOLLOW UP DELIVERY") -> FOLLOW UP DELIVERY | S31: =IF(L31<K31,0,1) -> 1
A32: 599 | B32: Beverage - مشروبات / Dairy | C32: SF-00189 | D32: MANGO RIPPLING SAUSE - صوص المانجو مع القطع | E32: 1 Box X 2Ltr | F32: Box | G32: 0.5 | H32: =VLOOKUP($C32,'Master File June-26'!$C$3:$L$670,6,0) -> 38.5 | I32: =VLOOKUP($C32,'Master File June-26'!$C$3:$L$670,7,0) -> 77 | J32: =VLOOKUP($C32,'Master File June-26'!$C$3:$L$670,8,0) -> 14 | K32: =VLOOKUP($C32,'Master File June-26'!$C$3:$L$670,9,0) -> 38.5 | L32: =VLOOKUP($C32,'Master File June-26'!$C$3:$L$670,10,0) -> 0 | M32: =IFERROR((L32/I32*30),0) -> 0 | N32: =IF(M32<J32,"ORDER NOW","IN STOCK") -> ORDER NOW | O32: =IF(M32<J32,"CRITICAL","FOLLOW UP DELIVERY") -> CRITICAL | S32: =IF(L32<K32,0,1) -> 0
A33: 385 | B33: Beverage - مشروبات | C33: RM-00445 | D33: Kompletin Spray Oil بخاخ زيت كومبليت ان | E33: 1 Box X 6 Pcs X 500ml | F33: Box | G33: 0.33333333 | H33: =VLOOKUP($C33,'Master File June-26'!$C$3:$L$670,6,0) -> 135 | I33: =VLOOKUP($C33,'Master File June-26'!$C$3:$L$670,7,0) -> 405 | J33: =VLOOKUP($C33,'Master File June-26'!$C$3:$L$670,8,0) -> 14 | K33: =VLOOKUP($C33,'Master File June-26'!$C$3:$L$670,9,0) -> 202.5 | L33: =VLOOKUP($C33,'Master File June-26'!$C$3:$L$670,10,0) -> 1050 | M33: =IFERROR((L33/I33*30),0) -> 77.777778 | N33: =IF(M33<J33,"ORDER NOW","IN STOCK") -> IN STOCK | O33: =IF(M33<J33,"CRITICAL","FOLLOW UP DELIVERY") -> FOLLOW UP DELIVERY | S33: =IF(L33<K33,0,1) -> 1
A34: 356 | B34: Dry Goods - منتجات جافة | C34: RM-00432 | D34: Sliced almond لوز شرايح امريكي | E34: 1 Box X 10 Kg | F34: Box | G34: 0.1 | H34: =VLOOKUP($C34,'Master File June-26'!$C$3:$L$670,6,0) -> 19 | I34: =VLOOKUP($C34,'Master File June-26'!$C$3:$L$670,7,0) -> 190 | J34: =VLOOKUP($C34,'Master File June-26'!$C$3:$L$670,8,0) -> 14 | K34: =VLOOKUP($C34,'Master File June-26'!$C$3:$L$670,9,0) -> 95 | L34: =VLOOKUP($C34,'Master File June-26'!$C$3:$L$670,10,0) -> 0 | M34: =IFERROR((L34/I34*30),0) -> 0 | N34: =IF(M34<J34,"ORDER NOW","IN STOCK") -> ORDER NOW | O34: =IF(M34<J34,"CRITICAL","FOLLOW UP DELIVERY") -> CRITICAL | S34: =IF(L34<K34,0,1) -> 0
A35: 97 | B35: طباعة وتغليف - Packaging | C35: PM-00270 | D35: lids Cups Brehehant with stick اغطية اكواب القهوة - بريهانت | E35: 1 Box X 20 Pack X 50 Pcs | F35: Box | G35: 0.001 | H35: =VLOOKUP($C35,'Master File June-26'!$C$3:$L$670,6,0) -> 400 | I35: =VLOOKUP($C35,'Master File June-26'!$C$3:$L$670,7,0) -> 400000 | J35: =VLOOKUP($C35,'Master File June-26'!$C$3:$L$670,8,0) -> 14 | K35: =VLOOKUP($C35,'Master File June-26'!$C$3:$L$670,9,0) -> 200000 | L35: =VLOOKUP($C35,'Master File June-26'!$C$3:$L$670,10,0) -> 0 | M35: =IFERROR((L35/I35*30),0) -> 0 | N35: =IF(M35<J35,"ORDER NOW","IN STOCK") -> ORDER NOW | O35: =IF(M35<J35,"CRITICAL","FOLLOW UP DELIVERY") -> CRITICAL | R35: A | S35: =IF(L35<K35,0,1) -> 0
A36: 384 | B36: Dry Goods - منتجات جافة | C36: RM-00673 | D36: Valrhona Javira 40% / شوكولاته فالرهونا | E36: 1 Box X 3 x 3 KG | F36: Box | G36: =1/9 -> 0.11111111 | H36: =VLOOKUP($C36,'Master File June-26'!$C$3:$L$670,6,0) -> 22 | I36: =VLOOKUP($C36,'Master File June-26'!$C$3:$L$670,7,0) -> 198 | J36: =VLOOKUP($C36,'Master File June-26'!$C$3:$L$670,8,0) -> 14 | K36: =VLOOKUP($C36,'Master File June-26'!$C$3:$L$670,9,0) -> 99 | L36: =VLOOKUP($C36,'Master File June-26'!$C$3:$L$670,10,0) -> 0 | M36: =IFERROR((L36/I36*30),0) -> 0 | N36: =IF(M36<J36,"ORDER NOW","IN STOCK") -> ORDER NOW | O36: =IF(M36<J36,"CRITICAL","FOLLOW UP DELIVERY") -> CRITICAL | S36: =IF(L36<K36,0,1) -> 0
A37: 215 | B37: Cleaning - منظفات | C37: CO-00061 | D37: Steam cleaner 1 liter منظف الاستيم 1 لتر | E37: 1 Pcs. X 1 Ltr | F37: Pcs | G37: 1 | H37: =VLOOKUP($C37,'Master File June-26'!$C$3:$L$670,6,0) -> 233 | I37: =VLOOKUP($C37,'Master File June-26'!$C$3:$L$670,7,0) -> 233 | J37: =VLOOKUP($C37,'Master File June-26'!$C$3:$L$670,8,0) -> 14 | K37: =VLOOKUP($C37,'Master File June-26'!$C$3:$L$670,9,0) -> 116.5 | L37: =VLOOKUP($C37,'Master File June-26'!$C$3:$L$670,10,0) -> 38 | M37: =IFERROR((L37/I37*30),0) -> 4.8927039 | N37: =IF(M37<J37,"ORDER NOW","IN STOCK") -> ORDER NOW | O37: =IF(M37<J37,"CRITICAL","FOLLOW UP DELIVERY") -> CRITICAL | S37: =IF(L37<K37,0,1) -> 0
A38: 375 | B38: Beverage - مشروبات | C38: RM-00538 | D38: SYRUP LEMONADE 1883 سيروب ليموناضة | E38: 1 Box X 6 Bottle X 1 Ltr | F38: Box | G38: 0.16666667 | H38: =VLOOKUP($C38,'Master File June-26'!$C$3:$L$670,6,0) -> 16.5 | I38: =VLOOKUP($C38,'Master File June-26'!$C$3:$L$670,7,0) -> 99 | J38: =VLOOKUP($C38,'Master File June-26'!$C$3:$L$670,8,0) -> 14 | K38: =VLOOKUP($C38,'Master File June-26'!$C$3:$L$670,9,0) -> 49.5 | L38: =VLOOKUP($C38,'Master File June-26'!$C$3:$L$670,10,0) -> 99 | M38: =IFERROR((L38/I38*30),0) -> 30 | N38: =IF(M38<J38,"ORDER NOW","IN STOCK") -> IN STOCK | O38: =IF(M38<J38,"CRITICAL","FOLLOW UP DELIVERY") -> FOLLOW UP DELIVERY | S38: =IF(L38<K38,0,1) -> 1
A39: 96 | B39: طباعة وتغليف - Packaging | C39: PM-00287 | D39: lids Cups Brehehant 6.5 Oz 80 ml اغطية اكواب القهوة - بريهانت 6.5 اونصه | E39: 1 Box X 20 Pack X 50 Pcs | F39: Box | G39: 0.001 | H39: =VLOOKUP($C39,'Master File June-26'!$C$3:$L$670,6,0) -> 18 | I39: =VLOOKUP($C39,'Master File June-26'!$C$3:$L$670,7,0) -> 18000 | J39: =VLOOKUP($C39,'Master File June-26'!$C$3:$L$670,8,0) -> 14 | K39: =VLOOKUP($C39,'Master File June-26'!$C$3:$L$670,9,0) -> 9000 | L39: =VLOOKUP($C39,'Master File June-26'!$C$3:$L$670,10,0) -> 0 | M39: =IFERROR((L39/I39*30),0) -> 0 | N39: =IF(M39<J39,"ORDER NOW","IN STOCK") -> ORDER NOW | O39: =IF(M39<J39,"CRITICAL","FOLLOW UP DELIVERY") -> CRITICAL | R39: A | S39: =IF(L39<K39,0,1) -> 0
A40: 494 | B40: Dry Goods - منتجات جافة | C40: RM-00434 | D40: Walnuts عين جمل | E40: 1 Box X 10 Kg | F40: Box | G40: 0.1 | H40: =VLOOKUP($C40,'Master File June-26'!$C$3:$L$670,6,0) -> 200 | I40: =VLOOKUP($C40,'Master File June-26'!$C$3:$L$670,7,0) -> 2000 | J40: =VLOOKUP($C40,'Master File June-26'!$C$3:$L$670,8,0) -> 14 | K40: =VLOOKUP($C40,'Master File June-26'!$C$3:$L$670,9,0) -> 1000 | L40: =VLOOKUP($C40,'Master File June-26'!$C$3:$L$670,10,0) -> 0 | M40: =IFERROR((L40/I40*30),0) -> 0 | N40: =IF(M40<J40,"ORDER NOW","IN STOCK") -> ORDER NOW | O40: =IF(M40<J40,"CRITICAL","FOLLOW UP DELIVERY") -> CRITICAL | S40: =IF(L40<K40,0,1) -> 0
A41: 607 | B41: Rosted Beans | C41: FPB-00077 | D41: Costa Rica San ignacio 1 Kg | E41: KG | F41: Pcs | G41: 1 | H41: =VLOOKUP($C41,'Master File June-26'!$C$3:$L$670,6,0) -> 3410 | I41: =VLOOKUP($C41,'Master File June-26'!$C$3:$L$670,7,0) -> 3410 | J41: =VLOOKUP($C41,'Master File June-26'!$C$3:$L$670,8,0) -> 14 | K41: =VLOOKUP($C41,'Master File June-26'!$C$3:$L$670,9,0) -> 1705 | L41: =VLOOKUP($C41,'Master File June-26'!$C$3:$L$670,10,0) -> 0 | M41: =IFERROR((L41/I41*30),0) -> 0 | N41: =IF(M41<J41,"ORDER NOW","IN STOCK") -> ORDER NOW | O41: =IF(M41<J41,"CRITICAL","FOLLOW UP DELIVERY") -> CRITICAL | S41: =IF(L41<K41,0,1) -> 0
A42: 453 | B42: Dry Goods - منتجات جافة | C42: RM-00313 | D42: Vanilla bourbon فانيلا بوربون | E42: 1 Box X 12bottle X 1kg | F42: Box | G42: 0.083333333 | H42: =VLOOKUP($C42,'Master File June-26'!$C$3:$L$670,6,0) -> 250 | I42: =VLOOKUP($C42,'Master File June-26'!$C$3:$L$670,7,0) -> 3000 | J42: =VLOOKUP($C42,'Master File June-26'!$C$3:$L$670,8,0) -> 14 | K42: =VLOOKUP($C42,'Master File June-26'!$C$3:$L$670,9,0) -> 1500 | L42: =VLOOKUP($C42,'Master File June-26'!$C$3:$L$670,10,0) -> 0 | M42: =IFERROR((L42/I42*30),0) -> 0 | N42: =IF(M42<J42,"ORDER NOW","IN STOCK") -> ORDER NOW | O42: =IF(M42<J42,"CRITICAL","FOLLOW UP DELIVERY") -> CRITICAL | S42: =IF(L42<K42,0,1) -> 0
A43: 613 | B43: Rosted Beans | C43: FPB-00070 | D43: Colombia la plata 1 Kg | E43: KG | F43: Pcs | G43: 1 | H43: =VLOOKUP($C43,'Master File June-26'!$C$3:$L$670,6,0) -> 7645 | I43: =VLOOKUP($C43,'Master File June-26'!$C$3:$L$670,7,0) -> 7645 | J43: =VLOOKUP($C43,'Master File June-26'!$C$3:$L$670,8,0) -> 14 | K43: =VLOOKUP($C43,'Master File June-26'!$C$3:$L$670,9,0) -> 3822.5 | L43: =VLOOKUP($C43,'Master File June-26'!$C$3:$L$670,10,0) -> 0 | M43: =IFERROR((L43/I43*30),0) -> 0 | N43: =IF(M43<J43,"ORDER NOW","IN STOCK") -> ORDER NOW | O43: =IF(M43<J43,"CRITICAL","FOLLOW UP DELIVERY") -> CRITICAL | S43: =IF(L43<K43,0,1) -> 0
A44: 160 | B44: طباعة وتغليف - Packaging | C44: PM-00606 | D44: Round aluminum plate 110 ml with cover | صحن دائري مع غطاء 110 مل | E44: Pcs. | F44: Pcs | G44: 1 | H44: =VLOOKUP($C44,'Master File June-26'!$C$3:$L$670,6,0) -> 60000 | I44: =VLOOKUP($C44,'Master File June-26'!$C$3:$L$670,7,0) -> 60000 | J44: =VLOOKUP($C44,'Master File June-26'!$C$3:$L$670,8,0) -> 14 | K44: =VLOOKUP($C44,'Master File June-26'!$C$3:$L$670,9,0) -> 30000 | L44: =VLOOKUP($C44,'Master File June-26'!$C$3:$L$670,10,0) -> 0 | M44: =IFERROR((L44/I44*30),0) -> 0 | N44: =IF(M44<J44,"ORDER NOW","IN STOCK") -> ORDER NOW | O44: =IF(M44<J44,"CRITICAL","FOLLOW UP DELIVERY") -> CRITICAL | S44: =IF(L44<K44,0,1) -> 0
A45: 11 | B45: طباعة وتغليف - Packaging | C45: PM-00568 | D45: كيس مخبوزات مطبوع مقاس 10 × 14.5 cm (نمق)-Printed Bakery Paper Bag, 10 × 14.5 cm(Namq) | E45: 1Box X 8000 | F45: Box | G45: =1/8000 -> 0.000125 | H45: =VLOOKUP($C45,'Master File June-26'!$C$3:$L$670,6,0) -> 8 | I45: =VLOOKUP($C45,'Master File June-26'!$C$3:$L$670,7,0) -> 64000 | J45: =VLOOKUP($C45,'Master File June-26'!$C$3:$L$670,8,0) -> 14 | K45: =VLOOKUP($C45,'Master File June-26'!$C$3:$L$670,9,0) -> 32000 | L45: =VLOOKUP($C45,'Master File June-26'!$C$3:$L$670,10,0) -> 150 | M45: =IFERROR((L45/I45*30),0) -> 0.0703125 | N45: =IF(M45<J45,"ORDER NOW","IN STOCK") -> ORDER NOW | O45: =IF(M45<J45,"CRITICAL","FOLLOW UP DELIVERY") -> CRITICAL | R45: A | S45: =IF(L45<K45,0,1) -> 0
A46: 19 | B46: طباعة وتغليف - Packaging | C46: PM-00075 | D46: Nozzle Lids for Coffee Box 1 Ltr أغطية كرتون القهوة سعة 1 لتر | E46: 1Box X 400 | F46: Box | G46: 0.0025 | H46: =VLOOKUP($C46,'Master File June-26'!$C$3:$L$670,6,0) -> 0 | I46: =VLOOKUP($C46,'Master File June-26'!$C$3:$L$670,7,0) -> 0 | J46: =VLOOKUP($C46,'Master File June-26'!$C$3:$L$670,8,0) -> 14 | K46: =VLOOKUP($C46,'Master File June-26'!$C$3:$L$670,9,0) -> 0 | L46: =VLOOKUP($C46,'Master File June-26'!$C$3:$L$670,10,0) -> 0 | M46: =IFERROR((L46/I46*30),0) -> 0 | N46: =IF(M46<J46,"ORDER NOW","IN STOCK") -> ORDER NOW | O46: =IF(M46<J46,"CRITICAL","FOLLOW UP DELIVERY") -> CRITICAL | R46: B | S46: =IF(L46<K46,0,1) -> 1
A47: 29 | B47: طباعة وتغليف - Packaging | C47: PM-00563 | D47: Paper Cup Surprise 16 oz - Outer كوب ورقي للمفاجأة 16 أونص نمق | E47: 1 Box X 1000 Pcs. | F47: Box | G47: =1/1000 -> 0.001 | H47: =VLOOKUP($C47,'Master File June-26'!$C$3:$L$670,6,0) -> 0 | I47: =VLOOKUP($C47,'Master File June-26'!$C$3:$L$670,7,0) -> 0 | J47: =VLOOKUP($C47,'Master File June-26'!$C$3:$L$670,8,0) -> 60 | K47: =VLOOKUP($C47,'Master File June-26'!$C$3:$L$670,9,0) -> 0 | L47: =VLOOKUP($C47,'Master File June-26'!$C$3:$L$670,10,0) -> 0 | M47: =IFERROR((L47/I47*30),0) -> 0 | N47: =IF(M47<J47,"ORDER NOW","IN STOCK") -> ORDER NOW | O47: =IF(M47<J47,"CRITICAL","FOLLOW UP DELIVERY") -> CRITICAL | R47: B | S47: =IF(L47<K47,0,1) -> 1
A48: 46 | B48: طباعة وتغليف - Packaging | C48: PM-00436 | D48: استيكر هوت شوكلت Hot chocolate sticker | F48: Box | G48: 1 | H48: =VLOOKUP($C48,'Master File June-26'!$C$3:$L$670,6,0) -> 5.5 | I48: =VLOOKUP($C48,'Master File June-26'!$C$3:$L$670,7,0) -> 5.5 | J48: =VLOOKUP($C48,'Master File June-26'!$C$3:$L$670,8,0) -> 14 | K48: =VLOOKUP($C48,'Master File June-26'!$C$3:$L$670,9,0) -> 2.75 | L48: =VLOOKUP($C48,'Master File June-26'!$C$3:$L$670,10,0) -> 0 | M48: =IFERROR((L48/I48*30),0) -> 0 | N48: =IF(M48<J48,"ORDER NOW","IN STOCK") -> ORDER NOW | O48: =IF(M48<J48,"CRITICAL","FOLLOW UP DELIVERY") -> CRITICAL | R48: A | S48: =IF(L48<K48,0,1) -> 0
A49: 49 | B49: طباعة وتغليف - Packaging | C49: PM-00230 | D49: Cafec V60 Filter 01 Coffee Filter كافيك فلاتر ترشيح ورقية - مقاس 01 | E49: 1 Box X 80 Case X 100 PCS | F49: Box | G49: =1/8000 -> 0.000125 | H49: =VLOOKUP($C49,'Master File June-26'!$C$3:$L$670,6,0) -> 0 | I49: =VLOOKUP($C49,'Master File June-26'!$C$3:$L$670,7,0) -> 0 | J49: =VLOOKUP($C49,'Master File June-26'!$C$3:$L$670,8,0) -> 14 | K49: =VLOOKUP($C49,'Master File June-26'!$C$3:$L$670,9,0) -> 0 | L49: =VLOOKUP($C49,'Master File June-26'!$C$3:$L$670,10,0) -> 8000 | M49: =IFERROR((L49/I49*30),0) -> 0 | N49: =IF(M49<J49,"ORDER NOW","IN STOCK") -> ORDER NOW | O49: =IF(M49<J49,"CRITICAL","FOLLOW UP DELIVERY") -> CRITICAL | R49: A | S49: =IF(L49<K49,0,1) -> 1
A50: 50 | B50: Consumables | C50: PM-00240 | D50: Cold Brew Filter فلتر كولد برو خفيف | E50: 1 Pcs | F50: Pcs | G50: 1 | H50: =VLOOKUP($C50,'Master File June-26'!$C$3:$L$670,6,0) -> 44 | I50: =VLOOKUP($C50,'Master File June-26'!$C$3:$L$670,7,0) -> 44 | J50: =VLOOKUP($C50,'Master File June-26'!$C$3:$L$670,8,0) -> 14 | K50: =VLOOKUP($C50,'Master File June-26'!$C$3:$L$670,9,0) -> 22 | L50: =VLOOKUP($C50,'Master File June-26'!$C$3:$L$670,10,0) -> 0 | M50: =IFERROR((L50/I50*30),0) -> 0 | N50: =IF(M50<J50,"ORDER NOW","IN STOCK") -> ORDER NOW | O50: =IF(M50<J50,"CRITICAL","FOLLOW UP DELIVERY") -> CRITICAL | R50: A | S50: =IF(L50<K50,0,1) -> 0
A51: 59 | B51: طباعة وتغليف - Packaging | C51: PM-00530 | D51: كوب فخار 300 مل - محفور عليه شعار من الداخل والخارج - قليز شفاف مطفي - STONEWARE | E51: Pcs. | F51: Pcs | G51: 1 | H51: =VLOOKUP($C51,'Master File June-26'!$C$3:$L$670,6,0) -> 40 | I51: =VLOOKUP($C51,'Master File June-26'!$C$3:$L$670,7,0) -> 40 | J51: =VLOOKUP($C51,'Master File June-26'!$C$3:$L$670,8,0) -> 30 | K51: =VLOOKUP($C51,'Master File June-26'!$C$3:$L$670,9,0) -> 42.857143 | L51: =VLOOKUP($C51,'Master File June-26'!$C$3:$L$670,10,0) -> 0 | M51: =IFERROR((L51/I51*30),0) -> 0 | N51: =IF(M51<J51,"ORDER NOW","IN STOCK") -> ORDER NOW | O51: =IF(M51<J51,"CRITICAL","FOLLOW UP DELIVERY") -> CRITICAL | R51: A | S51: =IF(L51<K51,0,1) -> 0
A52: 60 | B52: طباعة وتغليف - Packaging | C52: PM-00534 | D52: صحن فخار مقاس 20*20*15 محفور عليه الشعار في المنتصف | E52: Pcs. | F52: Pcs | G52: 1 | H52: =VLOOKUP($C52,'Master File June-26'!$C$3:$L$670,6,0) -> 10 | I52: =VLOOKUP($C52,'Master File June-26'!$C$3:$L$670,7,0) -> 10 | J52: =VLOOKUP($C52,'Master File June-26'!$C$3:$L$670,8,0) -> 30 | K52: =VLOOKUP($C52,'Master File June-26'!$C$3:$L$670,9,0) -> 10.714286 | L52: =VLOOKUP($C52,'Master File June-26'!$C$3:$L$670,10,0) -> 0 | M52: =IFERROR((L52/I52*30),0) -> 0 | N52: =IF(M52<J52,"ORDER NOW","IN STOCK") -> ORDER NOW | O52: =IF(M52<J52,"CRITICAL","FOLLOW UP DELIVERY") -> CRITICAL | R52: A | S52: =IF(L52<K52,0,1) -> 0
A53: 65 | B53: طباعة وتغليف - Packaging | C53: PM-00295 | D53: Customer Evaluation Card كرت تقييم العملاء ( نمق ) | E53: 1 Box X 1000 | F53: Box | G53: 0.001 | H53: =VLOOKUP($C53,'Master File June-26'!$C$3:$L$670,6,0) -> 0 | I53: =VLOOKUP($C53,'Master File June-26'!$C$3:$L$670,7,0) -> 0 | J53: =VLOOKUP($C53,'Master File June-26'!$C$3:$L$670,8,0) -> 14 | K53: =VLOOKUP($C53,'Master File June-26'!$C$3:$L$670,9,0) -> 0 | L53: =VLOOKUP($C53,'Master File June-26'!$C$3:$L$670,10,0) -> 0 | M53: =IFERROR((L53/I53*30),0) -> 0 | N53: =IF(M53<J53,"ORDER NOW","IN STOCK") -> ORDER NOW | O53: =IF(M53<J53,"CRITICAL","FOLLOW UP DELIVERY") -> CRITICAL | R53: A | S53: =IF(L53<K53,0,1) -> 1
A54: 66 | B54: طباعة وتغليف - Packaging | C54: PM-00276 | D54: Tape شطرطون | E54: 1 Box X 24 Pcs | F54: Box | G54: 0.041666667 | H54: =VLOOKUP($C54,'Master File June-26'!$C$3:$L$670,6,0) -> 5.5 | I54: =VLOOKUP($C54,'Master File June-26'!$C$3:$L$670,7,0) -> 132 | J54: =VLOOKUP($C54,'Master File June-26'!$C$3:$L$670,8,0) -> 14 | K54: =VLOOKUP($C54,'Master File June-26'!$C$3:$L$670,9,0) -> 66 | L54: =VLOOKUP($C54,'Master File June-26'!$C$3:$L$670,10,0) -> 0 | M54: =IFERROR((L54/I54*30),0) -> 0 | N54: =IF(M54<J54,"ORDER NOW","IN STOCK") -> ORDER NOW | O54: =IF(M54<J54,"CRITICAL","FOLLOW UP DELIVERY") -> CRITICAL | R54: A | S54: =IF(L54<K54,0,1) -> 0
A55: 69 | B55: طباعة وتغليف - Packaging | C55: PM-00448 | D55: Sticker Date ستيكر التاريخ | G55: 1 | H55: =VLOOKUP($C55,'Master File June-26'!$C$3:$L$670,6,0) -> 5.5 | I55: =VLOOKUP($C55,'Master File June-26'!$C$3:$L$670,7,0) -> 5.5 | J55: =VLOOKUP($C55,'Master File June-26'!$C$3:$L$670,8,0) -> 14 | K55: =VLOOKUP($C55,'Master File June-26'!$C$3:$L$670,9,0) -> 2.75 | L55: =VLOOKUP($C55,'Master File June-26'!$C$3:$L$670,10,0) -> 0 | M55: =IFERROR((L55/I55*30),0) -> 0 | N55: =IF(M55<J55,"ORDER NOW","IN STOCK") -> ORDER NOW | O55: =IF(M55<J55,"CRITICAL","FOLLOW UP DELIVERY") -> CRITICAL | R55: A | S55: =IF(L55<K55,0,1) -> 0
A56: 72 | B56: طباعة وتغليف - Packaging | C56: PM-00341 | D56: Point of sale roll - رول نقاط البيع | E56: 1 Box X 50 Pcs | F56: Box | G56: =1/50 -> 0.02 | H56: =VLOOKUP($C56,'Master File June-26'!$C$3:$L$670,6,0) -> 11 | I56: =VLOOKUP($C56,'Master File June-26'!$C$3:$L$670,7,0) -> 550 | J56: =VLOOKUP($C56,'Master File June-26'!$C$3:$L$670,8,0) -> 14 | K56: =VLOOKUP($C56,'Master File June-26'!$C$3:$L$670,9,0) -> 275 | L56: =VLOOKUP($C56,'Master File June-26'!$C$3:$L$670,10,0) -> 0 | M56: =IFERROR((L56/I56*30),0) -> 0 | N56: =IF(M56<J56,"ORDER NOW","IN STOCK") -> ORDER NOW | O56: =IF(M56<J56,"CRITICAL","FOLLOW UP DELIVERY") -> CRITICAL | R56: A | S56: =IF(L56<K56,0,1) -> 0
A57: 90 | B57: طباعة وتغليف - Packaging | C57: PM-00182 | D57: Breehant Paper cup 6.5 OZ كوب ورقي 6.5 اونص بريهانت | E57: 1 Box 20 Pack X 25 Pcs | F57: Box | G57: 0.002 | H57: =VLOOKUP($C57,'Master File June-26'!$C$3:$L$670,6,0) -> 150 | I57: =VLOOKUP($C57,'Master File June-26'!$C$3:$L$670,7,0) -> 75000 | J57: =VLOOKUP($C57,'Master File June-26'!$C$3:$L$670,8,0) -> 14 | K57: =VLOOKUP($C57,'Master File June-26'!$C$3:$L$670,9,0) -> 37500 | L57: =VLOOKUP($C57,'Master File June-26'!$C$3:$L$670,10,0) -> 3500 | M57: =IFERROR((L57/I57*30),0) -> 1.4 | N57: =IF(M57<J57,"ORDER NOW","IN STOCK") -> ORDER NOW | O57: =IF(M57<J57,"CRITICAL","FOLLOW UP DELIVERY") -> CRITICAL | R57: A | S57: =IF(L57<K57,0,1) -> 0
A58: 95 | B58: طباعة وتغليف - Packaging | C58: PM-00201 | D58: Season Paper cup Double 9 Oz ( BREEHANT ) كوب ورقي 9 اونصه تصميم موسمي ( بريهانت ) | E58: 1 Box X 1000 Pcs | F58: Box | G58: 0.001 | H58: =VLOOKUP($C58,'Master File June-26'!$C$3:$L$670,6,0) -> 0 | I58: =VLOOKUP($C58,'Master File June-26'!$C$3:$L$670,7,0) -> 0 | J58: =VLOOKUP($C58,'Master File June-26'!$C$3:$L$670,8,0) -> 14 | K58: =VLOOKUP($C58,'Master File June-26'!$C$3:$L$670,9,0) -> 0 | L58: =VLOOKUP($C58,'Master File June-26'!$C$3:$L$670,10,0) -> 0 | M58: =IFERROR((L58/I58*30),0) -> 0 | N58: =IF(M58<J58,"ORDER NOW","IN STOCK") -> ORDER NOW | O58: =IF(M58<J58,"CRITICAL","FOLLOW UP DELIVERY") -> CRITICAL | R58: B | S58: =IF(L58<K58,0,1) -> 1
A59: 107 | B59: طباعة وتغليف - Packaging | C59: PM-00268 | D59: Breehant CANSعلبة بريهانت الباردة | E59: 1 Box X 200 Pcs | F59: Box | G59: 0.005 | H59: =VLOOKUP($C59,'Master File June-26'!$C$3:$L$670,6,0) -> 25 | I59: =VLOOKUP($C59,'Master File June-26'!$C$3:$L$670,7,0) -> 5000 | J59: =VLOOKUP($C59,'Master File June-26'!$C$3:$L$670,8,0) -> 14 | K59: =VLOOKUP($C59,'Master File June-26'!$C$3:$L$670,9,0) -> 2500 | L59: =VLOOKUP($C59,'Master File June-26'!$C$3:$L$670,10,0) -> 0 | M59: =IFERROR((L59/I59*30),0) -> 0 | N59: =IF(M59<J59,"ORDER NOW","IN STOCK") -> ORDER NOW | O59: =IF(M59<J59,"CRITICAL","FOLLOW UP DELIVERY") -> CRITICAL | R59: A | S59: =IF(L59<K59,0,1) -> 0
A60: 108 | B60: طباعة وتغليف - Packaging | C60: PM-00285 | D60: Breehant card rating كرت التقييم بريهانت | E60: 1 Box X 500 Pcs | F60: Box | G60: 0.002 | H60: =VLOOKUP($C60,'Master File June-26'!$C$3:$L$670,6,0) -> 16 | I60: =VLOOKUP($C60,'Master File June-26'!$C$3:$L$670,7,0) -> 8000 | J60: =VLOOKUP($C60,'Master File June-26'!$C$3:$L$670,8,0) -> 14 | K60: =VLOOKUP($C60,'Master File June-26'!$C$3:$L$670,9,0) -> 4000 | L60: =VLOOKUP($C60,'Master File June-26'!$C$3:$L$670,10,0) -> 1000 | M60: =IFERROR((L60/I60*30),0) -> 3.75 | N60: =IF(M60<J60,"ORDER NOW","IN STOCK") -> ORDER NOW | O60: =IF(M60<J60,"CRITICAL","FOLLOW UP DELIVERY") -> CRITICAL | R60: A | S60: =IF(L60<K60,0,1) -> 0
A61: 112 | B61: طباعة وتغليف - Packaging | C61: PM-00369 | D61: Saudi coffee sticker roll رول استيكر القهوه السعوديه | E61: 1 Box X 1000 Pcs | F61: Box | G61: =1/1000 -> 0.001 | H61: =VLOOKUP($C61,'Master File June-26'!$C$3:$L$670,6,0) -> 15 | I61: =VLOOKUP($C61,'Master File June-26'!$C$3:$L$670,7,0) -> 15000 | J61: =VLOOKUP($C61,'Master File June-26'!$C$3:$L$670,8,0) -> 14 | K61: =VLOOKUP($C61,'Master File June-26'!$C$3:$L$670,9,0) -> 7500 | L61: =VLOOKUP($C61,'Master File June-26'!$C$3:$L$670,10,0) -> 0 | M61: =IFERROR((L61/I61*30),0) -> 0 | N61: =IF(M61<J61,"ORDER NOW","IN STOCK") -> ORDER NOW | O61: =IF(M61<J61,"CRITICAL","FOLLOW UP DELIVERY") -> CRITICAL | R61: A | S61: =IF(L61<K61,0,1) -> 0
A62: 116 | B62: طباعة وتغليف - Packaging | C62: PM-00445 | D62: Caramel Bites Sticker Bar (Nmaq) ستيكر بار كراميل بايتس ( نمق ) | E62: 1 Roll X 1000 Pcs. | F62: Box | G62: 0.001 | H62: =VLOOKUP($C62,'Master File June-26'!$C$3:$L$670,6,0) -> 8 | I62: =VLOOKUP($C62,'Master File June-26'!$C$3:$L$670,7,0) -> 8000 | J62: =VLOOKUP($C62,'Master File June-26'!$C$3:$L$670,8,0) -> 14 | K62: =VLOOKUP($C62,'Master File June-26'!$C$3:$L$670,9,0) -> 4000 | L62: =VLOOKUP($C62,'Master File June-26'!$C$3:$L$670,10,0) -> 0 | M62: =IFERROR((L62/I62*30),0) -> 0 | N62: =IF(M62<J62,"ORDER NOW","IN STOCK") -> ORDER NOW | O62: =IF(M62<J62,"CRITICAL","FOLLOW UP DELIVERY") -> CRITICAL | R62: A | S62: =IF(L62<K62,0,1) -> 0
A63: 123 | B63: طباعة وتغليف - Packaging | C63: PM-00080 | D63: Bar Box (NAMQ)بوكس البارات (نمق) | E63: 1 bundle X 500 PCS | F63: bundel | G63: 0.002 | H63: =VLOOKUP($C63,'Master File June-26'!$C$3:$L$670,6,0) -> 15 | I63: =VLOOKUP($C63,'Master File June-26'!$C$3:$L$670,7,0) -> 7500 | J63: =VLOOKUP($C63,'Master File June-26'!$C$3:$L$670,8,0) -> 14 | K63: =VLOOKUP($C63,'Master File June-26'!$C$3:$L$670,9,0) -> 3750 | L63: =VLOOKUP($C63,'Master File June-26'!$C$3:$L$670,10,0) -> 0 | M63: =IFERROR((L63/I63*30),0) -> 0 | N63: =IF(M63<J63,"ORDER NOW","IN STOCK") -> ORDER NOW | O63: =IF(M63<J63,"CRITICAL","FOLLOW UP DELIVERY") -> CRITICAL | R63: A | S63: =IF(L63<K63,0,1) -> 0
A64: 127 | B64: طباعة وتغليف - Packaging | C64: PM-00076 | D64: Salted caramel box بوكس كراميل مملح | E64: 1 bundle X 100 PCS | F64: bundel | G64: 0.01 | H64: =VLOOKUP($C64,'Master File June-26'!$C$3:$L$670,6,0) -> 300 | I64: =VLOOKUP($C64,'Master File June-26'!$C$3:$L$670,7,0) -> 30000 | J64: =VLOOKUP($C64,'Master File June-26'!$C$3:$L$670,8,0) -> 14 | K64: =VLOOKUP($C64,'Master File June-26'!$C$3:$L$670,9,0) -> 15000 | L64: =VLOOKUP($C64,'Master File June-26'!$C$3:$L$670,10,0) -> 0 | M64: =IFERROR((L64/I64*30),0) -> 0 | N64: =IF(M64<J64,"ORDER NOW","IN STOCK") -> ORDER NOW | O64: =IF(M64<J64,"CRITICAL","FOLLOW UP DELIVERY") -> CRITICAL | R64: A | S64: =IF(L64<K64,0,1) -> 0
A65: 129 | B65: طباعة وتغليف - Packaging | C65: PM-00105 | D65: Crunchy Chocolate box (BREEHANT) بوكس كرانشي شوكلت ( بريهانت ) | E65: 1 Box X 200 Pcs | F65: Box | G65: =1/200 -> 0.005 | H65: =VLOOKUP($C65,'Master File June-26'!$C$3:$L$670,6,0) -> 50 | I65: =VLOOKUP($C65,'Master File June-26'!$C$3:$L$670,7,0) -> 10000 | J65: =VLOOKUP($C65,'Master File June-26'!$C$3:$L$670,8,0) -> 14 | K65: =VLOOKUP($C65,'Master File June-26'!$C$3:$L$670,9,0) -> 5000 | L65: =VLOOKUP($C65,'Master File June-26'!$C$3:$L$670,10,0) -> 0 | M65: =IFERROR((L65/I65*30),0) -> 0 | N65: =IF(M65<J65,"ORDER NOW","IN STOCK") -> ORDER NOW | O65: =IF(M65<J65,"CRITICAL","FOLLOW UP DELIVERY") -> CRITICAL | R65: A | S65: =IF(L65<K65,0,1) -> 0
A66: 136 | B66: طباعة وتغليف - Packaging | C66: PM-00330 | D66: Transfer Chocolate Paper ( Breehant ) ورق ترانسفير التشوكلت ( بريهانت ) | E66: 1 Bundle X 50 Pcs. | F66: bundel | G66: 0.02 | H66: =VLOOKUP($C66,'Master File June-26'!$C$3:$L$670,6,0) -> 0 | I66: =VLOOKUP($C66,'Master File June-26'!$C$3:$L$670,7,0) -> 0 | J66: =VLOOKUP($C66,'Master File June-26'!$C$3:$L$670,8,0) -> 14 | K66: =VLOOKUP($C66,'Master File June-26'!$C$3:$L$670,9,0) -> 0 | L66: =VLOOKUP($C66,'Master File June-26'!$C$3:$L$670,10,0) -> 0 | M66: =IFERROR((L66/I66*30),0) -> 0 | N66: =IF(M66<J66,"ORDER NOW","IN STOCK") -> ORDER NOW | O66: =IF(M66<J66,"CRITICAL","FOLLOW UP DELIVERY") -> CRITICAL | R66: A | S66: =IF(L66<K66,0,1) -> 1
A67: 144 | B67: طباعة وتغليف - Packaging | C67: PM-00688 | D67: سليف مارشميلو كراميل||Marshmallow Caramel Sleeve | E67: Pcs | F67: Pcs | G67: 1 | H67: =VLOOKUP($C67,'Master File June-26'!$C$3:$L$670,6,0) -> 0 | I67: =VLOOKUP($C67,'Master File June-26'!$C$3:$L$670,7,0) -> 200 | J67: =VLOOKUP($C67,'Master File June-26'!$C$3:$L$670,8,0) -> 14 | K67: =VLOOKUP($C67,'Master File June-26'!$C$3:$L$670,9,0) -> 100 | L67: =VLOOKUP($C67,'Master File June-26'!$C$3:$L$670,10,0) -> 0 | M67: =IFERROR((L67/I67*30),0) -> 0 | N67: =IF(M67<J67,"ORDER NOW","IN STOCK") -> ORDER NOW | O67: =IF(M67<J67,"CRITICAL","FOLLOW UP DELIVERY") -> CRITICAL | R67: A | S67: =IF(L67<K67,0,1) -> 0
A68: 145 | B68: طباعة وتغليف - Packaging | C68: PM-00687 | D68: سليف مارشميلو كرانشي||Marshmallow Crunchy Sleeve | E68: Pcs | F68: Pcs | G68: 1 | H68: =VLOOKUP($C68,'Master File June-26'!$C$3:$L$670,6,0) -> 0 | I68: =VLOOKUP($C68,'Master File June-26'!$C$3:$L$670,7,0) -> 200 | J68: =VLOOKUP($C68,'Master File June-26'!$C$3:$L$670,8,0) -> 14 | K68: =VLOOKUP($C68,'Master File June-26'!$C$3:$L$670,9,0) -> 100 | L68: =VLOOKUP($C68,'Master File June-26'!$C$3:$L$670,10,0) -> 0 | M68: =IFERROR((L68/I68*30),0) -> 0 | N68: =IF(M68<J68,"ORDER NOW","IN STOCK") -> ORDER NOW | O68: =IF(M68<J68,"CRITICAL","FOLLOW UP DELIVERY") -> CRITICAL | R68: A | S68: =IF(L68<K68,0,1) -> 0
A69: 150 | B69: طباعة وتغليف - Packaging | C69: PM-00038 | D69: Tiramisu Cover (breehant) غلاف تيراميسو (بريهانت) | E69: 1 Bundle X 500 PCS | F69: bundel | G69: =1/500 -> 0.002 | H69: =VLOOKUP($C69,'Master File June-26'!$C$3:$L$670,6,0) -> 6 | I69: =VLOOKUP($C69,'Master File June-26'!$C$3:$L$670,7,0) -> 3000 | J69: =VLOOKUP($C69,'Master File June-26'!$C$3:$L$670,8,0) -> 14 | K69: =VLOOKUP($C69,'Master File June-26'!$C$3:$L$670,9,0) -> 1500 | L69: =VLOOKUP($C69,'Master File June-26'!$C$3:$L$670,10,0) -> 0 | M69: =IFERROR((L69/I69*30),0) -> 0 | N69: =IF(M69<J69,"ORDER NOW","IN STOCK") -> ORDER NOW | O69: =IF(M69<J69,"CRITICAL","FOLLOW UP DELIVERY") -> CRITICAL | R69: A | S69: =IF(L69<K69,0,1) -> 0
A70: 155 | B70: طباعة وتغليف - Packaging | C70: PM-00339 | D70: ورق ترانسفير الكوكيز مقاس 10سم (نمق)Transfer cookies Paper(NAMQ ) | E70: 1 Box X 750 Sheet | F70: Box | G70: 0.0013333333 | H70: =VLOOKUP($C70,'Master File June-26'!$C$3:$L$670,6,0) -> 28 | I70: =VLOOKUP($C70,'Master File June-26'!$C$3:$L$670,7,0) -> 21000 | J70: =VLOOKUP($C70,'Master File June-26'!$C$3:$L$670,8,0) -> 14 | K70: =VLOOKUP($C70,'Master File June-26'!$C$3:$L$670,9,0) -> 10500 | L70: =VLOOKUP($C70,'Master File June-26'!$C$3:$L$670,10,0) -> 0 | M70: =IFERROR((L70/I70*30),0) -> 0 | N70: =IF(M70<J70,"ORDER NOW","IN STOCK") -> ORDER NOW | O70: =IF(M70<J70,"CRITICAL","FOLLOW UP DELIVERY") -> CRITICAL | S70: =IF(L70<K70,0,1) -> 0
A71: 156 | B71: طباعة وتغليف - Packaging | C71: PM-00627 | D71: ورق زبدة بني 22سم دائري-Brown baking paper, 22 cm, round | G71: 1 | H71: =VLOOKUP($C71,'Master File June-26'!$C$3:$L$670,6,0) -> 15000 | I71: =VLOOKUP($C71,'Master File June-26'!$C$3:$L$670,7,0) -> 15000 | J71: =VLOOKUP($C71,'Master File June-26'!$C$3:$L$670,8,0) -> 14 | K71: =VLOOKUP($C71,'Master File June-26'!$C$3:$L$670,9,0) -> 7500 | L71: =VLOOKUP($C71,'Master File June-26'!$C$3:$L$670,10,0) -> 0 | M71: =IFERROR((L71/I71*30),0) -> 0 | N71: =IF(M71<J71,"ORDER NOW","IN STOCK") -> ORDER NOW | O71: =IF(M71<J71,"CRITICAL","FOLLOW UP DELIVERY") -> CRITICAL | S71: =IF(L71<K71,0,1) -> 0
A72: 157 | B72: طباعة وتغليف - Packaging | C72: PM-00347 | D72: ورق ترانسفير الكوكيز مقاس 10سم (بريهانت)Transfer cookies Paper(BREEHANT ) | E72: Sheet 25pcs | F72: Pcs | G72: =1/25 -> 0.04 | H72: =VLOOKUP($C72,'Master File June-26'!$C$3:$L$670,6,0) -> 400 | I72: =VLOOKUP($C72,'Master File June-26'!$C$3:$L$670,7,0) -> 10000 | J72: =VLOOKUP($C72,'Master File June-26'!$C$3:$L$670,8,0) -> 14 | K72: =VLOOKUP($C72,'Master File June-26'!$C$3:$L$670,9,0) -> 5000 | L72: =VLOOKUP($C72,'Master File June-26'!$C$3:$L$670,10,0) -> 0 | M72: =IFERROR((L72/I72*30),0) -> 0 | N72: =IF(M72<J72,"ORDER NOW","IN STOCK") -> ORDER NOW | O72: =IF(M72<J72,"CRITICAL","FOLLOW UP DELIVERY") -> CRITICAL | S72: =IF(L72<K72,0,1) -> 0
A73: 158 | B73: Consumables | C73: PM-00281 | D73: Roll packing machine رول مكينة تغليف | E73: Pcs. | F73: Pcs | G73: 1 | H73: =VLOOKUP($C73,'Master File June-26'!$C$3:$L$670,6,0) -> 80 | I73: =VLOOKUP($C73,'Master File June-26'!$C$3:$L$670,7,0) -> 80 | J73: =VLOOKUP($C73,'Master File June-26'!$C$3:$L$670,8,0) -> 14 | K73: =VLOOKUP($C73,'Master File June-26'!$C$3:$L$670,9,0) -> 40 | L73: =VLOOKUP($C73,'Master File June-26'!$C$3:$L$670,10,0) -> 0 | M73: =IFERROR((L73/I73*30),0) -> 0 | N73: =IF(M73<J73,"ORDER NOW","IN STOCK") -> ORDER NOW | O73: =IF(M73<J73,"CRITICAL","FOLLOW UP DELIVERY") -> CRITICAL | S73: =IF(L73<K73,0,1) -> 0
A74: 159 | B74: طباعة وتغليف - Packaging | C74: PM-00648 | D74: صحن ألمنيوم دائري 25-4 | Round aluminum plate | E74: Pcs | F74: Pcs | G74: 1 | H74: =VLOOKUP($C74,'Master File June-26'!$C$3:$L$670,6,0) -> 3 | I74: =VLOOKUP($C74,'Master File June-26'!$C$3:$L$670,7,0) -> 0 | J74: =VLOOKUP($C74,'Master File June-26'!$C$3:$L$670,8,0) -> 14 | K74: =VLOOKUP($C74,'Master File June-26'!$C$3:$L$670,9,0) -> 0 | L74: =VLOOKUP($C74,'Master File June-26'!$C$3:$L$670,10,0) -> 0 | M74: =IFERROR((L74/I74*30),0) -> 0 | N74: =IF(M74<J74,"ORDER NOW","IN STOCK") -> ORDER NOW | O74: =IF(M74<J74,"CRITICAL","FOLLOW UP DELIVERY") -> CRITICAL | S74: =IF(L74<K74,0,1) -> 1
A75: 170 | B75: طباعة وتغليف - Packaging | C75: PM-00643 | D75: Pudding box 12 oz.(Breehant)-علبة بودنق 12 أونص (بريهانت) | E75: 1 Box X 150 | F75: Box | G75: 0.0066666667 | H75: =VLOOKUP($C75,'Master File June-26'!$C$3:$L$670,6,0) -> 50 | I75: =VLOOKUP($C75,'Master File June-26'!$C$3:$L$670,7,0) -> 7500 | J75: =VLOOKUP($C75,'Master File June-26'!$C$3:$L$670,8,0) -> 14 | K75: =VLOOKUP($C75,'Master File June-26'!$C$3:$L$670,9,0) -> 3750 | L75: =VLOOKUP($C75,'Master File June-26'!$C$3:$L$670,10,0) -> 0 | M75: =IFERROR((L75/I75*30),0) -> 0 | N75: =IF(M75<J75,"ORDER NOW","IN STOCK") -> ORDER NOW | O75: =IF(M75<J75,"CRITICAL","FOLLOW UP DELIVERY") -> CRITICAL | S75: =IF(L75<K75,0,1) -> 0
A76: 177 | B76: طباعة وتغليف - Packaging | C76: PM-00036 | D76: HD BAG PRINTED 2+2 COLORS SIZE كيس التاندو مطبوع | E76: Box | F76: Box | G76: 0.003125 | H76: =VLOOKUP($C76,'Master File June-26'!$C$3:$L$670,6,0) -> 10 | I76: =VLOOKUP($C76,'Master File June-26'!$C$3:$L$670,7,0) -> 3200 | J76: =VLOOKUP($C76,'Master File June-26'!$C$3:$L$670,8,0) -> 14 | K76: =VLOOKUP($C76,'Master File June-26'!$C$3:$L$670,9,0) -> 1600 | L76: =VLOOKUP($C76,'Master File June-26'!$C$3:$L$670,10,0) -> 0 | M76: =IFERROR((L76/I76*30),0) -> 0 | N76: =IF(M76<J76,"ORDER NOW","IN STOCK") -> ORDER NOW | O76: =IF(M76<J76,"CRITICAL","FOLLOW UP DELIVERY") -> CRITICAL | S76: =IF(L76<K76,0,1) -> 0
A77: 183 | B77: طباعة وتغليف - Packaging | C77: PM-00697 | D77: استيكر اغلاق بوكس فطورات كبير|| large breakfast box closure sticker | E77: Pcs | F77: Pcs | G77: 1 | H77: =VLOOKUP($C77,'Master File June-26'!$C$3:$L$670,6,0) -> 5000 | I77: =VLOOKUP($C77,'Master File June-26'!$C$3:$L$670,7,0) -> 5000 | J77: =VLOOKUP($C77,'Master File June-26'!$C$3:$L$670,8,0) -> 14 | K77: =VLOOKUP($C77,'Master File June-26'!$C$3:$L$670,9,0) -> 2500 | L77: =VLOOKUP($C77,'Master File June-26'!$C$3:$L$670,10,0) -> 0 | M77: =IFERROR((L77/I77*30),0) -> 0 | N77: =IF(M77<J77,"ORDER NOW","IN STOCK") -> ORDER NOW | O77: =IF(M77<J77,"CRITICAL","FOLLOW UP DELIVERY") -> CRITICAL | S77: =IF(L77<K77,0,1) -> 0
A78: 184 | B78: طباعة وتغليف - Packaging | C78: PM-00696 | D78: استيكر اغلاق بوكس فطورات صغير|| small breakfast box closure sticker | E78: Pcs | F78: Pcs | G78: 1 | H78: =VLOOKUP($C78,'Master File June-26'!$C$3:$L$670,6,0) -> 5000 | I78: =VLOOKUP($C78,'Master File June-26'!$C$3:$L$670,7,0) -> 5000 | J78: =VLOOKUP($C78,'Master File June-26'!$C$3:$L$670,8,0) -> 14 | K78: =VLOOKUP($C78,'Master File June-26'!$C$3:$L$670,9,0) -> 2500 | L78: =VLOOKUP($C78,'Master File June-26'!$C$3:$L$670,10,0) -> 0 | M78: =IFERROR((L78/I78*30),0) -> 0 | N78: =IF(M78<J78,"ORDER NOW","IN STOCK") -> ORDER NOW | O78: =IF(M78<J78,"CRITICAL","FOLLOW UP DELIVERY") -> CRITICAL | S78: =IF(L78<K78,0,1) -> 0
A79: 185 | B79: طباعة وتغليف - Packaging | C79: CO-00471 | D79: كوب سراميك 110ملي لتقديم الاسبريسو لون وردي مع بيج (نمق)Ceramic cup, 110 ml, for serving espresso pink and beige color | E79: 1 Pcs | F79: Pcs | G79: 1 | H79: =VLOOKUP($C79,'Master File June-26'!$C$3:$L$670,6,0) -> 0 | I79: =VLOOKUP($C79,'Master File June-26'!$C$3:$L$670,7,0) -> 0 | J79: =VLOOKUP($C79,'Master File June-26'!$C$3:$L$670,8,0) -> 14 | K79: =VLOOKUP($C79,'Master File June-26'!$C$3:$L$670,9,0) -> 0 | L79: =VLOOKUP($C79,'Master File June-26'!$C$3:$L$670,10,0) -> 0 | M79: =IFERROR((L79/I79*30),0) -> 0 | N79: =IF(M79<J79,"ORDER NOW","IN STOCK") -> ORDER NOW | O79: =IF(M79<J79,"CRITICAL","FOLLOW UP DELIVERY") -> CRITICAL | S79: =IF(L79<K79,0,1) -> 1
A80: 188 | B80: طباعة وتغليف - Packaging | C80: CO-00393 | D80: Brother Label Maker Printer - طابعه ملصقات | E80: Pcs. | F80: Pcs | G80: 1 | H80: =VLOOKUP($C80,'Master File June-26'!$C$3:$L$670,6,0) -> 11 | I80: =VLOOKUP($C80,'Master File June-26'!$C$3:$L$670,7,0) -> 0 | J80: =VLOOKUP($C80,'Master File June-26'!$C$3:$L$670,8,0) -> 14 | K80: =VLOOKUP($C80,'Master File June-26'!$C$3:$L$670,9,0) -> 0 | L80: =VLOOKUP($C80,'Master File June-26'!$C$3:$L$670,10,0) -> 0 | M80: =IFERROR((L80/I80*30),0) -> 0 | N80: =IF(M80<J80,"ORDER NOW","IN STOCK") -> ORDER NOW | O80: =IF(M80<J80,"CRITICAL","FOLLOW UP DELIVERY") -> CRITICAL | S80: =IF(L80<K80,0,1) -> 1
A81: 189 | B81: General Markting -مواد التسويق | C81: CO-00468 | D81: Plastic Holder for Cups حامل بلاستيك للاكواب | E81: Pcs. | F81: Pcs | G81: 1 | H81: =VLOOKUP($C81,'Master File June-26'!$C$3:$L$670,6,0) -> 0 | I81: =VLOOKUP($C81,'Master File June-26'!$C$3:$L$670,7,0) -> 0 | J81: =VLOOKUP($C81,'Master File June-26'!$C$3:$L$670,8,0) -> 14 | K81: =VLOOKUP($C81,'Master File June-26'!$C$3:$L$670,9,0) -> 0 | L81: =VLOOKUP($C81,'Master File June-26'!$C$3:$L$670,10,0) -> 0 | M81: =IFERROR((L81/I81*30),0) -> 0 | N81: =IF(M81<J81,"ORDER NOW","IN STOCK") -> ORDER NOW | O81: =IF(M81<J81,"CRITICAL","FOLLOW UP DELIVERY") -> CRITICAL | S81: =IF(L81<K81,0,1) -> 1
A82: 195 | B82: طباعة وتغليف - Packaging | C82: CO-00523 | D82: Turner Spoon Full Steel ملعقة ستيل | E82: 1 Pcs | F82: Pcs | G82: 1 | H82: =VLOOKUP($C82,'Master File June-26'!$C$3:$L$670,6,0) -> 11 | I82: =VLOOKUP($C82,'Master File June-26'!$C$3:$L$670,7,0) -> 11 | J82: =VLOOKUP($C82,'Master File June-26'!$C$3:$L$670,8,0) -> 14 | K82: =VLOOKUP($C82,'Master File June-26'!$C$3:$L$670,9,0) -> 5.5 | L82: =VLOOKUP($C82,'Master File June-26'!$C$3:$L$670,10,0) -> 0 | M82: =IFERROR((L82/I82*30),0) -> 0 | N82: =IF(M82<J82,"ORDER NOW","IN STOCK") -> ORDER NOW | O82: =IF(M82<J82,"CRITICAL","FOLLOW UP DELIVERY") -> CRITICAL | S82: =IF(L82<K82,0,1) -> 0
A83: 196 | B83: Tools - ادوات | C83: CO-00473 | D83: Loveramics Coffee Spoon Gold 10cm ملعقة اسبريسو | E83: 1 Pcs | F83: Pcs | G83: 1 | H83: =VLOOKUP($C83,'Master File June-26'!$C$3:$L$670,6,0) -> 680 | I83: =VLOOKUP($C83,'Master File June-26'!$C$3:$L$670,7,0) -> 680 | J83: =VLOOKUP($C83,'Master File June-26'!$C$3:$L$670,8,0) -> 14 | K83: =VLOOKUP($C83,'Master File June-26'!$C$3:$L$670,9,0) -> 340 | L83: =VLOOKUP($C83,'Master File June-26'!$C$3:$L$670,10,0) -> 0 | M83: =IFERROR((L83/I83*30),0) -> 0 | N83: =IF(M83<J83,"ORDER NOW","IN STOCK") -> ORDER NOW | O83: =IF(M83<J83,"CRITICAL","FOLLOW UP DELIVERY") -> CRITICAL | S83: =IF(L83<K83,0,1) -> 0
A84: 204 | B84: SmallWare | C84: CO-00522 | D84: Ice Scoop S/S Round bottom مغرفة ايس سكوب | E84: 1 Pcs | F84: Pcs | G84: 1 | H84: =VLOOKUP($C84,'Master File June-26'!$C$3:$L$670,6,0) -> 88 | I84: =VLOOKUP($C84,'Master File June-26'!$C$3:$L$670,7,0) -> 88 | J84: =VLOOKUP($C84,'Master File June-26'!$C$3:$L$670,8,0) -> 14 | K84: =VLOOKUP($C84,'Master File June-26'!$C$3:$L$670,9,0) -> 44 | L84: =VLOOKUP($C84,'Master File June-26'!$C$3:$L$670,10,0) -> 0 | M84: =IFERROR((L84/I84*30),0) -> 0 | N84: =IF(M84<J84,"ORDER NOW","IN STOCK") -> ORDER NOW | O84: =IF(M84<J84,"CRITICAL","FOLLOW UP DELIVERY") -> CRITICAL | S84: =IF(L84<K84,0,1) -> 0
... A91: 229 | B91: Tools - ادوات | C91: CO-00129 | D91: N.W BLU فوط غير منسوجة ازرق | E91: Pcs. | F91: Pcs | G91: 1 | H91: =VLOOKUP($C91,'Master File June-26'!$C$3:$L$670,6,0) -> 5.5 | I91: =VLOOKUP($C91,'Master File June-26'!$C$3:$L$670,7,0) -> 0 | J91: =VLOOKUP($C91,'Master File June-26'!$C$3:$L$670,8,0) -> 14 | K91: =VLOOKUP($C91,'Master File June-26'!$C$3:$L$670,9,0) -> 0 | L91: =VLOOKUP($C91,'Master File June-26'!$C$3:$L$670,10,0) -> 0 | M91: =IFERROR((L91/I91*30),0) -> 0 | N91: =IF(M91<J91,"ORDER NOW","IN STOCK") -> ORDER NOW | O91: =IF(M91<J91,"CRITICAL","FOLLOW UP DELIVERY") -> CRITICAL | S91: =IF(L91<K91,0,1) -> 1
A92: 252 | B92: Cleaning - منظفات | C92: CO-00072 | D92: Tide تايد | E92: 1 Case X 20 KG | F92: case | G92: =1/20 -> 0.05 | H92: =VLOOKUP($C92,'Master File June-26'!$C$3:$L$670,6,0) -> 5.5 | I92: =VLOOKUP($C92,'Master File June-26'!$C$3:$L$670,7,0) -> 110 | J92: =VLOOKUP($C92,'Master File June-26'!$C$3:$L$670,8,0) -> 14 | K92: =VLOOKUP($C92,'Master File June-26'!$C$3:$L$670,9,0) -> 55 | L92: =VLOOKUP($C92,'Master File June-26'!$C$3:$L$670,10,0) -> 0 | M92: =IFERROR((L92/I92*30),0) -> 0 | N92: =IF(M92<J92,"ORDER NOW","IN STOCK") -> ORDER NOW | O92: =IF(M92<J92,"CRITICAL","FOLLOW UP DELIVERY") -> CRITICAL | S92: =IF(L92<K92,0,1) -> 0
A93: 260 | B93: Kitchen tools | C93: CO-00352 | D93: Anfim SP2 Grinder fan filter فلتر مروحة طاحونة انفيم اس بي 2 | E93: 1 Bundel X 10 Pcs | F93: bundel | G93: 0.1 | H93: =VLOOKUP($C93,'Master File June-26'!$C$3:$L$670,6,0) -> 184 | I93: =VLOOKUP($C93,'Master File June-26'!$C$3:$L$670,7,0) -> 1840 | J93: =VLOOKUP($C93,'Master File June-26'!$C$3:$L$670,8,0) -> 14 | K93: =VLOOKUP($C93,'Master File June-26'!$C$3:$L$670,9,0) -> 920 | L93: =VLOOKUP($C93,'Master File June-26'!$C$3:$L$670,10,0) -> 0 | M93: =IFERROR((L93/I93*30),0) -> 0 | N93: =IF(M93<J93,"ORDER NOW","IN STOCK") -> ORDER NOW | O93: =IF(M93<J93,"CRITICAL","FOLLOW UP DELIVERY") -> CRITICAL | S93: =IF(L93<K93,0,1) -> 0
A94: 265 | B94: Consumables | C94: CO-00339 | D94: Cartridge Atlas 10" CPP 5 mcr RA5706508 قلب فلتر اطلس 10 " بولي بروبيبلين 5 ميكرون | E94: 1 Pcs | F94: Pcs | G94: 1 | H94: =VLOOKUP($C94,'Master File June-26'!$C$3:$L$670,6,0) -> 0 | I94: =VLOOKUP($C94,'Master File June-26'!$C$3:$L$670,7,0) -> 0 | J94: =VLOOKUP($C94,'Master File June-26'!$C$3:$L$670,8,0) -> 14 | K94: =VLOOKUP($C94,'Master File June-26'!$C$3:$L$670,9,0) -> 0 | L94: =VLOOKUP($C94,'Master File June-26'!$C$3:$L$670,10,0) -> 0 | M94: =IFERROR((L94/I94*30),0) -> 0 | N94: =IF(M94<J94,"ORDER NOW","IN STOCK") -> ORDER NOW | O94: =IF(M94<J94,"CRITICAL","FOLLOW UP DELIVERY") -> CRITICAL | S94: =IF(L94<K94,0,1) -> 1
A95: 266 | B95: Tools - ادوات | C95: CO-00511 | D95: Cartridge Atlas 20" CPP 5 mcr [RA5706708] قلب فلتر اطلس 20 " بولي بروبيبلين 5 ميكرون | E95: Pcs. | F95: Pcs | G95: 1 | H95: =VLOOKUP($C95,'Master File June-26'!$C$3:$L$670,6,0) -> 0 | I95: =VLOOKUP($C95,'Master File June-26'!$C$3:$L$670,7,0) -> 0 | J95: =VLOOKUP($C95,'Master File June-26'!$C$3:$L$670,8,0) -> 14 | K95: =VLOOKUP($C95,'Master File June-26'!$C$3:$L$670,9,0) -> 0 | L95: =VLOOKUP($C95,'Master File June-26'!$C$3:$L$670,10,0) -> 0 | M95: =IFERROR((L95/I95*30),0) -> 0 | N95: =IF(M95<J95,"ORDER NOW","IN STOCK") -> ORDER NOW | O95: =IF(M95<J95,"CRITICAL","FOLLOW UP DELIVERY") -> CRITICAL | S95: =IF(L95<K95,0,1) -> 1
A96: 267 | B96: Tools - ادوات | C96: CO-00513 | D96: Cartridge Atlas 20" BIG CPP 5 mcr [RE5706908] قلب فلتر اطلس 20 " جامبو بولي بروبيبلين 5 ميكرون | E96: Pcs. | F96: Pcs | G96: 1 | H96: =VLOOKUP($C96,'Master File June-26'!$C$3:$L$670,6,0) -> 0 | I96: =VLOOKUP($C96,'Master File June-26'!$C$3:$L$670,7,0) -> 0 | J96: =VLOOKUP($C96,'Master File June-26'!$C$3:$L$670,8,0) -> 14 | K96: =VLOOKUP($C96,'Master File June-26'!$C$3:$L$670,9,0) -> 0 | L96: =VLOOKUP($C96,'Master File June-26'!$C$3:$L$670,10,0) -> 1 | M96: =IFERROR((L96/I96*30),0) -> 0 | N96: =IF(M96<J96,"ORDER NOW","IN STOCK") -> ORDER NOW | O96: =IF(M96<J96,"CRITICAL","FOLLOW UP DELIVERY") -> CRITICAL | S96: =IF(L96<K96,0,1) -> 1
A97: 268 | B97: Tools - ادوات | C97: CO-00340 | D97: Cartridge Atlas 10" carbon block 5 mcr SX [RE5395108] قلب فلتر اطلس 10 " كربون بلوك 5 ميكرون اس اكس | E97: Pcs. | F97: Pcs | G97: 1 | H97: =VLOOKUP($C97,'Master File June-26'!$C$3:$L$670,6,0) -> 0 | I97: =VLOOKUP($C97,'Master File June-26'!$C$3:$L$670,7,0) -> 0 | J97: =VLOOKUP($C97,'Master File June-26'!$C$3:$L$670,8,0) -> 14 | K97: =VLOOKUP($C97,'Master File June-26'!$C$3:$L$670,9,0) -> 0 | L97: =VLOOKUP($C97,'Master File June-26'!$C$3:$L$670,10,0) -> 1 | M97: =IFERROR((L97/I97*30),0) -> 0 | N97: =IF(M97<J97,"ORDER NOW","IN STOCK") -> ORDER NOW | O97: =IF(M97<J97,"CRITICAL","FOLLOW UP DELIVERY") -> CRITICAL | S97: =IF(L97<K97,0,1) -> 1
A98: 270 | B98: Kitchen tools | C98: CO-00515 | D98: قالب سيلكون 3 فتحات 10سم ايطالي Silicone mold, 3 holes, 10 cm, Italian | E98: Pcs. | F98: Pcs | G98: 1 | H98: =VLOOKUP($C98,'Master File June-26'!$C$3:$L$670,6,0) -> 0 | I98: =VLOOKUP($C98,'Master File June-26'!$C$3:$L$670,7,0) -> 0 | J98: =VLOOKUP($C98,'Master File June-26'!$C$3:$L$670,8,0) -> 14 | K98: =VLOOKUP($C98,'Master File June-26'!$C$3:$L$670,9,0) -> 0 | L98: =VLOOKUP($C98,'Master File June-26'!$C$3:$L$670,10,0) -> 0 | M98: =IFERROR((L98/I98*30),0) -> 0 | N98: =IF(M98<J98,"ORDER NOW","IN STOCK") -> ORDER NOW | O98: =IF(M98<J98,"CRITICAL","FOLLOW UP DELIVERY") -> CRITICAL | S98: =IF(L98<K98,0,1) -> 1
A99: 271 | B99: Tools - ادوات | C99: CO-00331 | D99: Gasket portafilter 8.5 mm with grooves ربر لماكينة سنسو - 8.5 ملم | E99: Pcs. | F99: Pcs | G99: 1 | H99: =VLOOKUP($C99,'Master File June-26'!$C$3:$L$670,6,0) -> 0 | I99: =VLOOKUP($C99,'Master File June-26'!$C$3:$L$670,7,0) -> 0 | J99: =VLOOKUP($C99,'Master File June-26'!$C$3:$L$670,8,0) -> 14 | K99: =VLOOKUP($C99,'Master File June-26'!$C$3:$L$670,9,0) -> 0 | L99: =VLOOKUP($C99,'Master File June-26'!$C$3:$L$670,10,0) -> 0 | M99: =IFERROR((L99/I99*30),0) -> 0 | N99: =IF(M99<J99,"ORDER NOW","IN STOCK") -> ORDER NOW | O99: =IF(M99<J99,"CRITICAL","FOLLOW UP DELIVERY") -> CRITICAL | S99: =IF(L99<K99,0,1) -> 1
A100: 275 | B100: Consumables | C100: CO-00349 | D100: BREAD KNIFE سكين مخبوزات | E100: 1 Pcs | F100: Pcs | G100: 1 | H100: =VLOOKUP($C100,'Master File June-26'!$C$3:$L$670,6,0) -> 22 | I100: =VLOOKUP($C100,'Master File June-26'!$C$3:$L$670,7,0) -> 22 | J100: =VLOOKUP($C100,'Master File June-26'!$C$3:$L$670,8,0) -> 14 | K100: =VLOOKUP($C100,'Master File June-26'!$C$3:$L$670,9,0) -> 11 | L100: =VLOOKUP($C100,'Master File June-26'!$C$3:$L$670,10,0) -> 0 | M100: =IFERROR((L100/I100*30),0) -> 0 | N100: =IF(M100<J100,"ORDER NOW","IN STOCK") -> ORDER NOW | O100: =IF(M100<J100,"CRITICAL","FOLLOW UP DELIVERY") -> CRITICAL | S100: =IF(L100<K100,0,1) -> 0
A101: 276 | B101: Consumables | C101: CO-00505 | D101: Steel Ashtray طفاية سجائر | E101: 1 Pcs | F101: Pcs | G101: 1 | H101: =VLOOKUP($C101,'Master File June-26'!$C$3:$L$670,6,0) -> 600 | I101: =VLOOKUP($C101,'Master File June-26'!$C$3:$L$670,7,0) -> 600 | J101: =VLOOKUP($C101,'Master File June-26'!$C$3:$L$670,8,0) -> 14 | K101: =VLOOKUP($C101,'Master File June-26'!$C$3:$L$670,9,0) -> 300 | L101: =VLOOKUP($C101,'Master File June-26'!$C$3:$L$670,10,0) -> 0 | M101: =IFERROR((L101/I101*30),0) -> 0 | N101: =IF(M101<J101,"ORDER NOW","IN STOCK") -> ORDER NOW | O101: =IF(M101<J101,"CRITICAL","FOLLOW UP DELIVERY") -> CRITICAL | S101: =IF(L101<K101,0,1) -> 0
A102: 279 | B102: طباعة وتغليف - Packaging | C102: CO-00221 | D102: PRICE MACHINE INK ROLLER ALL حبر الة تسعير وتواريخ | E102: 1 Pcs | F102: Pcs | G102: 1 | H102: =VLOOKUP($C102,'Master File June-26'!$C$3:$L$670,6,0) -> 27.5 | I102: =VLOOKUP($C102,'Master File June-26'!$C$3:$L$670,7,0) -> 27.5 | J102: =VLOOKUP($C102,'Master File June-26'!$C$3:$L$670,8,0) -> 14 | K102: =VLOOKUP($C102,'Master File June-26'!$C$3:$L$670,9,0) -> 13.75 | L102: =VLOOKUP($C102,'Master File June-26'!$C$3:$L$670,10,0) -> 0 | M102: =IFERROR((L102/I102*30),0) -> 0 | N102: =IF(M102<J102,"ORDER NOW","IN STOCK") -> ORDER NOW | O102: =IF(M102<J102,"CRITICAL","FOLLOW UP DELIVERY") -> CRITICAL | S102: =IF(L102<K102,0,1) -> 0
A103: 282 | B103: طباعة وتغليف - Packaging | C103: CO-00412 | D103: Namq Tooth Wipes | E103: 1 Box X 1200 Pcs. | F103: Box | G103: 0.00083333333 | H103: =VLOOKUP($C103,'Master File June-26'!$C$3:$L$670,6,0) -> 11 | I103: =VLOOKUP($C103,'Master File June-26'!$C$3:$L$670,7,0) -> 13200 | J103: =VLOOKUP($C103,'Master File June-26'!$C$3:$L$670,8,0) -> 14 | K103: =VLOOKUP($C103,'Master File June-26'!$C$3:$L$670,9,0) -> 6600 | L103: =VLOOKUP($C103,'Master File June-26'!$C$3:$L$670,10,0) -> 0 | M103: =IFERROR((L103/I103*30),0) -> 0 | N103: =IF(M103<J103,"ORDER NOW","IN STOCK") -> ORDER NOW | O103: =IF(M103<J103,"CRITICAL","FOLLOW UP DELIVERY") -> CRITICAL | S103: =IF(L103<K103,0,1) -> 0
A104: 283 | B104: طباعة وتغليف - Packaging | C104: CO-00217 | D104: receipt NAMQ سند نمق | E104: Pcs. | F104: Pcs | G104: 1 | H104: =VLOOKUP($C104,'Master File June-26'!$C$3:$L$670,6,0) -> 22 | I104: =VLOOKUP($C104,'Master File June-26'!$C$3:$L$670,7,0) -> 22 | J104: =VLOOKUP($C104,'Master File June-26'!$C$3:$L$670,8,0) -> 14 | K104: =VLOOKUP($C104,'Master File June-26'!$C$3:$L$670,9,0) -> 11 | L104: =VLOOKUP($C104,'Master File June-26'!$C$3:$L$670,10,0) -> 0 | M104: =IFERROR((L104/I104*30),0) -> 0 | N104: =IF(M104<J104,"ORDER NOW","IN STOCK") -> ORDER NOW | O104: =IF(M104<J104,"CRITICAL","FOLLOW UP DELIVERY") -> CRITICAL | S104: =IF(L104<K104,0,1) -> 0
... A129: 312 | B129: Uniform | C129: CO-00543 | D129: Breehant Hoodie هودي بريهانت | E129: Pcs. | F129: Pcs | G129: 1 | H129: =VLOOKUP($C129,'Master File June-26'!$C$3:$L$670,6,0) -> 200 | I129: =VLOOKUP($C129,'Master File June-26'!$C$3:$L$670,7,0) -> 200 | J129: =VLOOKUP($C129,'Master File June-26'!$C$3:$L$670,8,0) -> 14 | K129: =VLOOKUP($C129,'Master File June-26'!$C$3:$L$670,9,0) -> 100 | L129: =VLOOKUP($C129,'Master File June-26'!$C$3:$L$670,10,0) -> 0 | M129: =IFERROR((L129/I129*30),0) -> 0 | N129: =IF(M129<J129,"ORDER NOW","IN STOCK") -> ORDER NOW | O129: =IF(M129<J129,"CRITICAL","FOLLOW UP DELIVERY") -> CRITICAL | S129: =IF(L129<K129,0,1) -> 0
A130: 315 | B130: Tools - ادوات | C130: CO-00483 | D130: Syscall SGP-300R 10c (set) Diamond pager +charger base with power supply" جهاز بيجر سانكول لبريهانت | E130: 1 Box X 10 Pcs. | F130: Box | G130: =1/10 -> 0.1 | H130: =VLOOKUP($C130,'Master File June-26'!$C$3:$L$670,6,0) -> 8 | I130: =VLOOKUP($C130,'Master File June-26'!$C$3:$L$670,7,0) -> 80 | J130: =VLOOKUP($C130,'Master File June-26'!$C$3:$L$670,8,0) -> 14 | K130: =VLOOKUP($C130,'Master File June-26'!$C$3:$L$670,9,0) -> 40 | L130: =VLOOKUP($C130,'Master File June-26'!$C$3:$L$670,10,0) -> 0 | M130: =IFERROR((L130/I130*30),0) -> 0 | N130: =IF(M130<J130,"ORDER NOW","IN STOCK") -> ORDER NOW | O130: =IF(M130<J130,"CRITICAL","FOLLOW UP DELIVERY") -> CRITICAL | S130: =IF(L130<K130,0,1) -> 0
...

Sheet Raw Material Stock status
A2: Item Code | B2: Item Description | C2: Packing | D2: UOM | E2: Conversion | F2: QTY in Pack | G2: QTY in Unit | H2: Lead Time | I2: Reordering Point | J2: WH Stocks | K2: Coverage/Day | L2: 0rder Status | M2: Criticality | N2: Stock Status
A3: RM-00502 | B3: Sugar Jaggery Vijay سكر جاجيري مدور | C3: Box | D3: Box | E3: 1 | F3: =VLOOKUP($A3,'Master File June-26'!$C$3:$L$670,6,0) -> 2 | G3: =VLOOKUP($A3,'Master File June-26'!$C$3:$L$670,7,0) -> 2 | H3: =VLOOKUP($A3,'Master File June-26'!$C$3:$L$670,8,0) -> 14 | I3: =VLOOKUP($A3,'Master File June-26'!$C$3:$L$670,9,0) -> 1 | J3: =VLOOKUP($A3,'Master File June-26'!$C$3:$L$670,10,0) -> 0 | K3: =IFERROR((J3/G3*30),0) -> 0 | L3: =IF(K3<H3,"ORDER NOW","IN STOCK") -> ORDER NOW | M3: =IF(K3<H3,"CRITICAL","FOLLOW UP DELIVERY") -> CRITICAL | N3: 1
A4: RM-00206 | B4: Mehran red pepper فلفل أحمر مهران | C4: Box | D4: Box | E4: 1 | F4: =VLOOKUP($A4,'Master File June-26'!$C$3:$L$670,6,0) -> 1 | G4: =VLOOKUP($A4,'Master File June-26'!$C$3:$L$670,7,0) -> 1 | H4: =VLOOKUP($A4,'Master File June-26'!$C$3:$L$670,8,0) -> 14 | I4: =VLOOKUP($A4,'Master File June-26'!$C$3:$L$670,9,0) -> 0.5 | J4: =VLOOKUP($A4,'Master File June-26'!$C$3:$L$670,10,0) -> 0 | K4: =IFERROR((J4/G4*30),0) -> 0 | L4: =IF(K4<H4,"ORDER NOW","IN STOCK") -> ORDER NOW | M4: =IF(K4<H4,"CRITICAL","FOLLOW UP DELIVERY") -> CRITICAL | N4: 1
A5: RM-00677 | B5: مايونيز قودي / Goody Mayonnaise | C5: 1 Box X 4 Pcs X 3.75 | D5: Box | E5: 0.066666667 | F5: =VLOOKUP($A5,'Master File June-26'!$C$3:$L$670,6,0) -> 13 | G5: =VLOOKUP($A5,'Master File June-26'!$C$3:$L$670,7,0) -> 195 | H5: =VLOOKUP($A5,'Master File June-26'!$C$3:$L$670,8,0) -> 14 | I5: =VLOOKUP($A5,'Master File June-26'!$C$3:$L$670,9,0) -> 97.5 | J5: =VLOOKUP($A5,'Master File June-26'!$C$3:$L$670,10,0) -> 211.44 | K5: =IFERROR((J5/G5*30),0) -> 32.529231 | L5: =IF(K5<H5,"ORDER NOW","IN STOCK") -> IN STOCK | M5: =IF(K5<H5,"CRITICAL","FOLLOW UP DELIVERY") -> FOLLOW UP DELIVERY | N5: 1
A6: RM-00415 | B6: جوز البيكان | Pecan nuts | C6: 1 Bag X 13.6 Kg | D6: bag | E6: 0.076923077 | F6: =VLOOKUP($A6,'Master File June-26'!$C$3:$L$670,6,0) -> 89.5 | G6: =VLOOKUP($A6,'Master File June-26'!$C$3:$L$670,7,0) -> 1163.5 | H6: =VLOOKUP($A6,'Master File June-26'!$C$3:$L$670,8,0) -> 14 | I6: =VLOOKUP($A6,'Master File June-26'!$C$3:$L$670,9,0) -> 581.75 | J6: =VLOOKUP($A6,'Master File June-26'!$C$3:$L$670,10,0) -> 0 | K6: =IFERROR((J6/G6*30),0) -> 0 | L6: =IF(K6<H6,"ORDER NOW","IN STOCK") -> ORDER NOW | M6: =IF(K6<H6,"CRITICAL","FOLLOW UP DELIVERY") -> CRITICAL | N6: 0
A7: RM-00421 | B7: Coconut powder | جوز الهند بودر | C7: 1 BAG X X 7 KG | D7: bag | E7: 0.14285714 | F7: =VLOOKUP($A7,'Master File June-26'!$C$3:$L$670,6,0) -> 43 | G7: =VLOOKUP($A7,'Master File June-26'!$C$3:$L$670,7,0) -> 301 | H7: =VLOOKUP($A7,'Master File June-26'!$C$3:$L$670,8,0) -> 14 | I7: =VLOOKUP($A7,'Master File June-26'!$C$3:$L$670,9,0) -> 150.5 | J7: =VLOOKUP($A7,'Master File June-26'!$C$3:$L$670,10,0) -> 0 | K7: =IFERROR((J7/G7*30),0) -> 0 | L7: =IF(K7<H7,"ORDER NOW","IN STOCK") -> ORDER NOW | M7: =IF(K7<H7,"CRITICAL","FOLLOW UP DELIVERY") -> CRITICAL | N7: 0
A8: RM-00183 | B8: Ketchup Tomato كاتشب | C8: 1 Box X 10pcs X 570 grm | D8: Box | E8: 0.1754386 | F8: =VLOOKUP($A8,'Master File June-26'!$C$3:$L$670,6,0) -> 4 | G8: =VLOOKUP($A8,'Master File June-26'!$C$3:$L$670,7,0) -> 22.8 | H8: =VLOOKUP($A8,'Master File June-26'!$C$3:$L$670,8,0) -> 14 | I8: =VLOOKUP($A8,'Master File June-26'!$C$3:$L$670,9,0) -> 11.4 | J8: =VLOOKUP($A8,'Master File June-26'!$C$3:$L$670,10,0) -> 23.94 | K8: =IFERROR((J8/G8*30),0) -> 31.5 | L8: =IF(K8<H8,"ORDER NOW","IN STOCK") -> IN STOCK | M8: =IF(K8<H8,"CRITICAL","FOLLOW UP DELIVERY") -> FOLLOW UP DELIVERY | N8: 0
A9: RM-00018 | B9: جبن شيدر انجليزي Irish Mild yellow cheddar Cheese | C9: KG | D9: Pcs | E9: 1 | F9: =VLOOKUP($A9,'Master File June-26'!$C$3:$L$670,6,0) -> 13 | G9: =VLOOKUP($A9,'Master File June-26'!$C$3:$L$670,7,0) -> 13 | H9: =VLOOKUP($A9,'Master File June-26'!$C$3:$L$670,8,0) -> 14 | I9: =VLOOKUP($A9,'Master File June-26'!$C$3:$L$670,9,0) -> 6.5 | J9: =VLOOKUP($A9,'Master File June-26'!$C$3:$L$670,10,0) -> 0 | K9: =IFERROR((J9/G9*30),0) -> 0 | L9: =IF(K9<H9,"ORDER NOW","IN STOCK") -> ORDER NOW | M9: =IF(K9<H9,"CRITICAL","FOLLOW UP DELIVERY") -> CRITICAL | N9: 0
A10: RM-00681 | B10: معبوج تمر هندي / Tamrind | C10: 1 Pcs X 500 G | D10: Pcs | E10: 2 | F10: =VLOOKUP($A10,'Master File June-26'!$C$3:$L$670,6,0) -> 44 | G10: =VLOOKUP($A10,'Master File June-26'!$C$3:$L$670,7,0) -> 22 | H10: =VLOOKUP($A10,'Master File June-26'!$C$3:$L$670,8,0) -> 14 | I10: =VLOOKUP($A10,'Master File June-26'!$C$3:$L$670,9,0) -> 11 | J10: =VLOOKUP($A10,'Master File June-26'!$C$3:$L$670,10,0) -> 0 | K10: =IFERROR((J10/G10*30),0) -> 0 | L10: =IF(K10<H10,"ORDER NOW","IN STOCK") -> ORDER NOW | M10: =IF(K10<H10,"CRITICAL","FOLLOW UP DELIVERY") -> CRITICAL | N10: 0
A11: RM-00423 | B11: Hazelnut بندق | C11: 1 Bag X 10 Kg | D11: Box | E11: 0.1 | F11: =VLOOKUP($A11,'Master File June-26'!$C$3:$L$670,6,0) -> 120 | G11: =VLOOKUP($A11,'Master File June-26'!$C$3:$L$670,7,0) -> 1200 | H11: =VLOOKUP($A11,'Master File June-26'!$C$3:$L$670,8,0) -> 14 | I11: =VLOOKUP($A11,'Master File June-26'!$C$3:$L$670,9,0) -> 600 | J11: =VLOOKUP($A11,'Master File June-26'!$C$3:$L$670,10,0) -> 0 | K11: =IFERROR((J11/G11*30),0) -> 0 | L11: =IF(K11<H11,"ORDER NOW","IN STOCK") -> ORDER NOW | M11: =IF(K11<H11,"CRITICAL","FOLLOW UP DELIVERY") -> CRITICAL | N11: 0
A12: RM-00439 | B12: Unroasted peanuts | فول سوداني | C12: 1 Bag X 10 Kg | D12: bag | E12: 0.1 | F12: =VLOOKUP($A12,'Master File June-26'!$C$3:$L$670,6,0) -> 9.5 | G12: =VLOOKUP($A12,'Master File June-26'!$C$3:$L$670,7,0) -> 95 | H12: =VLOOKUP($A12,'Master File June-26'!$C$3:$L$670,8,0) -> 14 | I12: =VLOOKUP($A12,'Master File June-26'!$C$3:$L$670,9,0) -> 47.5 | J12: =VLOOKUP($A12,'Master File June-26'!$C$3:$L$670,10,0) -> 20 | K12: =IFERROR((J12/G12*30),0) -> 6.3157895 | L12: =IF(K12<H12,"ORDER NOW","IN STOCK") -> ORDER NOW | M12: =IF(K12<H12,"CRITICAL","FOLLOW UP DELIVERY") -> CRITICAL | N12: 1
A13: RM-00006 | B13: Goody Creamy Peanut Butte | قودي زبدة الفول السوداني الناعمة | C13: 12pcs x 1 kg | D13: Pcs | E13: 0.083333333 | F13: =VLOOKUP($A13,'Master File June-26'!$C$3:$L$670,6,0) -> 55 | G13: =VLOOKUP($A13,'Master File June-26'!$C$3:$L$670,7,0) -> 660 | H13: =VLOOKUP($A13,'Master File June-26'!$C$3:$L$670,8,0) -> 14 | I13: =VLOOKUP($A13,'Master File June-26'!$C$3:$L$670,9,0) -> 330 | J13: =VLOOKUP($A13,'Master File June-26'!$C$3:$L$670,10,0) -> 6.2 | K13: =IFERROR((J13/G13*30),0) -> 0.28181818 | L13: =IF(K13<H13,"ORDER NOW","IN STOCK") -> ORDER NOW | M13: =IF(K13<H13,"CRITICAL","FOLLOW UP DELIVERY") -> CRITICAL | N13: 0
A14: RM-00175 | B14: ORIG RANCH SAUCE | صوص الرانش | C14: 1X6X530 GM (3.8 KG) | D14: KG | E14: 0.26315789 | F14: =VLOOKUP($A14,'Master File June-26'!$C$3:$L$670,6,0) -> 16 | G14: =VLOOKUP($A14,'Master File June-26'!$C$3:$L$670,7,0) -> 60.8 | H14: =VLOOKUP($A14,'Master File June-26'!$C$3:$L$670,8,0) -> 14 | I14: =VLOOKUP($A14,'Master File June-26'!$C$3:$L$670,9,0) -> 30.4 | J14: =VLOOKUP($A14,'Master File June-26'!$C$3:$L$670,10,0) -> 0 | K14: =IFERROR((J14/G14*30),0) -> 0 | L14: =IF(K14<H14,"ORDER NOW","IN STOCK") -> ORDER NOW | M14: =IF(K14<H14,"CRITICAL","FOLLOW UP DELIVERY") -> CRITICAL | N14: 0
A15: RM-00320 | B15: صوص جوز البيكان VARIEGATO NOCE PECAN | C15: 1 Ctn. X 2 Tin X 5kg | D15: Ctn | E15: 0.1 | F15: =VLOOKUP($A15,'Master File June-26'!$C$3:$L$670,6,0) -> 143 | G15: =VLOOKUP($A15,'Master File June-26'!$C$3:$L$670,7,0) -> 1430 | H15: =VLOOKUP($A15,'Master File June-26'!$C$3:$L$670,8,0) -> 14 | I15: =VLOOKUP($A15,'Master File June-26'!$C$3:$L$670,9,0) -> 715 | J15: =VLOOKUP($A15,'Master File June-26'!$C$3:$L$670,10,0) -> 650 | K15: =IFERROR((J15/G15*30),0) -> 13.636364 | L15: =IF(K15<H15,"ORDER NOW","IN STOCK") -> ORDER NOW | M15: =IF(K15<H15,"CRITICAL","FOLLOW UP DELIVERY") -> CRITICAL | N15: 0
A16: RM-00582 | B16: Syrup Mango Teisseireسيروب المانجو | C16: 1 Box X 6 Bottle X 1 Ltr | D16: Box | E16: 0.16666667 | F16: =VLOOKUP($A16,'Master File June-26'!$C$3:$L$670,6,0) -> 5.5 | G16: =VLOOKUP($A16,'Master File June-26'!$C$3:$L$670,7,0) -> 33 | H16: =VLOOKUP($A16,'Master File June-26'!$C$3:$L$670,8,0) -> 14 | I16: =VLOOKUP($A16,'Master File June-26'!$C$3:$L$670,9,0) -> 16.5 | J16: =VLOOKUP($A16,'Master File June-26'!$C$3:$L$670,10,0) -> 0 | K16: =IFERROR((J16/G16*30),0) -> 0 | L16: =IF(K16<H16,"ORDER NOW","IN STOCK") -> ORDER NOW | M16: =IF(K16<H16,"CRITICAL","FOLLOW UP DELIVERY") -> CRITICAL | N16: 0 | O16: NO Demand
A17: RM-00508 | B17: Condensed milkحليب مكثف | C17: 1 Box X 24 Pcs. X 1 Kilo | D17: Box | E17: 0.041666667 | F17: =VLOOKUP($A17,'Master File June-26'!$C$3:$L$670,6,0) -> 56 | G17: =VLOOKUP($A17,'Master File June-26'!$C$3:$L$670,7,0) -> 1344 | H17: =VLOOKUP($A17,'Master File June-26'!$C$3:$L$670,8,0) -> 14 | I17: =VLOOKUP($A17,'Master File June-26'!$C$3:$L$670,9,0) -> 672 | J17: =VLOOKUP($A17,'Master File June-26'!$C$3:$L$670,10,0) -> 5884.8 | K17: =IFERROR((J17/G17*30),0) -> 131.35714 | L17: =IF(K17<H17,"ORDER NOW","IN STOCK") -> IN STOCK | M17: =IF(K17<H17,"CRITICAL","FOLLOW UP DELIVERY") -> FOLLOW UP DELIVERY | N17: 0
A18: RM-00445 | B18: Kompletin Spray Oil بخاخ زيت كومبليت ان | C18: 1 Box X 6 Pcs X 500ml | D18: Box | E18: 0.33333333 | F18: =VLOOKUP($A18,'Master File June-26'!$C$3:$L$670,6,0) -> 135 | G18: =VLOOKUP($A18,'Master File June-26'!$C$3:$L$670,7,0) -> 405 | H18: =VLOOKUP($A18,'Master File June-26'!$C$3:$L$670,8,0) -> 14 | I18: =VLOOKUP($A18,'Master File June-26'!$C$3:$L$670,9,0) -> 202.5 | J18: =VLOOKUP($A18,'Master File June-26'!$C$3:$L$670,10,0) -> 1050 | K18: =IFERROR((J18/G18*30),0) -> 77.777778 | L18: =IF(K18<H18,"ORDER NOW","IN STOCK") -> IN STOCK | M18: =IF(K18<H18,"CRITICAL","FOLLOW UP DELIVERY") -> FOLLOW UP DELIVERY | N18: 0
A19: RM-00432 | B19: Sliced almond لوز شرايح امريكي | C19: 1 Box X 10 Kg | D19: Box | E19: 0.1 | F19: =VLOOKUP($A19,'Master File June-26'!$C$3:$L$670,6,0) -> 19 | G19: =VLOOKUP($A19,'Master File June-26'!$C$3:$L$670,7,0) -> 190 | H19: =VLOOKUP($A19,'Master File June-26'!$C$3:$L$670,8,0) -> 14 | I19: =VLOOKUP($A19,'Master File June-26'!$C$3:$L$670,9,0) -> 95 | J19: =VLOOKUP($A19,'Master File June-26'!$C$3:$L$670,10,0) -> 0 | K19: =IFERROR((J19/G19*30),0) -> 0 | L19: =IF(K19<H19,"ORDER NOW","IN STOCK") -> ORDER NOW | M19: =IF(K19<H19,"CRITICAL","FOLLOW UP DELIVERY") -> CRITICAL | N19: 1
A20: RM-00673 | B20: Valrhona Javira 40% / شوكولاته فالرهونا | C20: 1 Box X 3 x 3 KG | D20: Box | E20: 0.11111111 | F20: =VLOOKUP($A20,'Master File June-26'!$C$3:$L$670,6,0) -> 22 | G20: =VLOOKUP($A20,'Master File June-26'!$C$3:$L$670,7,0) -> 198 | H20: =VLOOKUP($A20,'Master File June-26'!$C$3:$L$670,8,0) -> 14 | I20: =VLOOKUP($A20,'Master File June-26'!$C$3:$L$670,9,0) -> 99 | J20: =VLOOKUP($A20,'Master File June-26'!$C$3:$L$670,10,0) -> 0 | K20: =IFERROR((J20/G20*30),0) -> 0 | L20: =IF(K20<H20,"ORDER NOW","IN STOCK") -> ORDER NOW | M20: =IF(K20<H20,"CRITICAL","FOLLOW UP DELIVERY") -> CRITICAL | N20: 0 | O20: NO Demand
A21: RM-00538 | B21: SYRUP LEMONADE 1883 سيروب ليموناضة | C21: 1 Box X 6 Bottle X 1 Ltr | D21: Box | E21: 0.16666667 | F21: =VLOOKUP($A21,'Master File June-26'!$C$3:$L$670,6,0) -> 16.5 | G21: =VLOOKUP($A21,'Master File June-26'!$C$3:$L$670,7,0) -> 99 | H21: =VLOOKUP($A21,'Master File June-26'!$C$3:$L$670,8,0) -> 14 | I21: =VLOOKUP($A21,'Master File June-26'!$C$3:$L$670,9,0) -> 49.5 | J21: =VLOOKUP($A21,'Master File June-26'!$C$3:$L$670,10,0) -> 99 | K21: =IFERROR((J21/G21*30),0) -> 30 | L21: =IF(K21<H21,"ORDER NOW","IN STOCK") -> IN STOCK | M21: =IF(K21<H21,"CRITICAL","FOLLOW UP DELIVERY") -> FOLLOW UP DELIVERY | N21: 0
A22: RM-00434 | B22: Walnuts عين جمل | C22: 1 Box X 10 Kg | D22: Box | E22: 0.1 | F22: =VLOOKUP($A22,'Master File June-26'!$C$3:$L$670,6,0) -> 200 | G22: =VLOOKUP($A22,'Master File June-26'!$C$3:$L$670,7,0) -> 2000 | H22: =VLOOKUP($A22,'Master File June-26'!$C$3:$L$670,8,0) -> 14 | I22: =VLOOKUP($A22,'Master File June-26'!$C$3:$L$670,9,0) -> 1000 | J22: =VLOOKUP($A22,'Master File June-26'!$C$3:$L$670,10,0) -> 0 | K22: =IFERROR((J22/G22*30),0) -> 0 | L22: =IF(K22<H22,"ORDER NOW","IN STOCK") -> ORDER NOW | M22: =IF(K22<H22,"CRITICAL","FOLLOW UP DELIVERY") -> CRITICAL | N22: 0
A23: RM-00313 | B23: Vanilla bourbon فانيلا بوربون | C23: 1 Box X 12bottle X 1kg | D23: Box | E23: 0.083333333 | F23: =VLOOKUP($A23,'Master File June-26'!$C$3:$L$670,6,0) -> 250 | G23: =VLOOKUP($A23,'Master File June-26'!$C$3:$L$670,7,0) -> 3000 | H23: =VLOOKUP($A23,'Master File June-26'!$C$3:$L$670,8,0) -> 14 | I23: =VLOOKUP($A23,'Master File June-26'!$C$3:$L$670,9,0) -> 1500 | J23: =VLOOKUP($A23,'Master File June-26'!$C$3:$L$670,10,0) -> 0 | K23: =IFERROR((J23/G23*30),0) -> 0 | L23: =IF(K23<H23,"ORDER NOW","IN STOCK") -> ORDER NOW | M23: =IF(K23<H23,"CRITICAL","FOLLOW UP DELIVERY") -> CRITICAL | N23: 1
A24: RM-00293 | B24: Soft White Vanilla مسحوق فانيلا روبيكون | C24: 1 Box X 8 Bag X 1.5 Kg | D24: Box | E24: 0.083333333 | F24: =VLOOKUP($A24,'Master File June-26'!$C$3:$L$670,6,0) -> 77 | G24: =VLOOKUP($A24,'Master File June-26'!$C$3:$L$670,7,0) -> 924 | H24: =VLOOKUP($A24,'Master File June-26'!$C$3:$L$670,8,0) -> 14 | I24: =VLOOKUP($A24,'Master File June-26'!$C$3:$L$670,9,0) -> 462 | J24: =VLOOKUP($A24,'Master File June-26'!$C$3:$L$670,10,0) -> 0 | K24: =IFERROR((J24/G24*30),0) -> 0 | L24: =IF(K24<H24,"ORDER NOW","IN STOCK") -> ORDER NOW | M24: =IF(K24<H24,"CRITICAL","FOLLOW UP DELIVERY") -> CRITICAL | N24: 0
A25: RM-00458 | B25: Costa Rica San ignacio Coffee Breehant 1 KGكوستاريكا سان اجناسيو بريهانت 1kg | C25: KG | D25: Pcs | E25: 1 | F25: =VLOOKUP($A25,'Master File June-26'!$C$3:$L$670,6,0) -> 0 | G25: =VLOOKUP($A25,'Master File June-26'!$C$3:$L$670,7,0) -> 0 | H25: =VLOOKUP($A25,'Master File June-26'!$C$3:$L$670,8,0) -> 14 | I25: =VLOOKUP($A25,'Master File June-26'!$C$3:$L$670,9,0) -> 0 | J25: =VLOOKUP($A25,'Master File June-26'!$C$3:$L$670,10,0) -> 0 | K25: =IFERROR((J25/G25*30),0) -> 0 | L25: =IF(K25<H25,"ORDER NOW","IN STOCK") -> ORDER NOW | M25: =IF(K25<H25,"CRITICAL","FOLLOW UP DELIVERY") -> CRITICAL | N25: 1
A26: RM-00573 | B26: Syrup Giffard pomegranate سيروب رمان جيفارد | C26: 1 Box 6 Bottle X 1 Ltr | D26: Box | E26: 0.16666667 | F26: =VLOOKUP($A26,'Master File June-26'!$C$3:$L$670,6,0) -> 16.5 | G26: =VLOOKUP($A26,'Master File June-26'!$C$3:$L$670,7,0) -> 99 | H26: =VLOOKUP($A26,'Master File June-26'!$C$3:$L$670,8,0) -> 14 | I26: =VLOOKUP($A26,'Master File June-26'!$C$3:$L$670,9,0) -> 49.5 | J26: =VLOOKUP($A26,'Master File June-26'!$C$3:$L$670,10,0) -> 0 | K26: =IFERROR((J26/G26*30),0) -> 0 | L26: =IF(K26<H26,"ORDER NOW","IN STOCK") -> ORDER NOW | M26: =IF(K26<H26,"CRITICAL","FOLLOW UP DELIVERY") -> CRITICAL | N26: 0
A27: RM-00572 | B27: Syrup Giffard red raspberryسيروب توت احمر جيفراد | C27: 1 Box 6 Bottle X 1 Ltr | D27: Box | E27: 0.16666667 | F27: =VLOOKUP($A27,'Master File June-26'!$C$3:$L$670,6,0) -> 11 | G27: =VLOOKUP($A27,'Master File June-26'!$C$3:$L$670,7,0) -> 66 | H27: =VLOOKUP($A27,'Master File June-26'!$C$3:$L$670,8,0) -> 14 | I27: =VLOOKUP($A27,'Master File June-26'!$C$3:$L$670,9,0) -> 33 | J27: =VLOOKUP($A27,'Master File June-26'!$C$3:$L$670,10,0) -> 0 | K27: =IFERROR((J27/G27*30),0) -> 0 | L27: =IF(K27<H27,"ORDER NOW","IN STOCK") -> ORDER NOW | M27: =IF(K27<H27,"CRITICAL","FOLLOW UP DELIVERY") -> CRITICAL | N27: 0
A28: RM-00371 | B28: Fruits Puree Boiron Raspberry فواكة مهروسة بوارون - توت | C28: 1 PCS X 10 KG | D28: Pcs | E28: 0.1 | F28: =VLOOKUP($A28,'Master File June-26'!$C$3:$L$670,6,0) -> 0 | G28: =VLOOKUP($A28,'Master File June-26'!$C$3:$L$670,7,0) -> 0 | H28: =VLOOKUP($A28,'Master File June-26'!$C$3:$L$670,8,0) -> 14 | I28: =VLOOKUP($A28,'Master File June-26'!$C$3:$L$670,9,0) -> 0 | J28: =VLOOKUP($A28,'Master File June-26'!$C$3:$L$670,10,0) -> 0 | K28: =IFERROR((J28/G28*30),0) -> 0 | L28: =IF(K28<H28,"ORDER NOW","IN STOCK") -> ORDER NOW | M28: =IF(K28<H28,"CRITICAL","FOLLOW UP DELIVERY") -> CRITICAL | N28: 1
A29: RM-00100 | B29: FLORIMONT CREAM WHIPPING 35% FAT - FRANCE | كريمة خفق | C29: 1 Box X 12 Bottle X 1 ltr | D29: Box | E29: 0.083333333 | F29: =VLOOKUP($A29,'Master File June-26'!$C$3:$L$670,6,0) -> 66 | G29: =VLOOKUP($A29,'Master File June-26'!$C$3:$L$670,7,0) -> 792 | H29: =VLOOKUP($A29,'Master File June-26'!$C$3:$L$670,8,0) -> 14 | I29: =VLOOKUP($A29,'Master File June-26'!$C$3:$L$670,9,0) -> 396 | J29: =VLOOKUP($A29,'Master File June-26'!$C$3:$L$670,10,0) -> 0 | K29: =IFERROR((J29/G29*30),0) -> 0 | L29: =IF(K29<H29,"ORDER NOW","IN STOCK") -> ORDER NOW | M29: =IF(K29<H29,"CRITICAL","FOLLOW UP DELIVERY") -> CRITICAL | N29: 0
A30: RM-00642 | B30: Sponge chocolate Premix | خليط كيك شوكولاتة | C30: 1 Pcs X 25 KG | D30: Pcs | E30: 0.04 | F30: =VLOOKUP($A30,'Master File June-26'!$C$3:$L$670,6,0) -> 0 | G30: =VLOOKUP($A30,'Master File June-26'!$C$3:$L$670,7,0) -> 0 | H30: =VLOOKUP($A30,'Master File June-26'!$C$3:$L$670,8,0) -> 14 | I30: =VLOOKUP($A30,'Master File June-26'!$C$3:$L$670,9,0) -> 0 | J30: =VLOOKUP($A30,'Master File June-26'!$C$3:$L$670,10,0) -> 0 | K30: =IFERROR((J30/G30*30),0) -> 0 | L30: =IF(K30<H30,"ORDER NOW","IN STOCK") -> ORDER NOW | M30: =IF(K30<H30,"CRITICAL","FOLLOW UP DELIVERY") -> CRITICAL | N30: 1
A31: RM-00628 | B31: Slices cheddar cheese | جبن شدر سلايدر | C31: 200 Grm | D31: Pcs | E31: 5 | F31: =VLOOKUP($A31,'Master File June-26'!$C$3:$L$670,6,0) -> 500 | G31: =VLOOKUP($A31,'Master File June-26'!$C$3:$L$670,7,0) -> 100 | H31: =VLOOKUP($A31,'Master File June-26'!$C$3:$L$670,8,0) -> 14 | I31: =VLOOKUP($A31,'Master File June-26'!$C$3:$L$670,9,0) -> 50 | J31: =VLOOKUP($A31,'Master File June-26'!$C$3:$L$670,10,0) -> 0 | K31: =IFERROR((J31/G31*30),0) -> 0 | L31: =IF(K31<H31,"ORDER NOW","IN STOCK") -> ORDER NOW | M31: =IF(K31<H31,"CRITICAL","FOLLOW UP DELIVERY") -> CRITICAL | N31: 0
A32: RM-00253 | B32: Fresh yeast - خميرة فرش | C32: KG | D32: Pcs | E32: 1 | F32: =VLOOKUP($A32,'Master File June-26'!$C$3:$L$670,6,0) -> 0 | G32: =VLOOKUP($A32,'Master File June-26'!$C$3:$L$670,7,0) -> 0 | H32: =VLOOKUP($A32,'Master File June-26'!$C$3:$L$670,8,0) -> 14 | I32: =VLOOKUP($A32,'Master File June-26'!$C$3:$L$670,9,0) -> 0 | J32: =VLOOKUP($A32,'Master File June-26'!$C$3:$L$670,10,0) -> 0 | K32: =IFERROR((J32/G32*30),0) -> 0 | L32: =IF(K32<H32,"ORDER NOW","IN STOCK") -> ORDER NOW | M32: =IF(K32<H32,"CRITICAL","FOLLOW UP DELIVERY") -> CRITICAL | N32: 1
... A75: RM-00123 | B75: Bob Red Rice Flour طحين الرز | C75: 24*500 GRM | D75: KG | E75: 0.083333333 | F75: =VLOOKUP($A75,'Master File June-26'!$C$3:$L$670,6,0) -> 0 | G75: =VLOOKUP($A75,'Master File June-26'!$C$3:$L$670,7,0) -> 10 | H75: =VLOOKUP($A75,'Master File June-26'!$C$3:$L$670,8,0) -> 14 | I75: =VLOOKUP($A75,'Master File June-26'!$C$3:$L$670,9,0) -> 5 | J75: =VLOOKUP($A75,'Master File June-26'!$C$3:$L$670,10,0) -> 0 | K75: =IFERROR((J75/G75*30),0) -> 0 | L75: =IF(K75<H75,"ORDER NOW","IN STOCK") -> ORDER NOW | M75: =IF(K75<H75,"CRITICAL","FOLLOW UP DELIVERY") -> CRITICAL | N75: 0
A76: RM-00314 | B76: Vanilla Powder بودرة الفانيلا | C76: Pcs | E76: 1 | F76: =VLOOKUP($A76,'Master File June-26'!$C$3:$L$670,6,0) -> 0 | G76: =VLOOKUP($A76,'Master File June-26'!$C$3:$L$670,7,0) -> 2 | H76: =VLOOKUP($A76,'Master File June-26'!$C$3:$L$670,8,0) -> 14 | I76: =VLOOKUP($A76,'Master File June-26'!$C$3:$L$670,9,0) -> 1 | J76: =VLOOKUP($A76,'Master File June-26'!$C$3:$L$670,10,0) -> 0 | K76: =IFERROR((J76/G76*30),0) -> 0 | L76: =IF(K76<H76,"ORDER NOW","IN STOCK") -> ORDER NOW | M76: =IF(K76<H76,"CRITICAL","FOLLOW UP DELIVERY") -> CRITICAL | N76: 0
A77: RM-00328 | B77: Dried banana slices شرائح موز مجفف | C77: Pcs | E77: 1 | F77: =VLOOKUP($A77,'Master File June-26'!$C$3:$L$670,6,0) -> 0 | G77: =VLOOKUP($A77,'Master File June-26'!$C$3:$L$670,7,0) -> 30 | H77: =VLOOKUP($A77,'Master File June-26'!$C$3:$L$670,8,0) -> 14 | I77: =VLOOKUP($A77,'Master File June-26'!$C$3:$L$670,9,0) -> 15 | J77: =VLOOKUP($A77,'Master File June-26'!$C$3:$L$670,10,0) -> 0 | K77: =IFERROR((J77/G77*30),0) -> 0 | L77: =IF(K77<H77,"ORDER NOW","IN STOCK") -> ORDER NOW | M77: =IF(K77<H77,"CRITICAL","FOLLOW UP DELIVERY") -> CRITICAL | N77: 0
A78: RM-00318 | B78: INDOMIE - اندومي | C78: Box | D78: Box | E78: 1 | F78: =VLOOKUP($A78,'Master File June-26'!$C$3:$L$670,6,0) -> 25 | G78: =VLOOKUP($A78,'Master File June-26'!$C$3:$L$670,7,0) -> 25 | H78: =VLOOKUP($A78,'Master File June-26'!$C$3:$L$670,8,0) -> 14 | I78: =VLOOKUP($A78,'Master File June-26'!$C$3:$L$670,9,0) -> 12.5 | J78: =VLOOKUP($A78,'Master File June-26'!$C$3:$L$670,10,0) -> 0 | K78: =IFERROR((J78/G78*30),0) -> 0 | L78: =IF(K78<H78,"ORDER NOW","IN STOCK") -> ORDER NOW | M78: =IF(K78<H78,"CRITICAL","FOLLOW UP DELIVERY") -> CRITICAL | N78: 0
A79: RM-00329 | B79: Dried kiwi slices شرائح كيوي مجففة | C79: Pcs | E79: 1 | F79: =VLOOKUP($A79,'Master File June-26'!$C$3:$L$670,6,0) -> 0 | G79: =VLOOKUP($A79,'Master File June-26'!$C$3:$L$670,7,0) -> 20 | H79: =VLOOKUP($A79,'Master File June-26'!$C$3:$L$670,8,0) -> 14 | I79: =VLOOKUP($A79,'Master File June-26'!$C$3:$L$670,9,0) -> 10 | J79: =VLOOKUP($A79,'Master File June-26'!$C$3:$L$670,10,0) -> 0 | K79: =IFERROR((J79/G79*30),0) -> 0 | L79: =IF(K79<H79,"ORDER NOW","IN STOCK") -> ORDER NOW | M79: =IF(K79<H79,"CRITICAL","FOLLOW UP DELIVERY") -> CRITICAL | N79: 0
A80: RM-00208 | B80: Cardamom Whole JAMBO هيل اخضر | C80: KG | D80: Pcs | E80: 1 | F80: =VLOOKUP($A80,'Master File June-26'!$C$3:$L$670,6,0) -> 5 | G80: =VLOOKUP($A80,'Master File June-26'!$C$3:$L$670,7,0) -> 5 | H80: =VLOOKUP($A80,'Master File June-26'!$C$3:$L$670,8,0) -> 14 | I80: =VLOOKUP($A80,'Master File June-26'!$C$3:$L$670,9,0) -> 2.5 | J80: =VLOOKUP($A80,'Master File June-26'!$C$3:$L$670,10,0) -> 0 | K80: =IFERROR((J80/G80*30),0) -> 0 | L80: =IF(K80<H80,"ORDER NOW","IN STOCK") -> ORDER NOW | M80: =IF(K80<H80,"CRITICAL","FOLLOW UP DELIVERY") -> CRITICAL | N80: 0
A81: RM-00148 | B81: Clove قرنفل | C81: KG | D81: Pcs | E81: 1 | F81: =VLOOKUP($A81,'Master File June-26'!$C$3:$L$670,6,0) -> 1 | G81: =VLOOKUP($A81,'Master File June-26'!$C$3:$L$670,7,0) -> 1 | H81: =VLOOKUP($A81,'Master File June-26'!$C$3:$L$670,8,0) -> 14 | I81: =VLOOKUP($A81,'Master File June-26'!$C$3:$L$670,9,0) -> 0.5 | J81: =VLOOKUP($A81,'Master File June-26'!$C$3:$L$670,10,0) -> 0 | K81: =IFERROR((J81/G81*30),0) -> 0 | L81: =IF(K81<H81,"ORDER NOW","IN STOCK") -> ORDER NOW | M81: =IF(K81<H81,"CRITICAL","FOLLOW UP DELIVERY") -> CRITICAL | N81: 0
A82: RM-00019 | B82: Blue Cheese جبن ازرق | C82: KG | D82: Pcs | E82: 1 | F82: =VLOOKUP($A82,'Master File June-26'!$C$3:$L$670,6,0) -> 10 | G82: =VLOOKUP($A82,'Master File June-26'!$C$3:$L$670,7,0) -> 10 | H82: =VLOOKUP($A82,'Master File June-26'!$C$3:$L$670,8,0) -> 14 | I82: =VLOOKUP($A82,'Master File June-26'!$C$3:$L$670,9,0) -> 5 | J82: =VLOOKUP($A82,'Master File June-26'!$C$3:$L$670,10,0) -> 0 | K82: =IFERROR((J82/G82*30),0) -> 0 | L82: =IF(K82<H82,"ORDER NOW","IN STOCK") -> ORDER NOW | M82: =IF(K82<H82,"CRITICAL","FOLLOW UP DELIVERY") -> CRITICAL | N82: 0
A83: RM-00017 | B83: جبن موزريلا مبشورة Mozzarella cheese shredded | C83: KG | D83: Pcs | E83: 1 | F83: =VLOOKUP($A83,'Master File June-26'!$C$3:$L$670,6,0) -> 15 | G83: =VLOOKUP($A83,'Master File June-26'!$C$3:$L$670,7,0) -> 15 | H83: =VLOOKUP($A83,'Master File June-26'!$C$3:$L$670,8,0) -> 14 | I83: =VLOOKUP($A83,'Master File June-26'!$C$3:$L$670,9,0) -> 7.5 | J83: =VLOOKUP($A83,'Master File June-26'!$C$3:$L$670,10,0) -> 0 | K83: =IFERROR((J83/G83*30),0) -> 0 | L83: =IF(K83<H83,"ORDER NOW","IN STOCK") -> ORDER NOW | M83: =IF(K83<H83,"CRITICAL","FOLLOW UP DELIVERY") -> CRITICAL | N83: 0
A84: RM-00374 | B84: Lamb weston potato dippers بطاطس لامب وستون | C84: Box | D84: Box | E84: 1 | F84: =VLOOKUP($A84,'Master File June-26'!$C$3:$L$670,6,0) -> 20 | G84: =VLOOKUP($A84,'Master File June-26'!$C$3:$L$670,7,0) -> 20 | H84: =VLOOKUP($A84,'Master File June-26'!$C$3:$L$670,8,0) -> 14 | I84: =VLOOKUP($A84,'Master File June-26'!$C$3:$L$670,9,0) -> 10 | J84: =VLOOKUP($A84,'Master File June-26'!$C$3:$L$670,10,0) -> 0 | K84: =IFERROR((J84/G84*30),0) -> 0 | L84: =IF(K84<H84,"ORDER NOW","IN STOCK") -> ORDER NOW | M84: =IF(K84<H84,"CRITICAL","FOLLOW UP DELIVERY") -> CRITICAL | N84: 0
A85: RM-00281 | B85: Red color / Baba 100 لون طعام احمر | C85: Box | D85: Box | E85: 1 | F85: =VLOOKUP($A85,'Master File June-26'!$C$3:$L$670,6,0) -> 1 | G85: =VLOOKUP($A85,'Master File June-26'!$C$3:$L$670,7,0) -> 1 | H85: =VLOOKUP($A85,'Master File June-26'!$C$3:$L$670,8,0) -> 14 | I85: =VLOOKUP($A85,'Master File June-26'!$C$3:$L$670,9,0) -> 0.5 | J85: =VLOOKUP($A85,'Master File June-26'!$C$3:$L$670,10,0) -> 0 | K85: =IFERROR((J85/G85*30),0) -> 0 | L85: =IF(K85<H85,"ORDER NOW","IN STOCK") -> ORDER NOW | M85: =IF(K85<H85,"CRITICAL","FOLLOW UP DELIVERY") -> CRITICAL | N85: 0
A86: RM-00263 | B86: Orange Flavor Powder بودرة طعام لون برتقالي | C86: Pcs | D86: Box | E86: 1 | F86: =VLOOKUP($A86,'Master File June-26'!$C$3:$L$670,6,0) -> 1 | G86: =VLOOKUP($A86,'Master File June-26'!$C$3:$L$670,7,0) -> 1 | H86: =VLOOKUP($A86,'Master File June-26'!$C$3:$L$670,8,0) -> 14 | I86: =VLOOKUP($A86,'Master File June-26'!$C$3:$L$670,9,0) -> 0.5 | J86: =VLOOKUP($A86,'Master File June-26'!$C$3:$L$670,10,0) -> 0 | K86: =IFERROR((J86/G86*30),0) -> 0 | L86: =IF(K86<H86,"ORDER NOW","IN STOCK") -> ORDER NOW | M86: =IF(K86<H86,"CRITICAL","FOLLOW UP DELIVERY") -> CRITICAL | N86: 0
A87: RM-00090 | B87: Cooking Cream Almaraie كريمة طبخ | C87: Box | D87: Box | E87: 1 | F87: =VLOOKUP($A87,'Master File June-26'!$C$3:$L$670,6,0) -> 5 | G87: =VLOOKUP($A87,'Master File June-26'!$C$3:$L$670,7,0) -> 5 | H87: =VLOOKUP($A87,'Master File June-26'!$C$3:$L$670,8,0) -> 14 | I87: =VLOOKUP($A87,'Master File June-26'!$C$3:$L$670,9,0) -> 2.5 | J87: =VLOOKUP($A87,'Master File June-26'!$C$3:$L$670,10,0) -> 0 | K87: =IFERROR((J87/G87*30),0) -> 0 | L87: =IF(K87<H87,"ORDER NOW","IN STOCK") -> ORDER NOW | M87: =IF(K87<H87,"CRITICAL","FOLLOW UP DELIVERY") -> CRITICAL | N87: 0
A88: RM-00646 | B88: long-life milk | حليب طويل الاجل | C88: Box | D88: Box | E88: 1 | F88: =VLOOKUP($A88,'Master File June-26'!$C$3:$L$670,6,0) -> 10 | G88: =VLOOKUP($A88,'Master File June-26'!$C$3:$L$670,7,0) -> 10 | H88: =VLOOKUP($A88,'Master File June-26'!$C$3:$L$670,8,0) -> 14 | I88: =VLOOKUP($A88,'Master File June-26'!$C$3:$L$670,9,0) -> 5 | J88: =VLOOKUP($A88,'Master File June-26'!$C$3:$L$670,10,0) -> 0 | K88: =IFERROR((J88/G88*30),0) -> 0 | L88: =IF(K88<H88,"ORDER NOW","IN STOCK") -> ORDER NOW | M88: =IF(K88<H88,"CRITICAL","FOLLOW UP DELIVERY") -> CRITICAL | N88: 0
A89: RM-00690 | B89: Kashkaval cheese |جبن قشقوانcheese | C89: KG | D89: Pcs | E89: 1 | F89: =VLOOKUP($A89,'Master File June-26'!$C$3:$L$670,6,0) -> 25 | G89: =VLOOKUP($A89,'Master File June-26'!$C$3:$L$670,7,0) -> 25 | H89: =VLOOKUP($A89,'Master File June-26'!$C$3:$L$670,8,0) -> 14 | I89: =VLOOKUP($A89,'Master File June-26'!$C$3:$L$670,9,0) -> 12.5 | J89: =VLOOKUP($A89,'Master File June-26'!$C$3:$L$670,10,0) -> 0 | K89: =IFERROR((J89/G89*30),0) -> 0 | L89: =IF(K89<H89,"ORDER NOW","IN STOCK") -> ORDER NOW | M89: =IF(K89<H89,"CRITICAL","FOLLOW UP DELIVERY") -> CRITICAL | N89: 0
A90: RM-00712 | B90: فليفلة حمراء مطحونة - Red capsicum molases | C90: KG | D90: Pcs | E90: 1 | F90: =VLOOKUP($A90,'Master File June-26'!$C$3:$L$670,6,0) -> 1 | G90: =VLOOKUP($A90,'Master File June-26'!$C$3:$L$670,7,0) -> 1 | H90: =VLOOKUP($A90,'Master File June-26'!$C$3:$L$670,8,0) -> 14 | I90: =VLOOKUP($A90,'Master File June-26'!$C$3:$L$670,9,0) -> 0.5 | J90: =VLOOKUP($A90,'Master File June-26'!$C$3:$L$670,10,0) -> 6 | K90: =IFERROR((J90/G90*30),0) -> 180 | L90: =IF(K90<H90,"ORDER NOW","IN STOCK") -> IN STOCK | M90: =IF(K90<H90,"CRITICAL","FOLLOW UP DELIVERY") -> FOLLOW UP DELIVERY | N90: 0
A91: RM-00302 | B91: Tahina طحينة | C91: KG | D91: Pcs | E91: 1 | F91: =VLOOKUP($A91,'Master File June-26'!$C$3:$L$670,6,0) -> 4 | G91: =VLOOKUP($A91,'Master File June-26'!$C$3:$L$670,7,0) -> 4 | H91: =VLOOKUP($A91,'Master File June-26'!$C$3:$L$670,8,0) -> 14 | I91: =VLOOKUP($A91,'Master File June-26'!$C$3:$L$670,9,0) -> 2 | J91: =VLOOKUP($A91,'Master File June-26'!$C$3:$L$670,10,0) -> 10 | K91: =IFERROR((J91/G91*30),0) -> 75 | L91: =IF(K91<H91,"ORDER NOW","IN STOCK") -> IN STOCK | M91: =IF(K91<H91,"CRITICAL","FOLLOW UP DELIVERY") -> FOLLOW UP DELIVERY | N91: 0
... A94: RM-00184 | B94: Black Seed الحبه السوداء | C94: KG | D94: Pcs | E94: 1 | F94: =VLOOKUP($A94,'Master File June-26'!$C$3:$L$670,6,0) -> 3 | G94: =VLOOKUP($A94,'Master File June-26'!$C$3:$L$670,7,0) -> 3 | H94: =VLOOKUP($A94,'Master File June-26'!$C$3:$L$670,8,0) -> 14 | I94: =VLOOKUP($A94,'Master File June-26'!$C$3:$L$670,9,0) -> 1.5 | J94: =VLOOKUP($A94,'Master File June-26'!$C$3:$L$670,10,0) -> 0 | K94: =IFERROR((J94/G94*30),0) -> 0 | L94: =IF(K94<H94,"ORDER NOW","IN STOCK") -> ORDER NOW | M94: =IF(K94<H94,"CRITICAL","FOLLOW UP DELIVERY") -> CRITICAL | N94: 0
A95: RM-00335 | B95: خميرة مايداغ مجمدة | Frozen Mayadag Yeast | C95: Pcs | E95: 1 | F95: =VLOOKUP($A95,'Master File June-26'!$C$3:$L$670,6,0) -> 0 | G95: =VLOOKUP($A95,'Master File June-26'!$C$3:$L$670,7,0) -> 60 | H95: =VLOOKUP($A95,'Master File June-26'!$C$3:$L$670,8,0) -> 14 | I95: =VLOOKUP($A95,'Master File June-26'!$C$3:$L$670,9,0) -> 30 | J95: =VLOOKUP($A95,'Master File June-26'!$C$3:$L$670,10,0) -> 0 | K95: =IFERROR((J95/G95*30),0) -> 0 | L95: =IF(K95<H95,"ORDER NOW","IN STOCK") -> ORDER NOW | M95: =IF(K95<H95,"CRITICAL","FOLLOW UP DELIVERY") -> CRITICAL | N95: 0
A96: RM-00258 | B96: Vanilla Beans AROME MADAGASCAR | حبوب الفانيلا مدغشقر | C96: 1X25X250 | D96: KG | E96: 0.16 | F96: =VLOOKUP($A96,'Master File June-26'!$C$3:$L$670,6,0) -> 5 | G96: =VLOOKUP($A96,'Master File June-26'!$C$3:$L$670,7,0) -> 31.25 | H96: =VLOOKUP($A96,'Master File June-26'!$C$3:$L$670,8,0) -> 14 | I96: =VLOOKUP($A96,'Master File June-26'!$C$3:$L$670,9,0) -> 15.625 | J96: =VLOOKUP($A96,'Master File June-26'!$C$3:$L$670,10,0) -> 0 | K96: =IFERROR((J96/G96*30),0) -> 0 | L96: =IF(K96<H96,"ORDER NOW","IN STOCK") -> ORDER NOW | M96: =IF(K96<H96,"CRITICAL","FOLLOW UP DELIVERY") -> CRITICAL | N96: 0
A97: RM-00336 | B97: فراولة مجففة | Dried strawberries | C97: Pcs | E97: 1 | F97: =VLOOKUP($A97,'Master File June-26'!$C$3:$L$670,6,0) -> 0 | G97: =VLOOKUP($A97,'Master File June-26'!$C$3:$L$670,7,0) -> 10 | H97: =VLOOKUP($A97,'Master File June-26'!$C$3:$L$670,8,0) -> 14 | I97: =VLOOKUP($A97,'Master File June-26'!$C$3:$L$670,9,0) -> 5 | J97: =VLOOKUP($A97,'Master File June-26'!$C$3:$L$670,10,0) -> 0 | K97: =IFERROR((J97/G97*30),0) -> 0 | L97: =IF(K97<H97,"ORDER NOW","IN STOCK") -> ORDER NOW | M97: =IF(K97<H97,"CRITICAL","FOLLOW UP DELIVERY") -> CRITICAL | N97: 0
A98: RM-00618 | B98: Lemon concentrated | C98: Pcs | E98: 1 | F98: =VLOOKUP($A98,'Master File June-26'!$C$3:$L$670,6,0) -> 0 | G98: =VLOOKUP($A98,'Master File June-26'!$C$3:$L$670,7,0) -> 10 | H98: =VLOOKUP($A98,'Master File June-26'!$C$3:$L$670,8,0) -> 14 | I98: =VLOOKUP($A98,'Master File June-26'!$C$3:$L$670,9,0) -> 5 | J98: =VLOOKUP($A98,'Master File June-26'!$C$3:$L$670,10,0) -> 0 | K98: =IFERROR((J98/G98*30),0) -> 0 | L98: =IF(K98<H98,"ORDER NOW","IN STOCK") -> ORDER NOW | M98: =IF(K98<H98,"CRITICAL","FOLLOW UP DELIVERY") -> CRITICAL | N98: 0
A99: RM-00675 | B99: صلصة بيتزا فرشلي / FRESHLY PIZZA SAUCE | C99: Pcs | E99: 1 | F99: =VLOOKUP($A99,'Master File June-26'!$C$3:$L$670,6,0) -> 0 | G99: =VLOOKUP($A99,'Master File June-26'!$C$3:$L$670,7,0) -> 10 | H99: =VLOOKUP($A99,'Master File June-26'!$C$3:$L$670,8,0) -> 14 | I99: =VLOOKUP($A99,'Master File June-26'!$C$3:$L$670,9,0) -> 5 | J99: =VLOOKUP($A99,'Master File June-26'!$C$3:$L$670,10,0) -> 0 | K99: =IFERROR((J99/G99*30),0) -> 0 | L99: =IF(K99<H99,"ORDER NOW","IN STOCK") -> ORDER NOW | M99: =IF(K99<H99,"CRITICAL","FOLLOW UP DELIVERY") -> CRITICAL | N99: 0
A100: RM-00676 | B100: جبنة كيري بلوك / KIRI CHEESE CTN | C100: Pcs | E100: 1 | F100: =VLOOKUP($A100,'Master File June-26'!$C$3:$L$670,6,0) -> 0 | G100: =VLOOKUP($A100,'Master File June-26'!$C$3:$L$670,7,0) -> 10 | H100: =VLOOKUP($A100,'Master File June-26'!$C$3:$L$670,8,0) -> 14 | I100: =VLOOKUP($A100,'Master File June-26'!$C$3:$L$670,9,0) -> 5 | J100: =VLOOKUP($A100,'Master File June-26'!$C$3:$L$670,10,0) -> 3.2 | K100: =IFERROR((J100/G100*30),0) -> 9.6 | L100: =IF(K100<H100,"ORDER NOW","IN STOCK") -> ORDER NOW | M100: =IF(K100<H100,"CRITICAL","FOLLOW UP DELIVERY") -> CRITICAL | N100: 0
A101: RM-00697 | B101: CHEDAR CHEESE - PRESIDENT |جبن تشيدر - بريزيدنت | C101: Pcs | E101: 1 | F101: =VLOOKUP($A101,'Master File June-26'!$C$3:$L$670,6,0) -> 0 | G101: =VLOOKUP($A101,'Master File June-26'!$C$3:$L$670,7,0) -> 10 | H101: =VLOOKUP($A101,'Master File June-26'!$C$3:$L$670,8,0) -> 14 | I101: =VLOOKUP($A101,'Master File June-26'!$C$3:$L$670,9,0) -> 5 | J101: =VLOOKUP($A101,'Master File June-26'!$C$3:$L$670,10,0) -> 0 | K101: =IFERROR((J101/G101*30),0) -> 0 | L101: =IF(K101<H101,"ORDER NOW","IN STOCK") -> ORDER NOW | M101: =IF(K101<H101,"CRITICAL","FOLLOW UP DELIVERY") -> CRITICAL | N101: 0
A102: RM-00698 | B102: Sunflower seeds |دوار الشمس مقشر | C102: Pcs | E102: 1 | F102: =VLOOKUP($A102,'Master File June-26'!$C$3:$L$670,6,0) -> 0 | G102: =VLOOKUP($A102,'Master File June-26'!$C$3:$L$670,7,0) -> 5 | H102: =VLOOKUP($A102,'Master File June-26'!$C$3:$L$670,8,0) -> 14 | I102: =VLOOKUP($A102,'Master File June-26'!$C$3:$L$670,9,0) -> 2.5 | J102: =VLOOKUP($A102,'Master File June-26'!$C$3:$L$670,10,0) -> 0 | K102: =IFERROR((J102/G102*30),0) -> 0 | L102: =IF(K102<H102,"ORDER NOW","IN STOCK") -> ORDER NOW | M102: =IF(K102<H102,"CRITICAL","FOLLOW UP DELIVERY") -> CRITICAL | N102: 0
A103: RM-00699 | B103: Pumpkin seeds |حب قرع مقشر | C103: Pcs | E103: 1 | F103: =VLOOKUP($A103,'Master File June-26'!$C$3:$L$670,6,0) -> 0 | G103: =VLOOKUP($A103,'Master File June-26'!$C$3:$L$670,7,0) -> 5 | H103: =VLOOKUP($A103,'Master File June-26'!$C$3:$L$670,8,0) -> 14 | I103: =VLOOKUP($A103,'Master File June-26'!$C$3:$L$670,9,0) -> 2.5 | J103: =VLOOKUP($A103,'Master File June-26'!$C$3:$L$670,10,0) -> 0 | K103: =IFERROR((J103/G103*30),0) -> 0 | L103: =IF(K103<H103,"ORDER NOW","IN STOCK") -> ORDER NOW | M103: =IF(K103<H103,"CRITICAL","FOLLOW UP DELIVERY") -> CRITICAL | N103: 0
A104: RM-00701 | B104: TOMATO PESTO - ORIET GRADENS |بيستو بالطماطم | C104: Pcs | E104: 1 | F104: =VLOOKUP($A104,'Master File June-26'!$C$3:$L$670,6,0) -> 0 | G104: =VLOOKUP($A104,'Master File June-26'!$C$3:$L$670,7,0) -> 10 | H104: =VLOOKUP($A104,'Master File June-26'!$C$3:$L$670,8,0) -> 14 | I104: =VLOOKUP($A104,'Master File June-26'!$C$3:$L$670,9,0) -> 5 | J104: =VLOOKUP($A104,'Master File June-26'!$C$3:$L$670,10,0) -> 0 | K104: =IFERROR((J104/G104*30),0) -> 0 | L104: =IF(K104<H104,"ORDER NOW","IN STOCK") -> ORDER NOW | M104: =IF(K104<H104,"CRITICAL","FOLLOW UP DELIVERY") -> CRITICAL | N104: 0
A105: RM-00672 | B105: Maboj Carrot | معبوج نورة جزر | C105: 1 Pcs X 500 G | D105: Pcs | E105: 2 | F105: =VLOOKUP($A105,'Master File June-26'!$C$3:$L$670,6,0) -> 44 | G105: =VLOOKUP($A105,'Master File June-26'!$C$3:$L$670,7,0) -> 22 | H105: =VLOOKUP($A105,'Master File June-26'!$C$3:$L$670,8,0) -> 14 | I105: =VLOOKUP($A105,'Master File June-26'!$C$3:$L$670,9,0) -> 11 | J105: =VLOOKUP($A105,'Master File June-26'!$C$3:$L$670,10,0) -> 0 | K105: =IFERROR((J105/G105*30),0) -> 0 | L105: =IF(K105<H105,"ORDER NOW","IN STOCK") -> ORDER NOW | M105: =IF(K105<H105,"CRITICAL","FOLLOW UP DELIVERY") -> CRITICAL | N105: 0
A106: RM-00133 | B106: Maznah coffee قهوة مزنة | C106: 1 Box X 12 Pcs X 800 Grm | D106: Box | E106: 0.10416667 | F106: =VLOOKUP($A106,'Master File June-26'!$C$3:$L$670,6,0) -> 70 | G106: =VLOOKUP($A106,'Master File June-26'!$C$3:$L$670,7,0) -> 672 | H106: =VLOOKUP($A106,'Master File June-26'!$C$3:$L$670,8,0) -> 14 | I106: =VLOOKUP($A106,'Master File June-26'!$C$3:$L$670,9,0) -> 336 | J106: =VLOOKUP($A106,'Master File June-26'!$C$3:$L$670,10,0) -> 0 | K106: =IFERROR((J106/G106*30),0) -> 0 | L106: =IF(K106<H106,"ORDER NOW","IN STOCK") -> ORDER NOW | M106: =IF(K106<H106,"CRITICAL","FOLLOW UP DELIVERY") -> CRITICAL | N106: 0
A107: RM-00442 | B107: CHEFMATE CLEAR LIQUID SHORTINING OIL زيت شيف ميت | C107: Can | D107: Box | E107: 0.057803468 | F107: =VLOOKUP($A107,'Master File June-26'!$C$3:$L$670,6,0) -> 25 | G107: =VLOOKUP($A107,'Master File June-26'!$C$3:$L$670,7,0) -> 432.5 | H107: =VLOOKUP($A107,'Master File June-26'!$C$3:$L$670,8,0) -> 14 | I107: =VLOOKUP($A107,'Master File June-26'!$C$3:$L$670,9,0) -> 216.25 | J107: =VLOOKUP($A107,'Master File June-26'!$C$3:$L$670,10,0) -> 208.8 | K107: =IFERROR((J107/G107*30),0) -> 14.483237 | L107: =IF(K107<H107,"ORDER NOW","IN STOCK") -> IN STOCK | M107: =IF(K107<H107,"CRITICAL","FOLLOW UP DELIVERY") -> FOLLOW UP DELIVERY | N107: 0
A108: RM-00231 | B108: Cumin Powder كمون مطحون | C108: Box | D108: Box | E108: 1 | F108: =VLOOKUP($A108,'Master File June-26'!$C$3:$L$670,6,0) -> 5 | G108: =VLOOKUP($A108,'Master File June-26'!$C$3:$L$670,7,0) -> 5 | H108: =VLOOKUP($A108,'Master File June-26'!$C$3:$L$670,8,0) -> 14 | I108: =VLOOKUP($A108,'Master File June-26'!$C$3:$L$670,9,0) -> 2.5 | J108: =VLOOKUP($A108,'Master File June-26'!$C$3:$L$670,10,0) -> 0 | K108: =IFERROR((J108/G108*30),0) -> 0 | L108: =IF(K108<H108,"ORDER NOW","IN STOCK") -> ORDER NOW | M108: =IF(K108<H108,"CRITICAL","FOLLOW UP DELIVERY") -> CRITICAL | N108: 1
A109: RM-00369 | B109: Frozen Beans بازلاء وجزر مجمد | C109: Box | D109: Box | E109: 1 | F109: =VLOOKUP($A109,'Master File June-26'!$C$3:$L$670,6,0) -> 10 | G109: =VLOOKUP($A109,'Master File June-26'!$C$3:$L$670,7,0) -> 10 | H109: =VLOOKUP($A109,'Master File June-26'!$C$3:$L$670,8,0) -> 14 | I109: =VLOOKUP($A109,'Master File June-26'!$C$3:$L$670,9,0) -> 5 | J109: =VLOOKUP($A109,'Master File June-26'!$C$3:$L$670,10,0) -> 0 | K109: =IFERROR((J109/G109*30),0) -> 0 | L109: =IF(K109<H109,"ORDER NOW","IN STOCK") -> ORDER NOW | M109: =IF(K109<H109,"CRITICAL","FOLLOW UP DELIVERY") -> CRITICAL | N109: 1
A110: RM-00605 | B110: Shaalan amber cedar - ارز الشعلان عنبر | C110: KG | D110: Box | E110: 0.1 | F110: =VLOOKUP($A110,'Master File June-26'!$C$3:$L$670,6,0) -> 100 | G110: =VLOOKUP($A110,'Master File June-26'!$C$3:$L$670,7,0) -> 1000 | H110: =VLOOKUP($A110,'Master File June-26'!$C$3:$L$670,8,0) -> 14 | I110: =VLOOKUP($A110,'Master File June-26'!$C$3:$L$670,9,0) -> 500 | J110: =VLOOKUP($A110,'Master File June-26'!$C$3:$L$670,10,0) -> 80 | K110: =IFERROR((J110/G110*30),0) -> 2.4 | L110: =IF(K110<H110,"ORDER NOW","IN STOCK") -> ORDER NOW | M110: =IF(K110<H110,"CRITICAL","FOLLOW UP DELIVERY") -> CRITICAL | N110: 0
A111: RM-00523 | B111: Berain 40*330 ML | مياه بيرين 330م*40 | C111: 1 BOX 40*330 ML PET | D111: bag | E111: 0.025 | F111: =VLOOKUP($A111,'Master File June-26'!$C$3:$L$670,6,0) -> 149 | G111: =VLOOKUP($A111,'Master File June-26'!$C$3:$L$670,7,0) -> 5960 | H111: =VLOOKUP($A111,'Master File June-26'!$C$3:$L$670,8,0) -> 14 | I111: =VLOOKUP($A111,'Master File June-26'!$C$3:$L$670,9,0) -> 2980 | J111: =VLOOKUP($A111,'Master File June-26'!$C$3:$L$670,10,0) -> 0 | K111: =IFERROR((J111/G111*30),0) -> 0 | L111: =IF(K111<H111,"ORDER NOW","IN STOCK") -> ORDER NOW | M111: =IF(K111<H111,"CRITICAL","FOLLOW UP DELIVERY") -> CRITICAL | N111: 1
A112: RM-00243 | B112: Biscuit Filling With Crunchy Pieces Ripieno | حشوة البسكويت مع كسر | C112: 1 box x 2 tin x 5 kg | D112: Box | E112: 0.1 | F112: =VLOOKUP($A112,'Master File June-26'!$C$3:$L$670,6,0) -> 160 | G112: =VLOOKUP($A112,'Master File June-26'!$C$3:$L$670,7,0) -> 1600 | H112: =VLOOKUP($A112,'Master File June-26'!$C$3:$L$670,8,0) -> 14 | I112: =VLOOKUP($A112,'Master File June-26'!$C$3:$L$670,9,0) -> 800 | J112: =VLOOKUP($A112,'Master File June-26'!$C$3:$L$670,10,0) -> 0 | K112: =IFERROR((J112/G112*30),0) -> 0 | L112: =IF(K112<H112,"ORDER NOW","IN STOCK") -> ORDER NOW | M112: =IF(K112<H112,"CRITICAL","FOLLOW UP DELIVERY") -> CRITICAL | N112: 1
A113: RM-00517 | B113: Meranda ميراندا برتقال علبة | C113: Box | D113: Box | E113: 0.033333333 | F113: =VLOOKUP($A113,'Master File June-26'!$C$3:$L$670,6,0) -> 10 | G113: =VLOOKUP($A113,'Master File June-26'!$C$3:$L$670,7,0) -> 300 | H113: =VLOOKUP($A113,'Master File June-26'!$C$3:$L$670,8,0) -> 14 | I113: =VLOOKUP($A113,'Master File June-26'!$C$3:$L$670,9,0) -> 150 | J113: =VLOOKUP($A113,'Master File June-26'!$C$3:$L$670,10,0) -> 120 | K113: =IFERROR((J113/G113*30),0) -> 12 | L113: =IF(K113<H113,"ORDER NOW","IN STOCK") -> ORDER NOW | M113: =IF(K113<H113,"CRITICAL","FOLLOW UP DELIVERY") -> CRITICAL | N113: 0
A114: RM-00097 | B114: Whipping cream كريمة خفق | C114: 1 Box X 12 Bottle X 1 ltr | D114: Box | E114: 0.083333333 | F114: =VLOOKUP($A114,'Master File June-26'!$C$3:$L$670,6,0) -> 608 | G114: =VLOOKUP($A114,'Master File June-26'!$C$3:$L$670,7,0) -> 7296 | H114: =VLOOKUP($A114,'Master File June-26'!$C$3:$L$670,8,0) -> 14 | I114: =VLOOKUP($A114,'Master File June-26'!$C$3:$L$670,9,0) -> 3648 | J114: =VLOOKUP($A114,'Master File June-26'!$C$3:$L$670,10,0) -> 2400 | K114: =IFERROR((J114/G114*30),0) -> 9.8684211 | L114: =IF(K114<H114,"ORDER NOW","IN STOCK") -> ORDER NOW | M114: =IF(K114<H114,"CRITICAL","FOLLOW UP DELIVERY") -> CRITICAL | N114: 0
A115: RM-00424 | B115: Indian Cashew كاجو هندي | C115: 1 Tin X 20 Kg | D115: Pcs | E115: 0.05 | F115: =VLOOKUP($A115,'Master File June-26'!$C$3:$L$670,6,0) -> 60 | G115: =VLOOKUP($A115,'Master File June-26'!$C$3:$L$670,7,0) -> 1200 | H115: =VLOOKUP($A115,'Master File June-26'!$C$3:$L$670,8,0) -> 14 | I115: =VLOOKUP($A115,'Master File June-26'!$C$3:$L$670,9,0) -> 600 | J115: =VLOOKUP($A115,'Master File June-26'!$C$3:$L$670,10,0) -> 0 | K115: =IFERROR((J115/G115*30),0) -> 0 | L115: =IF(K115<H115,"ORDER NOW","IN STOCK") -> ORDER NOW | M115: =IF(K115<H115,"CRITICAL","FOLLOW UP DELIVERY") -> CRITICAL | N115: 0
A116: RM-00050 | B116: Happy cao Cocoa powder بودرة كاكاو هابي كاو | C116: 1 Bag X 10 Kg | D116: bag | E116: 0.1 | F116: =VLOOKUP($A116,'Master File June-26'!$C$3:$L$670,6,0) -> 30.25 | G116: =VLOOKUP($A116,'Master File June-26'!$C$3:$L$670,7,0) -> 302.5 | H116: =VLOOKUP($A116,'Master File June-26'!$C$3:$L$670,8,0) -> 14 | I116: =VLOOKUP($A116,'Master File June-26'!$C$3:$L$670,9,0) -> 151.25 | J116: =VLOOKUP($A116,'Master File June-26'!$C$3:$L$670,10,0) -> 10 | K116: =IFERROR((J116/G116*30),0) -> 0.99173554 | L116: =IF(K116<H116,"ORDER NOW","IN STOCK") -> ORDER NOW | M116: =IF(K116<H116,"CRITICAL","FOLLOW UP DELIVERY") -> CRITICAL | N116: 1
... A133: RM-00009 | B133: Cheese Cream | جبن كريمي | C133: 1 Box X 4 Pack X 1650 Grm | D133: Box | E133: 0.15151515 | F133: =VLOOKUP($A133,'Master File June-26'!$C$3:$L$670,6,0) -> 1700 | G133: =VLOOKUP($A133,'Master File June-26'!$C$3:$L$670,7,0) -> 11220 | H133: =VLOOKUP($A133,'Master File June-26'!$C$3:$L$670,8,0) -> 14 | I133: =VLOOKUP($A133,'Master File June-26'!$C$3:$L$670,9,0) -> 5610 | J133: =VLOOKUP($A133,'Master File June-26'!$C$3:$L$670,10,0) -> 3320 | K133: =IFERROR((J133/G133*30),0) -> 8.8770053 | L133: =IF(K133<H133,"ORDER NOW","IN STOCK") -> ORDER NOW | M133: =IF(K133<H133,"CRITICAL","FOLLOW UP DELIVERY") -> CRITICAL | N133: 1
A134: RM-00689 | B134: reeses chocolate / شوكولاته ريسز | C134: Pcs | E134: 1 | F134: =VLOOKUP($A134,'Master File June-26'!$C$3:$L$670,6,0) -> 0 | G134: =VLOOKUP($A134,'Master File June-26'!$C$3:$L$670,7,0) -> 10 | H134: =VLOOKUP($A134,'Master File June-26'!$C$3:$L$670,8,0) -> 14 | I134: =VLOOKUP($A134,'Master File June-26'!$C$3:$L$670,9,0) -> 5 | J134: =VLOOKUP($A134,'Master File June-26'!$C$3:$L$670,10,0) -> 0 | K134: =IFERROR((J134/G134*30),0) -> 0 | L134: =IF(K134<H134,"ORDER NOW","IN STOCK") -> ORDER NOW | M134: =IF(K134<H134,"CRITICAL","FOLLOW UP DELIVERY") -> CRITICAL | N134: 1
A135: RM-00077 | B135: Milk chocolate drops 37% ( CREA ) شوكولاتة بالحليب اقراص ( كريا ) | C135: 1 Box X 2 Bag X 6 KG | D135: Box | E135: 0.083333333 | F135: =VLOOKUP($A135,'Master File June-26'!$C$3:$L$670,6,0) -> 2700 | G135: =VLOOKUP($A135,'Master File June-26'!$C$3:$L$670,7,0) -> 32400 | H135: =VLOOKUP($A135,'Master File June-26'!$C$3:$L$670,8,0) -> 14 | I135: =VLOOKUP($A135,'Master File June-26'!$C$3:$L$670,9,0) -> 16200 | J135: =VLOOKUP($A135,'Master File June-26'!$C$3:$L$670,10,0) -> 9168 | K135: =IFERROR((J135/G135*30),0) -> 8.4888889 | L135: =IF(K135<H135,"ORDER NOW","IN STOCK") -> ORDER NOW | M135: =IF(K135<H135,"CRITICAL","FOLLOW UP DELIVERY") -> CRITICAL | N135: 1
A136: RM-00077 | B136: Milk chocolate drops 37% ( CREA )شوكولاتة بالحليب اقراص ( كريا ) | C136: 1 Box X 2 Bag X 6 KG | D136: Box | E136: 0.083333333 | F136: =VLOOKUP($A136,'Master File June-26'!$C$3:$L$670,6,0) -> 2700 | G136: =VLOOKUP($A136,'Master File June-26'!$C$3:$L$670,7,0) -> 32400 | H136: =VLOOKUP($A136,'Master File June-26'!$C$3:$L$670,8,0) -> 14 | I136: =VLOOKUP($A136,'Master File June-26'!$C$3:$L$670,9,0) -> 16200 | J136: =VLOOKUP($A136,'Master File June-26'!$C$3:$L$670,10,0) -> 9168 | K136: =IFERROR((J136/G136*30),0) -> 8.4888889 | L136: =IF(K136<H136,"ORDER NOW","IN STOCK") -> ORDER NOW | M136: =IF(K136<H136,"CRITICAL","FOLLOW UP DELIVERY") -> CRITICAL | N136: 1
A137: RM-00520 | B137: Monin Vanilla Syrup 1L مونین شراب الفانیلا 1لتر | C137: 1 Box X 6 Bottle X 1 Ltr | D137: Box | E137: 0.16666667 | F137: =VLOOKUP($A137,'Master File June-26'!$C$3:$L$670,6,0) -> 64.5 | G137: =VLOOKUP($A137,'Master File June-26'!$C$3:$L$670,7,0) -> 387 | H137: =VLOOKUP($A137,'Master File June-26'!$C$3:$L$670,8,0) -> 14 | I137: =VLOOKUP($A137,'Master File June-26'!$C$3:$L$670,9,0) -> 193.5 | J137: =VLOOKUP($A137,'Master File June-26'!$C$3:$L$670,10,0) -> 864 | K137: =IFERROR((J137/G137*30),0) -> 66.976744 | L137: =IF(K137<H137,"ORDER NOW","IN STOCK") -> IN STOCK | M137: =IF(K137<H137,"CRITICAL","FOLLOW UP DELIVERY") -> FOLLOW UP DELIVERY | N137: 1
A138: RM-00158 | B138: English breakfast tea شاي الفطور الانجليزي | C138: 1 Box X 24 Pckt X 100 Pcs | D138: Box | E138: 0.00041666667 | F138: =VLOOKUP($A138,'Master File June-26'!$C$3:$L$670,6,0) -> 60.5 | G138: =VLOOKUP($A138,'Master File June-26'!$C$3:$L$670,7,0) -> 1452 | H138: =VLOOKUP($A138,'Master File June-26'!$C$3:$L$670,8,0) -> 14 | I138: =VLOOKUP($A138,'Master File June-26'!$C$3:$L$670,9,0) -> 726 | J138: =VLOOKUP($A138,'Master File June-26'!$C$3:$L$670,10,0) -> 2 | K138: =IFERROR((J138/G138*30),0) -> 0.041322314 | L138: =IF(K138<H138,"ORDER NOW","IN STOCK") -> ORDER NOW | M138: =IF(K138<H138,"CRITICAL","FOLLOW UP DELIVERY") -> CRITICAL | N138: 0
A139: RM-00068 | B139: Kunafa Chocolate Bar | تشوكلت بار كنافة | C139: 1 Pcs. | D139: Pcs | E139: 0.002 | F139: =VLOOKUP($A139,'Master File June-26'!$C$3:$L$670,6,0) -> 180 | G139: =VLOOKUP($A139,'Master File June-26'!$C$3:$L$670,7,0) -> 8640 | H139: =VLOOKUP($A139,'Master File June-26'!$C$3:$L$670,8,0) -> 14 | I139: =VLOOKUP($A139,'Master File June-26'!$C$3:$L$670,9,0) -> 4320 | J139: =VLOOKUP($A139,'Master File June-26'!$C$3:$L$670,10,0) -> 1014 | K139: =IFERROR((J139/G139*30),0) -> 3.5208333 | L139: =IF(K139<H139,"ORDER NOW","IN STOCK") -> ORDER NOW | M139: =IF(K139<H139,"CRITICAL","FOLLOW UP DELIVERY") -> CRITICAL | N139: 1
A140: RM-00617 | B140: Saffaron Food Color - baba لون طعام زعفران - بابا | C140: Pcs | E140: 1 | F140: =VLOOKUP($A140,'Master File June-26'!$C$3:$L$670,6,0) -> 0 | G140: =VLOOKUP($A140,'Master File June-26'!$C$3:$L$670,7,0) -> 10 | H140: =VLOOKUP($A140,'Master File June-26'!$C$3:$L$670,8,0) -> 14 | I140: =VLOOKUP($A140,'Master File June-26'!$C$3:$L$670,9,0) -> 5 | J140: =VLOOKUP($A140,'Master File June-26'!$C$3:$L$670,10,0) -> 0 | K140: =IFERROR((J140/G140*30),0) -> 0 | L140: =IF(K140<H140,"ORDER NOW","IN STOCK") -> ORDER NOW | M140: =IF(K140<H140,"CRITICAL","FOLLOW UP DELIVERY") -> CRITICAL | N140: 0
A141: RM-00071 | B141: Chocolate sticks BELCOSTICKS 44% 8CM | اصابع الشوكولاتة | C141: box X15 pcs x 1.6 kg | D141: Box | E141: 0.041666667 | F141: =VLOOKUP($A141,'Master File June-26'!$C$3:$L$670,6,0) -> 12 | G141: =VLOOKUP($A141,'Master File June-26'!$C$3:$L$670,7,0) -> 288 | H141: =VLOOKUP($A141,'Master File June-26'!$C$3:$L$670,8,0) -> 14 | I141: =VLOOKUP($A141,'Master File June-26'!$C$3:$L$670,9,0) -> 144 | J141: =VLOOKUP($A141,'Master File June-26'!$C$3:$L$670,10,0) -> 0 | K141: =IFERROR((J141/G141*30),0) -> 0 | L141: =IF(K141<H141,"ORDER NOW","IN STOCK") -> ORDER NOW | M141: =IF(K141<H141,"CRITICAL","FOLLOW UP DELIVERY") -> CRITICAL | N141: 0
A142: RM-00225 | B142: Lotus Biscoff بسكويت لوتس | C142: 1 Box X 1875 Grm | D142: Box | E142: 0.53333333 | F142: =VLOOKUP($A142,'Master File June-26'!$C$3:$L$670,6,0) -> 300 | G142: =VLOOKUP($A142,'Master File June-26'!$C$3:$L$670,7,0) -> 562.5 | H142: =VLOOKUP($A142,'Master File June-26'!$C$3:$L$670,8,0) -> 14 | I142: =VLOOKUP($A142,'Master File June-26'!$C$3:$L$670,9,0) -> 281.25 | J142: =VLOOKUP($A142,'Master File June-26'!$C$3:$L$670,10,0) -> 0 | K142: =IFERROR((J142/G142*30),0) -> 0 | L142: =IF(K142<H142,"ORDER NOW","IN STOCK") -> ORDER NOW | M142: =IF(K142<H142,"CRITICAL","FOLLOW UP DELIVERY") -> CRITICAL | N142: 0
A143: RM-00109 | B143: Sour cream | كريمة حامضة | C143: 1 box x 10 pcs x 1 kg | D143: Box | E143: 0.1 | F143: =VLOOKUP($A143,'Master File June-26'!$C$3:$L$670,6,0) -> 60 | G143: =VLOOKUP($A143,'Master File June-26'!$C$3:$L$670,7,0) -> 600 | H143: =VLOOKUP($A143,'Master File June-26'!$C$3:$L$670,8,0) -> 14 | I143: =VLOOKUP($A143,'Master File June-26'!$C$3:$L$670,9,0) -> 300 | J143: =VLOOKUP($A143,'Master File June-26'!$C$3:$L$670,10,0) -> 0 | K143: =IFERROR((J143/G143*30),0) -> 0 | L143: =IF(K143<H143,"ORDER NOW","IN STOCK") -> ORDER NOW | M143: =IF(K143<H143,"CRITICAL","FOLLOW UP DELIVERY") -> CRITICAL | N143: 1
A144: RM-00020 | B144: Westminster White Mild Cheddar Cheese جبنة شيدر ابيض و | C144: KG | D144: Pcs | E144: 1 | F144: =VLOOKUP($A144,'Master File June-26'!$C$3:$L$670,6,0) -> 10 | G144: =VLOOKUP($A144,'Master File June-26'!$C$3:$L$670,7,0) -> 10 | H144: =VLOOKUP($A144,'Master File June-26'!$C$3:$L$670,8,0) -> 14 | I144: =VLOOKUP($A144,'Master File June-26'!$C$3:$L$670,9,0) -> 5 | J144: =VLOOKUP($A144,'Master File June-26'!$C$3:$L$670,10,0) -> 0 | K144: =IFERROR((J144/G144*30),0) -> 0 | L144: =IF(K144<H144,"ORDER NOW","IN STOCK") -> ORDER NOW | M144: =IF(K144<H144,"CRITICAL","FOLLOW UP DELIVERY") -> CRITICAL | N144: 0
A145: RM-00583 | B145: Almond Milk حليب لوز | C145: 1 Box X 8 Bottle X 1 Ltr | D145: Box | E145: 0.125 | F145: =VLOOKUP($A145,'Master File June-26'!$C$3:$L$670,6,0) -> 70.5 | G145: =VLOOKUP($A145,'Master File June-26'!$C$3:$L$670,7,0) -> 564 | H145: =VLOOKUP($A145,'Master File June-26'!$C$3:$L$670,8,0) -> 14 | I145: =VLOOKUP($A145,'Master File June-26'!$C$3:$L$670,9,0) -> 282 | J145: =VLOOKUP($A145,'Master File June-26'!$C$3:$L$670,10,0) -> 120 | K145: =IFERROR((J145/G145*30),0) -> 6.3829787 | L145: =IF(K145<H145,"ORDER NOW","IN STOCK") -> ORDER NOW | M145: =IF(K145<H145,"CRITICAL","FOLLOW UP DELIVERY") -> CRITICAL | N145: 1
A146: RM-00490 | B146: Sasa Salt ملح ساسا | C146: 1 Box X 24 Pcs X 700 Grm | D146: Box | E146: 0.05952381 | F146: =VLOOKUP($A146,'Master File June-26'!$C$3:$L$670,6,0) -> 16 | G146: =VLOOKUP($A146,'Master File June-26'!$C$3:$L$670,7,0) -> 268.8 | H146: =VLOOKUP($A146,'Master File June-26'!$C$3:$L$670,8,0) -> 14 | I146: =VLOOKUP($A146,'Master File June-26'!$C$3:$L$670,9,0) -> 134.4 | J146: =VLOOKUP($A146,'Master File June-26'!$C$3:$L$670,10,0) -> 0 | K146: =IFERROR((J146/G146*30),0) -> 0 | L146: =IF(K146<H146,"ORDER NOW","IN STOCK") -> ORDER NOW | M146: =IF(K146<H146,"CRITICAL","FOLLOW UP DELIVERY") -> CRITICAL | N146: 1
A147: RM-00688 | B147: زيتون كالاماتا / kalamon olives | C147: 1 Pcs X 800 Grm | D147: Pcs | E147: 1.25 | F147: =VLOOKUP($A147,'Master File June-26'!$C$3:$L$670,6,0) -> 40 | G147: =VLOOKUP($A147,'Master File June-26'!$C$3:$L$670,7,0) -> 32 | H147: =VLOOKUP($A147,'Master File June-26'!$C$3:$L$670,8,0) -> 14 | I147: =VLOOKUP($A147,'Master File June-26'!$C$3:$L$670,9,0) -> 16 | J147: =VLOOKUP($A147,'Master File June-26'!$C$3:$L$670,10,0) -> 17 | K147: =IFERROR((J147/G147*30),0) -> 15.9375 | L147: =IF(K147<H147,"ORDER NOW","IN STOCK") -> IN STOCK | M147: =IF(K147<H147,"CRITICAL","FOLLOW UP DELIVERY") -> FOLLOW UP DELIVERY | N147: 1
A148: RM-00065 | B148: BELGIAN CHOCOLATE MILK 35% -بلشوكو شوكلاته بالحليب | C148: 1 box x 12 kg | D148: Box | E148: 0.1 | F148: =VLOOKUP($A148,'Master File June-26'!$C$3:$L$670,6,0) -> 80 | G148: =VLOOKUP($A148,'Master File June-26'!$C$3:$L$670,7,0) -> 800 | H148: =VLOOKUP($A148,'Master File June-26'!$C$3:$L$670,8,0) -> 14 | I148: =VLOOKUP($A148,'Master File June-26'!$C$3:$L$670,9,0) -> 400 | J148: =VLOOKUP($A148,'Master File June-26'!$C$3:$L$670,10,0) -> 0 | K148: =IFERROR((J148/G148*30),0) -> 0 | L148: =IF(K148<H148,"ORDER NOW","IN STOCK") -> ORDER NOW | M148: =IF(K148<H148,"CRITICAL","FOLLOW UP DELIVERY") -> CRITICAL | N148: 0
A149: RM-00499 | B149: Diet Sugar Sachetاظرف سكر دايت | C149: 1 Box X 24 Pckt X 50 Pcs | D149: Box | E149: 0.00083333333 | F149: =VLOOKUP($A149,'Master File June-26'!$C$3:$L$670,6,0) -> 22 | G149: =VLOOKUP($A149,'Master File June-26'!$C$3:$L$670,7,0) -> 528 | H149: =VLOOKUP($A149,'Master File June-26'!$C$3:$L$670,8,0) -> 14 | I149: =VLOOKUP($A149,'Master File June-26'!$C$3:$L$670,9,0) -> 264 | J149: =VLOOKUP($A149,'Master File June-26'!$C$3:$L$670,10,0) -> 0 | K149: =IFERROR((J149/G149*30),0) -> 0 | L149: =IF(K149<H149,"ORDER NOW","IN STOCK") -> ORDER NOW | M149: =IF(K149<H149,"CRITICAL","FOLLOW UP DELIVERY") -> CRITICAL | N149: 0
A150: RM-00503 | B150: Suger Sachet Breehantاظرف سكر بريهانت | C150: 1 Box X 1000 Sachet | D150: Box | E150: 0.001 | F150: =VLOOKUP($A150,'Master File June-26'!$C$3:$L$670,6,0) -> 24 | G150: =VLOOKUP($A150,'Master File June-26'!$C$3:$L$670,7,0) -> 24000 | H150: =VLOOKUP($A150,'Master File June-26'!$C$3:$L$670,8,0) -> 14 | I150: =VLOOKUP($A150,'Master File June-26'!$C$3:$L$670,9,0) -> 12000 | J150: =VLOOKUP($A150,'Master File June-26'!$C$3:$L$670,10,0) -> 0 | K150: =IFERROR((J150/G150*30),0) -> 0 | L150: =IF(K150<H150,"ORDER NOW","IN STOCK") -> ORDER NOW | M150: =IF(K150<H150,"CRITICAL","FOLLOW UP DELIVERY") -> CRITICAL | N150: 1
A151: RM-00576 | B151: Syrup blackberry Teisseire سيروب تيسير توت أسود | C151: 1 Box X 6 Bottle X 1 Ltr | D151: Box | E151: 0.16666667 | F151: =VLOOKUP($A151,'Master File June-26'!$C$3:$L$670,6,0) -> 17 | G151: =VLOOKUP($A151,'Master File June-26'!$C$3:$L$670,7,0) -> 102 | H151: =VLOOKUP($A151,'Master File June-26'!$C$3:$L$670,8,0) -> 14 | I151: =VLOOKUP($A151,'Master File June-26'!$C$3:$L$670,9,0) -> 51 | J151: =VLOOKUP($A151,'Master File June-26'!$C$3:$L$670,10,0) -> 0 | K151: =IFERROR((J151/G151*30),0) -> 0 | L151: =IF(K151<H151,"ORDER NOW","IN STOCK") -> ORDER NOW | M151: =IF(K151<H151,"CRITICAL","FOLLOW UP DELIVERY") -> CRITICAL | N151: 1
A152: RM-00224 | B152: Creme Caramel كريم كراميل | C152: 1 Box X 12 Pcs. X 49 g | D152: Box | E152: 0.14172336 | F152: =VLOOKUP($A152,'Master File June-26'!$C$3:$L$670,6,0) -> 15 | G152: =VLOOKUP($A152,'Master File June-26'!$C$3:$L$670,7,0) -> 105.84 | H152: =VLOOKUP($A152,'Master File June-26'!$C$3:$L$670,8,0) -> 14 | I152: =VLOOKUP($A152,'Master File June-26'!$C$3:$L$670,9,0) -> 52.92 | J152: =VLOOKUP($A152,'Master File June-26'!$C$3:$L$670,10,0) -> 306.046 | K152: =IFERROR((J152/G152*30),0) -> 86.747732 | L152: =IF(K152<H152,"ORDER NOW","IN STOCK") -> IN STOCK | M152: =IF(K152<H152,"CRITICAL","FOLLOW UP DELIVERY") -> FOLLOW UP DELIVERY | N152: 1
... A227: RM-00246 | B227: AFIA CINNAMON POWDER | بودرة القرفة العافية | C227: 1 KG | D227: Pcs | E227: 1 | F227: =VLOOKUP($A227,'Master File June-26'!$C$3:$L$670,6,0) -> 8 | G227: =VLOOKUP($A227,'Master File June-26'!$C$3:$L$670,7,0) -> 8 | H227: =VLOOKUP($A227,'Master File June-26'!$C$3:$L$670,8,0) -> 14 | I227: =VLOOKUP($A227,'Master File June-26'!$C$3:$L$670,9,0) -> 4 | J227: =VLOOKUP($A227,'Master File June-26'!$C$3:$L$670,10,0) -> 0 | K227: =IFERROR((J227/G227*30),0) -> 0 | L227: =IF(K227<H227,"ORDER NOW","IN STOCK") -> ORDER NOW | M227: =IF(K227<H227,"CRITICAL","FOLLOW UP DELIVERY") -> CRITICAL | N227: 1
A228: RM-00486 | B228: قهوة كيف المسافر هيل | Caif Almosafer Hill Coffee | E228: 1 | F228: =VLOOKUP($A228,'Master File June-26'!$C$3:$L$670,6,0) -> 27.5 | G228: =VLOOKUP($A228,'Master File June-26'!$C$3:$L$670,7,0) -> 27.5 | H228: =VLOOKUP($A228,'Master File June-26'!$C$3:$L$670,8,0) -> 14 | I228: =VLOOKUP($A228,'Master File June-26'!$C$3:$L$670,9,0) -> 13.75 | J228: =VLOOKUP($A228,'Master File June-26'!$C$3:$L$670,10,0) -> 0 | K228: =IFERROR((J228/G228*30),0) -> 0 | L228: =IF(K228<H228,"ORDER NOW","IN STOCK") -> ORDER NOW | M228: =IF(K228<H228,"CRITICAL","FOLLOW UP DELIVERY") -> CRITICAL | N228: 1
A229: RM-00417 | B229: Almond grain جوز حب امريكي | C229: KG | D229: Pcs | E229: 1 | F229: =VLOOKUP($A229,'Master File June-26'!$C$3:$L$670,6,0) -> 5 | G229: =VLOOKUP($A229,'Master File June-26'!$C$3:$L$670,7,0) -> 5 | H229: =VLOOKUP($A229,'Master File June-26'!$C$3:$L$670,8,0) -> 14 | I229: =VLOOKUP($A229,'Master File June-26'!$C$3:$L$670,9,0) -> 2.5 | J229: =VLOOKUP($A229,'Master File June-26'!$C$3:$L$670,10,0) -> 0 | K229: =IFERROR((J229/G229*30),0) -> 0 | L229: =IF(K229<H229,"ORDER NOW","IN STOCK") -> ORDER NOW | M229: =IF(K229<H229,"CRITICAL","FOLLOW UP DELIVERY") -> CRITICAL | N229: 1
A230: RM-00204 | B230: Mahran Biryani برياني مهران | C230: Box | D230: Box | E230: 1 | F230: =VLOOKUP($A230,'Master File June-26'!$C$3:$L$670,6,0) -> 1 | G230: =VLOOKUP($A230,'Master File June-26'!$C$3:$L$670,7,0) -> 1 | H230: =VLOOKUP($A230,'Master File June-26'!$C$3:$L$670,8,0) -> 14 | I230: =VLOOKUP($A230,'Master File June-26'!$C$3:$L$670,9,0) -> 0.5 | J230: =VLOOKUP($A230,'Master File June-26'!$C$3:$L$670,10,0) -> 0 | K230: =IFERROR((J230/G230*30),0) -> 0 | L230: =IF(K230<H230,"ORDER NOW","IN STOCK") -> ORDER NOW | M230: =IF(K230<H230,"CRITICAL","FOLLOW UP DELIVERY") -> CRITICAL | N230: 1
A231: RM-00568 | B231: Syrup lemon Teisseire سيروب تيسير ليمون | C231: 1 Box X 6 Bottle X 1 Ltr | D231: Box | E231: 0.16666667 | F231: =VLOOKUP($A231,'Master File June-26'!$C$3:$L$670,6,0) -> 21 | G231: =VLOOKUP($A231,'Master File June-26'!$C$3:$L$670,7,0) -> 126 | H231: =VLOOKUP($A231,'Master File June-26'!$C$3:$L$670,8,0) -> 14 | I231: =VLOOKUP($A231,'Master File June-26'!$C$3:$L$670,9,0) -> 63 | J231: =VLOOKUP($A231,'Master File June-26'!$C$3:$L$670,10,0) -> 25 | K231: =IFERROR((J231/G231*30),0) -> 5.952381 | L231: =IF(K231<H231,"ORDER NOW","IN STOCK") -> ORDER NOW | M231: =IF(K231<H231,"CRITICAL","FOLLOW UP DELIVERY") -> CRITICAL | N231: 0
A232: RM-00143 | B232: Lite corn syrup شراب الذرة الفاتح | C232: 1 Box X 12 Pcs X 710 ml | D232: Box | E232: 0.11737089 | F232: =VLOOKUP($A232,'Master File June-26'!$C$3:$L$670,6,0) -> 15 | G232: =VLOOKUP($A232,'Master File June-26'!$C$3:$L$670,7,0) -> 127.8 | H232: =VLOOKUP($A232,'Master File June-26'!$C$3:$L$670,8,0) -> 14 | I232: =VLOOKUP($A232,'Master File June-26'!$C$3:$L$670,9,0) -> 63.9 | J232: =VLOOKUP($A232,'Master File June-26'!$C$3:$L$670,10,0) -> 153.36 | K232: =IFERROR((J232/G232*30),0) -> 36 | L232: =IF(K232<H232,"ORDER NOW","IN STOCK") -> IN STOCK | M232: =IF(K232<H232,"CRITICAL","FOLLOW UP DELIVERY") -> FOLLOW UP DELIVERY | N232: 1
A233: RM-00368 | B233: Frisina Raspberry Filling 50% حشوة توت الاحمر فريزينا 50% | C233: 1 PCS X 2.7 KG | D233: Pcs | E233: 0.37037037 | F233: =VLOOKUP($A233,'Master File June-26'!$C$3:$L$670,6,0) -> 11 | G233: =VLOOKUP($A233,'Master File June-26'!$C$3:$L$670,7,0) -> 29.7 | H233: =VLOOKUP($A233,'Master File June-26'!$C$3:$L$670,8,0) -> 14 | I233: =VLOOKUP($A233,'Master File June-26'!$C$3:$L$670,9,0) -> 14.85 | J233: =VLOOKUP($A233,'Master File June-26'!$C$3:$L$670,10,0) -> 0 | K233: =IFERROR((J233/G233*30),0) -> 0 | L233: =IF(K233<H233,"ORDER NOW","IN STOCK") -> ORDER NOW | M233: =IF(K233<H233,"CRITICAL","FOLLOW UP DELIVERY") -> CRITICAL | N233: 1
A234: RM-00571 | B234: Syrup teisseire raspberry teisseire سيروب توت احمر - تيسير | C234: 1 Box X 6 Bottle X 1 Ltr | D234: Box | E234: 0.16666667 | F234: =VLOOKUP($A234,'Master File June-26'!$C$3:$L$670,6,0) -> 30.5 | G234: =VLOOKUP($A234,'Master File June-26'!$C$3:$L$670,7,0) -> 183 | H234: =VLOOKUP($A234,'Master File June-26'!$C$3:$L$670,8,0) -> 14 | I234: =VLOOKUP($A234,'Master File June-26'!$C$3:$L$670,9,0) -> 91.5 | J234: =VLOOKUP($A234,'Master File June-26'!$C$3:$L$670,10,0) -> 198 | K234: =IFERROR((J234/G234*30),0) -> 32.459016 | L234: =IF(K234<H234,"ORDER NOW","IN STOCK") -> IN STOCK | M234: =IF(K234<H234,"CRITICAL","FOLLOW UP DELIVERY") -> FOLLOW UP DELIVERY | N234: 0
A235: RM-00294 | B235: SRIRACHA FLAVORED WITH OAK BARREL AGED PEPPERS صلصة سريراتشا تباسكو | C235: 1 Box X 6 Pcs X 566 gm | D235: Box | E235: 0.29411765 | F235: =VLOOKUP($A235,'Master File June-26'!$C$3:$L$670,6,0) -> 5 | G235: =VLOOKUP($A235,'Master File June-26'!$C$3:$L$670,7,0) -> 17 | H235: =VLOOKUP($A235,'Master File June-26'!$C$3:$L$670,8,0) -> 14 | I235: =VLOOKUP($A235,'Master File June-26'!$C$3:$L$670,9,0) -> 8.5 | J235: =VLOOKUP($A235,'Master File June-26'!$C$3:$L$670,10,0) -> 8.712 | K235: =IFERROR((J235/G235*30),0) -> 15.374118 | L235: =IF(K235<H235,"ORDER NOW","IN STOCK") -> IN STOCK | M235: =IF(K235<H235,"CRITICAL","FOLLOW UP DELIVERY") -> FOLLOW UP DELIVERY | N235: 1
...

Sheet Packiging Materila Stock Status
B2: Item Code | C2: Item Description | D2: Packing | E2: UOM | F2: Conversion | G2: QTY in Pack | H2: QTY in Unit | I2: Lead Time | J2: Reordering Point | K2: WH Stocks | L2: Coverage/Day | M2: 0rder Status | N2: Criticality | O2: Stock Status
A3: 11 | B3: PM-00568 | C3: كيس مخبوزات مطبوع مقاس 10 × 14.5 cm (نمق)-Printed Bakery Paper Bag, 10 × 14.5 cm(Namq) | D3: 1Box X 8000 | E3: Box | F3: 0.000125 | G3: 8 | H3: 64000 | I3: 14 | J3: 32000 | K3: 0 | L3: =IFERROR((K3/H3*30),0) -> 0 | M3: ORDER NOW | N3: CRITICAL | O3: 0
A4: 19 | B4: PM-00075 | C4: Nozzle Lids for Coffee Box 1 Ltr أغطية كرتون القهوة سعة 1 لتر | D4: 1Box X 400 | E4: Box | F4: 0.0025 | G4: 0 | H4: 0 | I4: 14 | J4: 0 | K4: 0 | L4: =IFERROR((K4/H4*30),0) -> 0 | M4: ORDER NOW | N4: CRITICAL | O4: 1
A5: 29 | B5: PM-00563 | C5: Paper Cup Surprise 16 oz - Outer كوب ورقي للمفاجأة 16 أونص نمق | D5: 1 Box X 1000 Pcs. | E5: Box | F5: 0.001 | G5: 0 | H5: 0 | I5: 60 | J5: 0 | K5: 197000 | L5: =IFERROR((K5/H5*30),0) -> 0 | M5: ORDER NOW | N5: CRITICAL | O5: 1
A6: 46 | B6: PM-00436 | C6: استيكر هوت شوكلت Hot chocolate sticker | E6: Box | F6: 1 | G6: 5.5 | H6: 5.5 | I6: 14 | J6: 2.75 | K6: 0 | L6: =IFERROR((K6/H6*30),0) -> 0 | M6: ORDER NOW | N6: CRITICAL | O6: 0
A7: 49 | B7: PM-00230 | C7: Cafec V60 Filter 01 Coffee Filter كافيك فلاتر ترشيح ورقية - مقاس 01 | D7: 1 Box X 80 Case X 100 PCS | E7: Box | F7: 0.000125 | G7: 0 | H7: 0 | I7: 14 | J7: 0 | K7: 56000 | L7: =IFERROR((K7/H7*30),0) -> 0 | M7: ORDER NOW | N7: CRITICAL | O7: 1
A8: 50 | B8: PM-00240 | C8: Cold Brew Filter فلتر كولد برو خفيف | D8: 1 Pcs | E8: Pcs | F8: 1 | G8: 44 | H8: 44 | I8: 14 | J8: 22 | K8: 0 | L8: =IFERROR((K8/H8*30),0) -> 0 | M8: ORDER NOW | N8: CRITICAL | O8: 0
A9: 53 | B9: PM-00655 | C9: سليف زجاجة ايس تي | Glass sleeve for iced | D9: 1 Box X 600 Pcs | E9: Box | F9: 0.0016666667 | G9: 20 | H9: 12000 | I9: 14 | J9: 6000 | K9: 0 | L9: =IFERROR((K9/H9*30),0) -> 0 | M9: ORDER NOW | N9: CRITICAL | O9: 0
A10: 55 | B10: PM-00656 | C10: سليف زجاجة كولدر برو | Glass sleeve for cold bro | D10: 1 Box X1200 Pcs | E10: Box | F10: 0.00083333333 | G10: 10 | H10: 12000 | I10: 14 | J10: 6000 | K10: 0 | L10: =IFERROR((K10/H10*30),0) -> 0 | M10: ORDER NOW | N10: CRITICAL | O10: 0
A11: 56 | B11: PM-00533 | C11: كوب فخار 110 ملي محفور عليى شعار من الداخل والخارج قليز شفاف مطفي (لتقديم الاسبريسو) | D11: Pcs. | E11: Pcs | F11: 1 | G11: 0 | H11: 0 | I11: 30 | J11: 0 | K11: 16 | L11: =IFERROR((K11/H11*30),0) -> 0 | M11: ORDER NOW | N11: CRITICAL | O11: 1
A12: 57 | B12: PM-00527 | C12: كوب فخار 200 مل - محفور بشعار من الخارج - قليز شفاف لامع من الداخل والخارج | D12: Pcs. | E12: Pcs | F12: 1 | G12: 0 | H12: 0 | I12: 30 | J12: 0 | K12: 531 | L12: =IFERROR((K12/H12*30),0) -> 0 | M12: ORDER NOW | N12: CRITICAL | O12: 1
A13: 58 | B13: PM-00528 | C13: كوب فخار 200 مل - محفور بشعار من الداخل والخارج - قليز شفاف مطفي | D13: Pcs. | E13: Pcs | F13: 1 | G13: 0 | H13: 0 | I13: 30 | J13: 0 | K13: 0 | L13: =IFERROR((K13/H13*30),0) -> 0 | M13: ORDER NOW | N13: CRITICAL | O13: 1
A14: 59 | B14: PM-00530 | C14: كوب فخار 300 مل - محفور عليه شعار من الداخل والخارج - قليز شفاف مطفي - STONEWARE | D14: Pcs. | E14: Pcs | F14: 1 | G14: 0 | H14: 0 | I14: 30 | J14: 0 | K14: 0 | L14: =IFERROR((K14/H14*30),0) -> 0 | M14: ORDER NOW | N14: CRITICAL | O14: 1
A15: 60 | B15: PM-00534 | C15: صحن فخار مقاس 20*20*15 محفور عليه الشعار في المنتصف | D15: Pcs. | E15: Pcs | F15: 1 | G15: 0 | H15: 0 | I15: 30 | J15: 0 | K15: 2 | L15: =IFERROR((K15/H15*30),0) -> 0 | M15: ORDER NOW | N15: CRITICAL | O15: 1
A16: 64 | B16: PM-00139 | C16: كرت الاسبريسو نمق (سان اجناسيو) Espresso card (San Ignacio) | D16: 1 Bundle X 500 pcs | E16: bundel | F16: 0.002 | G16: 5.5 | H16: 2750 | I16: 14 | J16: 1375 | K16: 0 | L16: =IFERROR((K16/H16*30),0) -> 0 | M16: ORDER NOW | N16: CRITICAL | O16: 0
A17: 65 | B17: PM-00295 | C17: Customer Evaluation Card كرت تقييم العملاء ( نمق ) | D17: 1 Box X 1000 | E17: Box | F17: 0.001 | G17: 0 | H17: 0 | I17: 14 | J17: 0 | K17: 0 | L17: =IFERROR((K17/H17*30),0) -> 0 | M17: ORDER NOW | N17: CRITICAL | O17: 1
A18: 66 | B18: PM-00276 | C18: Tape شطرطون | D18: 1 Box X 24 Pcs | E18: Box | F18: 0.041666667 | G18: 5.5 | H18: 132 | I18: 14 | J18: 66 | K18: 0 | L18: =IFERROR((K18/H18*30),0) -> 0 | M18: ORDER NOW | N18: CRITICAL | O18: 0
A19: 68 | B19: PM-00277 | C19: knife ( NAMQ ) سكين ( نمق ) | D19: 1 Box X 500 Pcs. | E19: Box | F19: 0.002 | G19: 38.5 | H19: 19250 | I19: 14 | J19: 9625 | K19: 0 | L19: =IFERROR((K19/H19*30),0) -> 0 | M19: ORDER NOW | N19: CRITICAL | O19: 0
A20: 69 | B20: PM-00448 | C20: Sticker Date ستيكر التاريخ | F20: 1 | G20: 5.5 | H20: 5.5 | I20: 14 | J20: 2.75 | K20: 0 | L20: =IFERROR((K20/H20*30),0) -> 0 | M20: ORDER NOW | N20: CRITICAL | O20: 0
A21: 70 | B21: PM-00261 | C21: Baking Paper 60*40 ورق خبازة 60*40 | D21: 1 Box X 500 Pcs. / 1 Box X 1000 Pcs. | E21: Box | F21: 0.002 | G21: 100 | H21: 50000 | I21: 14 | J21: 25000 | K21: 0 | L21: =IFERROR((K21/H21*30),0) -> 0 | M21: ORDER NOW | N21: CRITICAL | O21: 0
A22: 71 | B22: PM-00263 | C22: Cling Film رول تغليف نايلون | D22: Pcs. | E22: Pcs | F22: 1 | G22: 400 | H22: 400 | I22: 14 | J22: 200 | K22: 0 | L22: =IFERROR((K22/H22*30),0) -> 0 | M22: ORDER NOW | N22: CRITICAL | O22: 0
A23: 72 | B23: PM-00341 | C23: Point of sale roll - رول نقاط البيع | D23: 1 Box X 50 Pcs | E23: Box | F23: 0.02 | G23: 11 | H23: 550 | I23: 14 | J23: 275 | K23: 0 | L23: =IFERROR((K23/H23*30),0) -> 0 | M23: ORDER NOW | N23: CRITICAL | O23: 0
A24: 73 | B24: PM-00586 | C24: Namq Thermal Stainless Steel Cup with Two Lids – Sky Blue Color | D24: Pcs. | E24: Pcs | F24: 1 | G24: 0 | H24: 0 | I24: 60 | J24: 0 | K24: 485 | L24: =IFERROR((K24/H24*30),0) -> 0 | M24: ORDER NOW | N24: CRITICAL | O24: 1
A25: 74 | B25: PM-00582 | C25: Namq Thermal Stainless Steel Cup with Two Lids – Olive Green Color | D25: Pcs. | E25: Pcs | F25: 1 | G25: 0 | H25: 0 | I25: 60 | J25: 0 | K25: 413 | L25: =IFERROR((K25/H25*30),0) -> 0 | M25: ORDER NOW | N25: CRITICAL | O25: 1
A26: 75 | B26: PM-00583 | C26: Namq Thermal Stainless Steel Cup with Two Lids - Burgundy Color | D26: Pcs. | E26: Pcs | F26: 1 | G26: 0 | H26: 0 | I26: 60 | J26: 0 | K26: 241 | L26: =IFERROR((K26/H26*30),0) -> 0 | M26: ORDER NOW | N26: CRITICAL | O26: 1
A27: 76 | B27: PM-00584 | C27: Namq Thermal Stainless Steel Cup with Two Lids – Beige Color | D27: Pcs. | E27: Pcs | F27: 1 | G27: 0 | H27: 0 | I27: 60 | J27: 0 | K27: 205 | L27: =IFERROR((K27/H27*30),0) -> 0 | M27: ORDER NOW | N27: CRITICAL | O27: 1
A28: 77 | B28: PM-00585 | C28: Thermal Stainless Steel Cup with Two Lids – Navy Blue | D28: Pcs. | E28: Pcs | F28: 1 | G28: 0 | H28: 0 | I28: 60 | J28: 0 | K28: 613 | L28: =IFERROR((K28/H28*30),0) -> 0 | M28: ORDER NOW | N28: CRITICAL | O28: 1
A29: 90 | B29: PM-00182 | C29: Breehant Paper cup 6.5 OZ كوب ورقي 6.5 اونص بريهانت | D29: 1 Box 20 Pack X 25 Pcs | E29: Box | F29: 0.002 | G29: 150 | H29: 75000 | I29: 14 | J29: 37500 | K29: 0 | L29: =IFERROR((K29/H29*30),0) -> 0 | M29: ORDER NOW | N29: CRITICAL | O29: 0
A30: 93 | B30: PM-00653 | C30: Cup 7 oz double wide Seasnal ( Breehant ) - كوب 7 اونص دبل فتحة واسعه موسمى ( بريهانت ) | D30: 1 Box 20 Pack X 25 Pcs | E30: Box | F30: 0.002 | G30: 8 | H30: 4000 | I30: 14 | J30: 2000 | K30: 0 | L30: =IFERROR((K30/H30*30),0) -> 0 | M30: ORDER NOW | N30: CRITICAL | O30: 0
A31: 94 | B31: PM-00200 | C31: Season Paper cup Double 12 Oz ( BREEHANT ) كوب ورقي 12 اونصه تصميم موسمي ( بريهانت ) | D31: 1 Box X 500 | E31: Box | F31: 0.002 | G31: 8 | H31: 4000 | I31: 14 | J31: 2000 | K31: 0 | L31: =IFERROR((K31/H31*30),0) -> 0 | M31: ORDER NOW | N31: CRITICAL | O31: 0
A32: 95 | B32: PM-00201 | C32: Season Paper cup Double 9 Oz ( BREEHANT ) كوب ورقي 9 اونصه تصميم موسمي ( بريهانت ) | D32: 1 Box X 1000 Pcs | E32: Box | F32: 0.001 | G32: 0 | H32: 0 | I32: 14 | J32: 0 | K32: 0 | L32: =IFERROR((K32/H32*30),0) -> 0 | M32: ORDER NOW | N32: CRITICAL | O32: 1
... A45: 123 | B45: PM-00080 | C45: Bar Box (NAMQ)بوكس البارات (نمق) | D45: 1 bundle X 500 PCS | E45: bundel | F45: 0.002 | G45: 15 | H45: 7500 | I45: 14 | J45: 3750 | K45: 0 | L45: =IFERROR((K45/H45*30),0) -> 0 | M45: ORDER NOW | N45: CRITICAL | O45: 0
A46: 125 | B46: PM-00093 | C46: Hallomi Sandwiche Box بوكس ساندويتش حلومي | D46: Pcs | F46: 1 | G46: 0 | H46: 0 | I46: 14 | J46: 0 | K46: 0 | L46: =IFERROR((K46/H46*30),0) -> 0 | M46: ORDER NOW | N46: CRITICAL | O46: 1
A47: 127 | B47: PM-00076 | C47: Salted caramel box بوكس كراميل مملح | D47: 1 bundle X 100 PCS | E47: bundel | F47: 0.01 | G47: 300 | H47: 30000 | I47: 14 | J47: 15000 | K47: 0 | L47: =IFERROR((K47/H47*30),0) -> 0 | M47: ORDER NOW | N47: CRITICAL | O47: 0
A48: 129 | B48: PM-00105 | C48: Crunchy Chocolate box (BREEHANT) بوكس كرانشي شوكلت ( بريهانت ) | D48: 1 Box X 200 Pcs | E48: Box | F48: 0.005 | G48: 50 | H48: 10000 | I48: 14 | J48: 5000 | K48: 0 | L48: =IFERROR((K48/H48*30),0) -> 0 | M48: ORDER NOW | N48: CRITICAL | O48: 0
A49: 136 | B49: PM-00330 | C49: Transfer Chocolate Paper ( Breehant ) ورق ترانسفير التشوكلت ( بريهانت ) | D49: 1 Bundle X 50 Pcs. | E49: bundel | F49: 0.02 | G49: 0 | H49: 0 | I49: 14 | J49: 0 | K49: 0 | L49: =IFERROR((K49/H49*30),0) -> 0 | M49: ORDER NOW | N49: CRITICAL | O49: 1
A50: 141 | B50: PM-00617 | C50: كوب ابيض سراميك + صحن 8 اونص White ceramic plate with sauce | D50: Pcs | E50: Pcs | F50: 1 | G50: 0 | H50: 0 | I50: 14 | J50: 0 | K50: 0 | L50: =IFERROR((K50/H50*30),0) -> 0 | M50: ORDER NOW | N50: CRITICAL | O50: 1
A51: 143 | B51: PM-00686 | C51: بوكس البار مارشميلو|| Marshmallow Bar Box | D51: Pcs | E51: Pcs | F51: 1 | G51: 0 | H51: 0 | I51: 14 | J51: 0 | K51: 0 | L51: =IFERROR((K51/H51*30),0) -> 0 | M51: ORDER NOW | N51: CRITICAL | O51: 1
A52: 144 | B52: PM-00688 | C52: سليف مارشميلو كراميل||Marshmallow Caramel Sleeve | D52: Pcs | E52: Pcs | F52: 1 | G52: 0 | H52: 0 | I52: 14 | J52: 0 | K52: 0 | L52: =IFERROR((K52/H52*30),0) -> 0 | M52: ORDER NOW | N52: CRITICAL | O52: 1
A53: 145 | B53: PM-00687 | C53: سليف مارشميلو كرانشي||Marshmallow Crunchy Sleeve | D53: Pcs | E53: Pcs | F53: 1 | G53: 0 | H53: 0 | I53: 14 | J53: 0 | K53: 0 | L53: =IFERROR((K53/H53*30),0) -> 0 | M53: ORDER NOW | N53: CRITICAL | O53: 1
A54: 146 | B54: PM-00689 | C54: بوكس البار مادلين|| Madeleine Bar Box | D54: Pcs | E54: Pcs | F54: 1 | G54: 0 | H54: 0 | I54: 14 | J54: 0 | K54: 16 | L54: =IFERROR((K54/H54*30),0) -> 0 | M54: ORDER NOW | N54: CRITICAL | O54: 1
A55: 147 | B55: PM-00690 | C55: سليف مادلين بيكان جوز الهند||Madeleine Pecan Coconut Sleeve | D55: Pcs | E55: Pcs | F55: 1 | G55: 0 | H55: 0 | I55: 14 | J55: 0 | K55: 0 | L55: =IFERROR((K55/H55*30),0) -> 0 | M55: ORDER NOW | N55: CRITICAL | O55: 1
A56: 148 | B56: PM-00691 | C56: سليف مادلين ماتشا شوكولاته||Madeleine Matcha Chocolate Sleeve | D56: Pcs | E56: Pcs | F56: 1 | G56: 0 | H56: 0 | I56: 14 | J56: 0 | K56: 0 | L56: =IFERROR((K56/H56*30),0) -> 0 | M56: ORDER NOW | N56: CRITICAL | O56: 1
A57: 149 | B57: PM-00666 | C57: سليف بار كراميل بايتس | Caramel Bites Bar sleeve | D57: 1 Box X 1600 Pcs | E57: Box | F57: 0.000625 | G57: 16 | H57: 25600 | I57: 14 | J57: 12800 | K57: 0 | L57: =IFERROR((K57/H57*30),0) -> 0 | M57: ORDER NOW | N57: CRITICAL | O57: 0
A58: 150 | B58: PM-00038 | C58: Tiramisu Cover (breehant) غلاف تيراميسو (بريهانت) | D58: 1 Bundle X 500 PCS | E58: bundel | F58: 0.002 | G58: 6 | H58: 3000 | I58: 14 | J58: 1500 | K58: 0 | L58: =IFERROR((K58/H58*30),0) -> 0 | M58: ORDER NOW | N58: CRITICAL | O58: 0
A59: 154 | B59: PM-00340 | C59: ورق شوكولاته مطبوع لبوكس الكرانشي بريهانتPrinted chocolate paper for crunchy BREEHANT box | F59: 1 | G59: 3 | H59: 3 | I59: 14 | J59: 1.5 | K59: 0 | L59: =IFERROR((K59/H59*30),0) -> 0 | M59: ORDER NOW | N59: CRITICAL | O59: 0
A60: 155 | B60: PM-00339 | C60: ورق ترانسفير الكوكيز مقاس 10سم (نمق)Transfer cookies Paper(NAMQ ) | D60: 1 Box X 750 Sheet | E60: Box | F60: 0.0013333333 | G60: 28 | H60: 21000 | I60: 14 | J60: 10500 | K60: 0 | L60: =IFERROR((K60/H60*30),0) -> 0 | M60: ORDER NOW | N60: CRITICAL | O60: 0
A61: 156 | B61: PM-00627 | C61: ورق زبدة بني 22سم دائري-Brown baking paper, 22 cm, round | F61: 1 | G61: 15000 | H61: 15000 | I61: 14 | J61: 7500 | K61: 0 | L61: =IFERROR((K61/H61*30),0) -> 0 | M61: ORDER NOW | N61: CRITICAL | O61: 0
A62: 157 | B62: PM-00347 | C62: ورق ترانسفير الكوكيز مقاس 10سم (بريهانت)Transfer cookies Paper(BREEHANT ) | D62: Sheet 25pcs | E62: Pcs | F62: 0.04 | G62: 400 | H62: 10000 | I62: 14 | J62: 5000 | K62: 0 | L62: =IFERROR((K62/H62*30),0) -> 0 | M62: ORDER NOW | N62: CRITICAL | O62: 0
A63: 158 | B63: PM-00281 | C63: Roll packing machine رول مكينة تغليف | D63: Pcs. | E63: Pcs | F63: 1 | G63: 80 | H63: 80 | I63: 14 | J63: 40 | K63: 0 | L63: =IFERROR((K63/H63*30),0) -> 0 | M63: ORDER NOW | N63: CRITICAL | O63: 0
A64: 159 | B64: PM-00648 | C64: صحن ألمنيوم دائري 25-4 | Round aluminum plate | D64: Pcs | E64: Pcs | F64: 1 | G64: 3 | I64: 14 | J64: 0 | K64: 9 | L64: =IFERROR((K64/H64*30),0) -> 0 | M64: ORDER NOW | N64: CRITICAL | O64: 1
A65: 160 | B65: PM-00606 | C65: Round aluminum plate 110 ml with cover | صحن دائري مع غطاء 110 مل | D65: Pcs. | E65: Pcs | F65: 1 | G65: 60000 | H65: 60000 | I65: 14 | J65: 30000 | K65: 0 | L65: =IFERROR((K65/H65*30),0) -> 0 | M65: ORDER NOW | N65: CRITICAL | O65: 0
A66: 164 | B66: PM-00029 | C66: foggy Bag size:13*17cm+3cm Thickness:0.05mm كيس ضبابي للكيك | D66: 1 Box X 8000 Pcs | E66: Box | F66: 0.000125 | G66: 10 | H66: 80000 | I66: 14 | J66: 40000 | K66: 0 | L66: =IFERROR((K66/H66*30),0) -> 0 | M66: ORDER NOW | N66: CRITICAL | O66: 0
A67: 168 | B67: PM-00638 | C67: Caramelized Pecan Paper Box 1 PCS (New ID) | علبة بيكان مكرمل ورقية | D67: 1 Box X 600 | E67: Box | F67: 0.0016666667 | G67: 13 | H67: 7800 | I67: 14 | J67: 3900 | K67: 0 | L67: =IFERROR((K67/H67*30),0) -> 0 | M67: ORDER NOW | N67: CRITICAL | O67: 0
A68: 169 | B68: PM-00645 | C68: علبة ألمنيوم مربعة 180 مل | 180ml square aluminum foil Tray | D68: Pcs. | E68: Pcs | F68: 1 | G68: 4000 | H68: 4000 | I68: 14 | J68: 2000 | K68: 0 | L68: =IFERROR((K68/H68*30),0) -> 0 | M68: ORDER NOW | N68: CRITICAL | O68: 0
A69: 170 | B69: PM-00643 | C69: Pudding box 12 oz.(Breehant)-علبة بودنق 12 أونص (بريهانت) | D69: 1 Box X 150 | E69: Box | F69: 0.0066666667 | G69: 50 | H69: 7500 | I69: 14 | J69: 3750 | K69: 0 | L69: =IFERROR((K69/H69*30),0) -> 0 | M69: ORDER NOW | N69: CRITICAL | O69: 0
A70: 177 | B70: PM-00036 | C70: HD BAG PRINTED 2+2 COLORS SIZE كيس التاندو مطبوع | D70: Box | E70: Box | F70: 0.003125 | G70: 10 | H70: 3200 | I70: 14 | J70: 1600 | K70: 0 | L70: =IFERROR((K70/H70*30),0) -> 0 | M70: ORDER NOW | N70: CRITICAL | O70: 0
A71: 183 | B71: PM-00697 | C71: استيكر اغلاق بوكس فطورات كبير|| large breakfast box closure sticker | D71: Pcs | E71: Pcs | F71: 1 | G71: 5000 | H71: 5000 | I71: 14 | J71: 2500 | K71: 0 | L71: =IFERROR((K71/H71*30),0) -> 0 | M71: ORDER NOW | N71: CRITICAL | O71: 0
A72: 184 | B72: PM-00696 | C72: استيكر اغلاق بوكس فطورات صغير|| small breakfast box closure sticker | D72: Pcs | E72: Pcs | F72: 1 | G72: 5000 | H72: 5000 | I72: 14 | J72: 2500 | K72: 0 | L72: =IFERROR((K72/H72*30),0) -> 0 | M72: ORDER NOW | N72: CRITICAL | O72: 0
A73: 37 | B73: PM-00664 | C73: ورق زبدة دائري 12 سم | round butter paper 12 sm | D73: Bundle X 2750 | E73: Box | F73: 0.00036363636 | G73: 121 | H73: 332750 | I73: 14 | J73: 166375 | K73: 2.5 | L73: =IFERROR((K73/H73*30),0) -> 0.00022539444 | M73: ORDER NOW | N73: CRITICAL | O73: 0
A74: 54 | B74: PM-00669 | C74: سليف ايس تي خوخ | D74: 1 Box X 1200 Pcs | E74: Box | F74: 0.00083333333 | G74: 10 | H74: 12000 | I74: 14 | J74: 6000 | K74: 4 | L74: =IFERROR((K74/H74*30),0) -> 0.01 | M74: ORDER NOW | N74: CRITICAL | O74: 0
A75: 137 | B75: PM-00052 | C75: Fruit granola bag cove (غطاء كيس جرانولا بالفواكه (بريهانت | D75: Pcs | F75: 1 | G75: 0 | H75: 5000 | I75: 14 | J75: 2500 | K75: 21 | L75: =IFERROR((K75/H75*30),0) -> 0.126 | M75: ORDER NOW | N75: CRITICAL | O75: 0
A76: 179 | B76: PM-00580 | C76: ماعون طبق قصب سكر عازل 1000 ملي مع غطاء بلاستيك - Sugarcane pulp bowl 1000 ml with plastic lid | D76: Pcs | E76: Pcs | F76: 1 | G76: 25000 | H76: 25000 | I76: 14 | J76: 12500 | K76: 106 | L76: =IFERROR((K76/H76*30),0) -> 0.1272 | M76: ORDER NOW | N76: CRITICAL | O76: 0
A77: 181 | B77: PM-00621 | C77: بوكس ورقي قطعة واحده فطورات Paper box, one piece, for Fotorat | D77: Pcs | E77: Pcs | F77: 1 | G77: 5000 | H77: 5000 | I77: 14 | J77: 2500 | K77: 28 | L77: =IFERROR((K77/H77*30),0) -> 0.168 | M77: ORDER NOW | N77: CRITICAL | O77: 0
A78: 182 | B78: PM-00622 | C78: بوكس ورقي ثلاثه قطع فطورات Paper box, three pieces, for Fotorat | D78: Pcs | E78: Pcs | F78: 1 | G78: 5000 | H78: 5000 | I78: 14 | J78: 2500 | K78: 28 | L78: =IFERROR((K78/H78*30),0) -> 0.168 | M78: ORDER NOW | N78: CRITICAL | O78: 0
A79: 139 | B79: PM-00549 | C79: Cake base size 10cm * 6cm | D79: Pcs | E79: Pcs | F79: 1 | G79: 5000 | H79: 5000 | I79: 14 | J79: 2500 | K79: 38 | L79: =IFERROR((K79/H79*30),0) -> 0.228 | M79: ORDER NOW | N79: CRITICAL | O79: 0
A80: 62 | B80: PM-00003 | C80: Cream bags أكياس كريمة | D80: 1 Box X 10 Pack X 100 pcs | E80: Box | F80: 0.001 | G80: 92 | H80: 92000 | I80: 14 | J80: 46000 | K80: 2400 | L80: =IFERROR((K80/H80*30),0) -> 0.7826087 | M80: ORDER NOW | N80: CRITICAL | O80: 0
A81: 36 | B81: PM-00345 | C81: Rap paper for paper cupsورق زبدة دائري 12 سم للاكواب الورقيه | D81: 1 Bundle X 2750 | E81: Box | F81: 0.00036363636 | G81: 92.5 | H81: 254375 | I81: 14 | J81: 127187.5 | K81: 22000 | L81: =IFERROR((K81/H81*30),0) -> 2.5945946 | M81: ORDER NOW | N81: CRITICAL | O81: 0
A82: 5 | B82: PM-00260 | C82: two cup holder حامل اكواب ثنائي | D82: 1 Box X 600 Pcs / 1 Box X 500 Pcs. | E82: Box | F82: 0.0016666667 | G82: 565.5 | H82: 339300 | I82: 14 | J82: 169650 | K82: 29400 | L82: =IFERROR((K82/H82*30),0) -> 2.5994695 | M82: ORDER NOW | N82: CRITICAL | O82: 0
A83: 163 | B83: PM-00509 | C83: قاعدة كيك بريهانت المطبوعة 28سم Breehant Cake Base 28cm | D83: 1 Box x 100 | E83: Box | F83: 0.01 | G83: 100 | H83: 10000 | I83: 14 | J83: 5000 | K83: 900 | L83: =IFERROR((K83/H83*30),0) -> 2.7 | M83: ORDER NOW | N83: CRITICAL | O83: 0
A84: 67 | B84: PM-00332 | C84: Printed cash roll Four colors size 80 x 70 , 37 meter (NAMQ ) ورق كاشير مطبوع ( نمق ) | D84: 1 Box X 50 Roll | E84: Box | F84: 0.02 | G84: 71.5 | H84: 3575 | I84: 14 | J84: 1787.5 | K84: 350 | L84: =IFERROR((K84/H84*30),0) -> 2.9370629 | M84: ORDER NOW | N84: CRITICAL | O84: 0
A85: 12 | B85: PM-00042 | C85: كيس بلاستيك ضبابي نمق مقاس 44سم *40سم مع لاصق اغلاق Namq Foggy Plastic Bag 44cm*40cm | D85: 1 Box X 10 Kg (320 Pcs) | E85: Box | F85: 0.003125 | G85: 825 | H85: 264000 | I85: 14 | J85: 132000 | K85: 28480 | L85: =IFERROR((K85/H85*30),0) -> 3.2363636 | M85: ORDER NOW | N85: CRITICAL | O85: 0
A86: 63 | B86: PM-00662 | C86: قاعدة صحن ألمنيوم ورقية 235 مل | Aluminum paper plat base 235ml | D86: 1 Box X 1000 Pcs | E86: Box | F86: 0.001 | G86: 70 | H86: 70000 | I86: 14 | J86: 35000 | K86: 8500 | L86: =IFERROR((K86/H86*30),0) -> 3.6428571 | M86: ORDER NOW | N86: CRITICAL | O86: 0
A87: 22 | B87: PM-00251 | C87: 4 Oz Sauce Cup plasticعلبة صوص 4 اونصه بلاستيك | D87: 1 Box X 20 Pack X 100 Pcs | E87: Box | F87: 0.0005 | G87: 145.5 | H87: 291000 | I87: 14 | J87: 145500 | K87: 36000 | L87: =IFERROR((K87/H87*30),0) -> 3.7113402 | M87: ORDER NOW | N87: CRITICAL | O87: 0
... A113: 39 | B113: PM-00566-01 | C113: Cookies Box - Sleeve بوكس الكوكيز السفري نمق | D113: 1 Box X 600 Pcs | E113: Box | F113: 0.0016666667 | G113: 100 | H113: 60000 | I113: 60 | J113: 128571.43 | K113: 36000 | L113: =IFERROR((K113/H113*30),0) -> 18 | M113: ORDER NOW | N113: CRITICAL | O113: 0
A114: 92 | B114: PM-00225 | C114: Breehant Roastery paper cup 12 Oz كوب ورقي 12 اونص محمصة بريهانت | D114: 1Box X 20 Pack X 25 Pcs | E114: Box | F114: 0.002 | G114: =VLOOKUP($B114,'Master File June-26'!$C$3:$L$670,6,0) -> 600 | H114: =VLOOKUP($B114,'Master File June-26'!$C$3:$L$670,7,0) -> 300000 | I114: =VLOOKUP($B114,'Master File June-26'!$C$3:$L$670,8,0) -> 14 | J114: =VLOOKUP($B114,'Master File June-26'!$C$3:$L$670,9,0) -> 168000 | K114: =VLOOKUP($B114,'Master File June-26'!$C$3:$L$670,10,0) -> 62500 | L114: =IFERROR((K114/H114*30),0) -> 6.25 | M114: ORDER NOW | N114: CRITICAL | O114: 0
A115: 45 | B115: PM-00661 | C115: سليف كوب الزجاج 200 مل | glass cup sleeve 200 ml | D115: Box X 1200 Pcs | E115: Box | F115: 0.00083333333 | G115: 38.5 | H115: 46200 | I115: 14 | J115: 23100 | K115: 30000 | L115: =IFERROR((K115/H115*30),0) -> 19.480519 | M115: IN STOCK | N115: FOLLOW UP DELIVERY | O115: 1
A116: 20 | B116: PM-00253 | C116: 2 Oz Sauce Cup plasticعلبة صوص 2 اونصه بلاستيك | D116: 1 Box X 20 Pack X 100 Pcs | E116: Box | F116: 0.0005 | G116: 100.5 | H116: 201000 | I116: 14 | J116: 100500 | K116: 138000 | L116: =IFERROR((K116/H116*30),0) -> 20.597015 | M116: IN STOCK | N116: FOLLOW UP DELIVERY | O116: 1
A117: 99 | B117: PM-00608 | C117: Vanilla Madrid Cheesecake Box بوكس تشيز كيك مدريد بالفانيليا | D117: 1 Box X 100 Pcs | E117: Box | F117: 0.01 | G117: 140 | H117: 14000 | I117: 14 | J117: 7000 | K117: 9800 | L117: =IFERROR((K117/H117*30),0) -> 21 | M117: IN STOCK | N117: FOLLOW UP DELIVERY | O117: 1
A118: 115 | B118: PM-00443 | C118: Caramel Bites Sticker (Namq) ستيكر كارميل بايتس مقاس 5سم ( نمق ) | D118: 1 Roll X 1000 Pcs. | E118: Box | F118: 0.001 | G118: 15 | H118: 15000 | I118: 14 | J118: 7500 | K118: 11000 | L118: =IFERROR((K118/H118*30),0) -> 22 | M118: IN STOCK | N118: FOLLOW UP DELIVERY | O118: 1
A119: 88 | B119: PM-00049 | C119: Breehant Small Foggy Plastic Bag 44cm*40cmكيس بلاستيك ضبابي بريهانت الصغير مقاس 44سم *40سم مع لاصق اغلاق | D119: 1 Box X 320 Pcs | E119: Box | F119: 0.003125 | G119: 40 | H119: 12800 | I119: 14 | J119: 6400 | K119: 9600 | L119: =IFERROR((K119/H119*30),0) -> 22.5 | M119: IN STOCK | N119: FOLLOW UP DELIVERY | O119: 1
A120: 34 | B120: PM-00197 | C120: Plastic cup Full Printed 14oz كوب بلاستيك مطبوعه 14 اونصه | D120: 1 Box X 500 Pcs. | E120: Box | F120: 0.002 | G120: 192.5 | H120: 96250 | I120: 60 | J120: 206250 | K120: 73000 | L120: =IFERROR((K120/H120*30),0) -> 22.753247 | M120: ORDER NOW | N120: CRITICAL | O120: 0
A121: 3 | B121: PM-00255 | C121: Namq Straw شفاط نمق | D121: 1 Box X 30 Pack X 100 Pcs | E121: Box | F121: 0.00033333333 | G121: 83.5 | H121: 250500 | I121: 14 | J121: 125250 | K121: 192000 | L121: =IFERROR((K121/H121*30),0) -> 22.994012 | M121: IN STOCK | N121: FOLLOW UP DELIVERY | O121: 1
A122: 52 | B122: PM-00660 | C122: سليف صحن البروكيز | tray sleeve for brokes | D122: 1 Bundle X 1000 Pcs | E122: Box | F122: 0.001 | G122: 10 | H122: 10000 | I122: 14 | J122: 5000 | K122: 8000 | L122: =IFERROR((K122/H122*30),0) -> 24 | M122: IN STOCK | N122: FOLLOW UP DELIVERY | O122: 1
A123: 138 | B123: PM-00060 | C123: Golden Cake Plate قاعدة كيك ذهبية 13*4.5 سم | D123: box x 1000 pcs | E123: Pcs | F123: 0.001 | G123: 25 | H123: 25000 | I123: 14 | J123: 12500 | K123: 20000 | L123: =IFERROR((K123/H123*30),0) -> 24 | M123: IN STOCK | N123: FOLLOW UP DELIVERY | O123: 1
A124: 86 | B124: PM-00595 | C124: Breehant Paper Bag Small - كيس ورقي صغير بريهانت | D124: 1 bundle X 100 PCS | E124: bundel | F124: 0.01 | G124: 96 | H124: 9600 | I124: 14 | J124: 4800 | K124: 7700 | L124: =IFERROR((K124/H124*30),0) -> 24.0625 | M124: IN STOCK | N124: FOLLOW UP DELIVERY | O124: 1
A125: 89 | B125: PM-00190 | C125: Breehant Paper cup 4 OZ كوب ورقي 4 اونص بريهانت | D125: 1 Box X 20 Pack X 50 Pcs | E125: Box | F125: 0.001 | G125: 22 | H125: 22000 | I125: 14 | J125: 11000 | K125: 18000 | L125: =IFERROR((K125/H125*30),0) -> 24.545455 | M125: IN STOCK | N125: FOLLOW UP DELIVERY | O125: 1
A126: 48 | B126: PM-00242 | C126: Cafec V60 Filter 02 Coffee Filter كافيك فلاتر ترشيح ورقية - مقاس 02 | D126: 1 Box X 80 Case X 100 PCS | E126: Box | F126: 0.000125 | G126: 25 | H126: 200000 | I126: 14 | J126: 100000 | K126: 165880 | L126: =IFERROR((K126/H126*30),0) -> 24.882 | M126: IN STOCK | N126: FOLLOW UP DELIVERY | O126: 1
... A130: 23 | B130: PM-00252 | C130: 4 Oz Sauce Lid plasticاغطية علبة صوص 4 اونصه بلاستيك | D130: 1 Box X 20 Pack X 100 Pcs | E130: Box | F130: 0.0005 | G130: 145.5 | H130: 291000 | I130: 14 | J130: 145500 | K130: 270000 | L130: =IFERROR((K130/H130*30),0) -> 27.835052 | M130: IN STOCK | N130: FOLLOW UP DELIVERY | O130: 1
A131: 106 | B131: PM-00525 | C131: بوكس فلين 1 كيلو مع طباعة خارجية | D131: 1X20 Pcs | F131: 0.05 | G131: 24 | H131: 480 | I131: 14 | J131: 240 | K131: 460 | L131: =IFERROR((K131/H131*30),0) -> 28.75 | M131: IN STOCK | N131: FOLLOW UP DELIVERY | O131: 1
A132: 128 | B132: PM-00089 | C132: Bar Box ( Breehant ) بوكس البارات ( بريهانت ) | D132: 1 Box X 500 Pcs | E132: Box | F132: 0.002 | G132: 40 | H132: 20000 | I132: 14 | J132: 10000 | K132: 19500 | L132: =IFERROR((K132/H132*30),0) -> 29.25 | M132: IN STOCK | N132: FOLLOW UP DELIVERY | O132: 1
A133: 121 | B133: PM-00430 | C133: استيكر اغلاق بكج الجرانولا (بريهانت) Granola package closing sticker BREEHANT | D133: 1 Box X 500 Pcs | E133: box | F133: 0.002 | G133: 5 | H133: 2500 | I133: 14 | J133: 1250 | K133: 2500 | L133: =IFERROR((K133/H133*30),0) -> 30 | M133: IN STOCK | N133: FOLLOW UP DELIVERY | O133: 1
A134: 47 | B134: PM-00239 | C134: FETCO Paper Filter فلتر ورقي لمكائن فتكو | D134: 1 Box X 2 Case X 250 Pcs | E134: Box | F134: 0.002 | G134: 175 | H134: 87500 | I134: 14 | J134: 43750 | K134: 93000 | L134: =IFERROR((K134/H134*30),0) -> 31.885714 | M134: IN STOCK | N134: FOLLOW UP DELIVERY | O134: 1
A135: 41 | B135: PM-00137 | C135: بوكس التراميسو والدولتشي للجمعات (نمق) Tiramisu and Dolce box for gatherings (Namaq) | D135: Bundle X 100 pcs | E135: Box | F135: 0.01 | G135: 30 | H135: 3000 | I135: 14 | J135: 1500 | K135: 3300 | L135: =IFERROR((K135/H135*30),0) -> 33 | M135: IN STOCK | N135: FOLLOW UP DELIVERY | O135: 1
A136: 61 | B136: PM-00258 | C136: Wooden Stirrer اعواد التحريك الخشب | D136: 1 Box X 10 Pack X 500 Pcs | E136: Box | F136: 0.0002 | G136: 22 | H136: 110000 | I136: 14 | J136: 55000 | K136: 125000 | L136: =IFERROR((K136/H136*30),0) -> 34.090909 | M136: IN STOCK | N136: FOLLOW UP DELIVERY | O136: 1
A137: 104 | B137: PM-00333 | C137: Printed cash roll Four colors size 80 x 70 , 37 meter ( BREEHANT ) ورق كاشير ماشير مطبوع ( بريهانت ) | D137: 1 Box X 50 Roll | F137: 0.02 | G137: 24 | H137: 1200 | I137: 14 | J137: 600 | K137: 1450 | L137: =IFERROR((K137/H137*30),0) -> 36.25 | M137: IN STOCK | N137: FOLLOW UP DELIVERY | O137: 1
A138: 17 | B138: PM-00611 | C138: Coffee Day Box 1 Lt with cup holder | بوكس قهوة اليوم 1 لتر مع قاعدة اكواب | D138: Box X 100 Pcs | E138: Box | F138: 0.01 | G138: 495 | H138: 49500 | I138: 14 | J138: 24750 | K138: 60000 | L138: =IFERROR((K138/H138*30),0) -> 36.363636 | M138: IN STOCK | N138: FOLLOW UP DELIVERY | O138: 1
A139: 26 | B139: PM-00177 | C139: Main Paper cup 7 Oz كوب ورقي 7 اونصه تصميم اساسي | D139: 1Box X 10 Pack X 100 Pcs | E139: Box | F139: 0.001 | G139: 137 | H139: 137000 | I139: 60 | J139: 293571.43 | K139: 171000 | L139: =IFERROR((K139/H139*30),0) -> 37.445255 | M139: ORDER NOW | N139: CRITICAL | O139: 0
A140: 132 | B140: PM-00017 | C140: Marble cake cover ( NAMQ ) غلاف كيكة الماربل ( نمق ) | D140: 1 Box X 2400 Pcs | E140: Box | F140: 0.00041666667 | G140: 10 | H140: 24000 | I140: 14 | J140: 12000 | K140: 30000 | L140: =IFERROR((K140/H140*30),0) -> 37.5 | M140: IN STOCK | N140: FOLLOW UP DELIVERY | O140: 1
A141: 87 | B141: PM-00457 | C141: BREEHANT Small Foggy Plastic Bag 33cm*30cmكيس بلاستيك ضبابي بريهانت لحامل الاكواب الثنائي مقاس 30سم *33سم مع لاصق اغلاق | D141: 1 Box X 11 Kg (615 Pcs) | E141: Box | F141: 0.0016260163 | G141: 96 | H141: 59040 | I141: 14 | J141: 29520 | K141: 77490 | L141: =IFERROR((K141/H141*30),0) -> 39.375 | M141: IN STOCK | N141: FOLLOW UP DELIVERY | O141: 1
...

Sheet Consumables Stock Status
B2: Item Code | C2: Item Description | D2: Packing | E2: UOM | F2: Conversion | G2: QTY in Pack | H2: QTY in Unit | I2: Lead Time | J2: Reordering Point | K2: WH Stocks | L2: Coverage/Day | M2: 0rder Status | N2: Criticality | O2: Stock Status
A3: 273 | B3: CO-00467 | C3: Glass cup 65ml كوب زجاج 65 ملي لتقديم المياه الغازية | D3: 1 Box X 6 Pcs | E3: Box | F3: 0.16666667 | G3: =VLOOKUP($B3,'Master File June-26'!$C$3:$L$670,6,0) -> 22 | H3: =VLOOKUP($B3,'Master File June-26'!$C$3:$L$670,7,0) -> 132 | I3: =VLOOKUP($B3,'Master File June-26'!$C$3:$L$670,8,0) -> 14 | J3: =VLOOKUP($B3,'Master File June-26'!$C$3:$L$670,9,0) -> 66 | K3: =VLOOKUP($B3,'Master File June-26'!$C$3:$L$670,10,0) -> 36 | L3: =IFERROR((K3/H3*30),0) -> 8.1818182 | M3: ORDER NOW | N3: CRITICAL | O3: 0
A4: 215 | B4: CO-00061 | C4: Steam cleaner 1 liter منظف الاستيم 1 لتر | D4: 1 Pcs. X 1 Ltr | E4: Pcs | F4: 1 | G4: =VLOOKUP($B4,'Master File June-26'!$C$3:$L$670,6,0) -> 233 | H4: =VLOOKUP($B4,'Master File June-26'!$C$3:$L$670,7,0) -> 233 | I4: =VLOOKUP($B4,'Master File June-26'!$C$3:$L$670,8,0) -> 14 | J4: =VLOOKUP($B4,'Master File June-26'!$C$3:$L$670,9,0) -> 116.5 | K4: =VLOOKUP($B4,'Master File June-26'!$C$3:$L$670,10,0) -> 38 | L4: =IFERROR((K4/H4*30),0) -> 4.8927039 | M4: ORDER NOW | N4: CRITICAL | O4: 0
A5: 185 | B5: CO-00471 | C5: كوب سراميك 110ملي لتقديم الاسبريسو لون وردي مع بيج (نمق)Ceramic cup, 110 ml, for serving espresso pink and beige color | D5: 1 Pcs | E5: Pcs | F5: 1 | G5: =VLOOKUP($B5,'Master File June-26'!$C$3:$L$670,6,0) -> 0 | H5: =VLOOKUP($B5,'Master File June-26'!$C$3:$L$670,7,0) -> 0 | I5: =VLOOKUP($B5,'Master File June-26'!$C$3:$L$670,8,0) -> 14 | J5: =VLOOKUP($B5,'Master File June-26'!$C$3:$L$670,9,0) -> 0 | K5: =VLOOKUP($B5,'Master File June-26'!$C$3:$L$670,10,0) -> 0 | L5: =IFERROR((K5/H5*30),0) -> 0 | M5: ORDER NOW | N5: CRITICAL | O5: 1
A6: 188 | B6: CO-00393 | C6: Brother Label Maker Printer - طابعه ملصقات | D6: Pcs. | E6: Pcs | F6: 1 | G6: =VLOOKUP($B6,'Master File June-26'!$C$3:$L$670,6,0) -> 11 | H6: =VLOOKUP($B6,'Master File June-26'!$C$3:$L$670,7,0) -> 0 | I6: =VLOOKUP($B6,'Master File June-26'!$C$3:$L$670,8,0) -> 14 | J6: =VLOOKUP($B6,'Master File June-26'!$C$3:$L$670,9,0) -> 0 | K6: =VLOOKUP($B6,'Master File June-26'!$C$3:$L$670,10,0) -> 0 | L6: =IFERROR((K6/H6*30),0) -> 0 | M6: ORDER NOW | N6: CRITICAL | O6: 1
A7: 189 | B7: CO-00468 | C7: Plastic Holder for Cups حامل بلاستيك للاكواب | D7: Pcs. | E7: Pcs | F7: 1 | G7: =VLOOKUP($B7,'Master File June-26'!$C$3:$L$670,6,0) -> 0 | H7: =VLOOKUP($B7,'Master File June-26'!$C$3:$L$670,7,0) -> 0 | I7: =VLOOKUP($B7,'Master File June-26'!$C$3:$L$670,8,0) -> 14 | J7: =VLOOKUP($B7,'Master File June-26'!$C$3:$L$670,9,0) -> 0 | K7: =VLOOKUP($B7,'Master File June-26'!$C$3:$L$670,10,0) -> 0 | L7: =IFERROR((K7/H7*30),0) -> 0 | M7: ORDER NOW | N7: CRITICAL | O7: 1
A8: 195 | B8: CO-00523 | C8: Turner Spoon Full Steel ملعقة ستيل | D8: 1 Pcs | E8: Pcs | F8: 1 | G8: =VLOOKUP($B8,'Master File June-26'!$C$3:$L$670,6,0) -> 11 | H8: =VLOOKUP($B8,'Master File June-26'!$C$3:$L$670,7,0) -> 11 | I8: =VLOOKUP($B8,'Master File June-26'!$C$3:$L$670,8,0) -> 14 | J8: =VLOOKUP($B8,'Master File June-26'!$C$3:$L$670,9,0) -> 5.5 | K8: =VLOOKUP($B8,'Master File June-26'!$C$3:$L$670,10,0) -> 0 | L8: =IFERROR((K8/H8*30),0) -> 0 | M8: ORDER NOW | N8: CRITICAL | O8: 0
A9: 196 | B9: CO-00473 | C9: Loveramics Coffee Spoon Gold 10cm ملعقة اسبريسو | D9: 1 Pcs | E9: Pcs | F9: 1 | G9: =VLOOKUP($B9,'Master File June-26'!$C$3:$L$670,6,0) -> 680 | H9: =VLOOKUP($B9,'Master File June-26'!$C$3:$L$670,7,0) -> 680 | I9: =VLOOKUP($B9,'Master File June-26'!$C$3:$L$670,8,0) -> 14 | J9: =VLOOKUP($B9,'Master File June-26'!$C$3:$L$670,9,0) -> 340 | K9: =VLOOKUP($B9,'Master File June-26'!$C$3:$L$670,10,0) -> 0 | L9: =IFERROR((K9/H9*30),0) -> 0 | M9: ORDER NOW | N9: CRITICAL | O9: 0
A10: 204 | B10: CO-00522 | C10: Ice Scoop S/S Round bottom مغرفة ايس سكوب | D10: 1 Pcs | E10: Pcs | F10: 1 | G10: =VLOOKUP($B10,'Master File June-26'!$C$3:$L$670,6,0) -> 88 | H10: =VLOOKUP($B10,'Master File June-26'!$C$3:$L$670,7,0) -> 88 | I10: =VLOOKUP($B10,'Master File June-26'!$C$3:$L$670,8,0) -> 14 | J10: =VLOOKUP($B10,'Master File June-26'!$C$3:$L$670,9,0) -> 44 | K10: =VLOOKUP($B10,'Master File June-26'!$C$3:$L$670,10,0) -> 0 | L10: =IFERROR((K10/H10*30),0) -> 0 | M10: ORDER NOW | N10: CRITICAL | O10: 0
A11: 205 | B11: CO-00560 | C11: Pitcher JIBBI1000ml بتشر تبخير جيبي الحاد - 1000 مل | D11: 1 Pcs | E11: Pcs | F11: 1 | G11: =VLOOKUP($B11,'Master File June-26'!$C$3:$L$670,6,0) -> 0 | H11: =VLOOKUP($B11,'Master File June-26'!$C$3:$L$670,7,0) -> 0 | I11: =VLOOKUP($B11,'Master File June-26'!$C$3:$L$670,8,0) -> 14 | J11: =VLOOKUP($B11,'Master File June-26'!$C$3:$L$670,9,0) -> 0 | K11: =VLOOKUP($B11,'Master File June-26'!$C$3:$L$670,10,0) -> 0 | L11: =IFERROR((K11/H11*30),0) -> 0 | M11: ORDER NOW | N11: CRITICAL | O11: 1
A12: 216 | B12: CO-00094 | C12: Cafetto Grinder Clean اقراص تنظيف طاحونة كافييتو | D12: Pcs | E12: Pcs | F12: 1 | G12: =VLOOKUP($B12,'Master File June-26'!$C$3:$L$670,6,0) -> 367.5 | H12: =VLOOKUP($B12,'Master File June-26'!$C$3:$L$670,7,0) -> 367.5 | I12: =VLOOKUP($B12,'Master File June-26'!$C$3:$L$670,8,0) -> 14 | J12: =VLOOKUP($B12,'Master File June-26'!$C$3:$L$670,9,0) -> 183.75 | K12: =VLOOKUP($B12,'Master File June-26'!$C$3:$L$670,10,0) -> 0 | L12: =IFERROR((K12/H12*30),0) -> 0 | M12: ORDER NOW | N12: CRITICAL | O12: 0
A13: 221 | B13: CO-00127 | C13: Microfiber mop with stick ممسحة مايكروفايبر مع العصا | D13: Pcs. | E13: Pcs | F13: 1 | G13: =VLOOKUP($B13,'Master File June-26'!$C$3:$L$670,6,0) -> 115.5 | H13: =VLOOKUP($B13,'Master File June-26'!$C$3:$L$670,7,0) -> 115.5 | I13: =VLOOKUP($B13,'Master File June-26'!$C$3:$L$670,8,0) -> 14 | J13: =VLOOKUP($B13,'Master File June-26'!$C$3:$L$670,9,0) -> 57.75 | K13: =VLOOKUP($B13,'Master File June-26'!$C$3:$L$670,10,0) -> 0 | L13: =IFERROR((K13/H13*30),0) -> 0 | M13: ORDER NOW | N13: CRITICAL | O13: 0
A14: 224 | B14: CO-00148 | C14: SINGLE FIX FLOORWIPER ممسحة شفط الارضيات 45 سم | D14: 1 Pcs. | E14: Pcs | F14: 1 | G14: =VLOOKUP($B14,'Master File June-26'!$C$3:$L$670,6,0) -> 99 | H14: =VLOOKUP($B14,'Master File June-26'!$C$3:$L$670,7,0) -> 99 | I14: =VLOOKUP($B14,'Master File June-26'!$C$3:$L$670,8,0) -> 14 | J14: =VLOOKUP($B14,'Master File June-26'!$C$3:$L$670,9,0) -> 49.5 | K14: =VLOOKUP($B14,'Master File June-26'!$C$3:$L$670,10,0) -> 0 | L14: =IFERROR((K14/H14*30),0) -> 0 | M14: ORDER NOW | N14: CRITICAL | O14: 0
... A149: 331 | B149: CO-00121 | C149: Gloves Vinyl Large - Clear قفازات فينيل كبيرة - شفاف | D149: Box | E149: Box | F149: 0.001 | G149: =VLOOKUP($B149,'Master File June-26'!$C$3:$L$670,6,0) -> 5 | H149: =VLOOKUP($B149,'Master File June-26'!$C$3:$L$670,7,0) -> 5000 | I149: =VLOOKUP($B149,'Master File June-26'!$C$3:$L$670,8,0) -> 14 | J149: =VLOOKUP($B149,'Master File June-26'!$C$3:$L$670,9,0) -> 2500 | K149: =VLOOKUP($B149,'Master File June-26'!$C$3:$L$670,10,0) -> 0 | L149: =IFERROR((K149/H149*30),0) -> 0 | M149: IN STOCK | N149: FOLLOW UP DELIVERY | O149: 1
O150: =SUM(O3:O149) -> 61
O151: =O150/147 -> 0.41496599

Sheet Dashboard - WH Situation
A2: Status | B2: All Items - Stock Status | C2: Raw Material - Stock Status | D2: Packiging Material - Stock Status | E2: Consumables - Stock Status
A3: % Available | B3: =SUM('All WH Stock Status'!$S$3:$S$667)/COUNT('All WH Stock Status'!$S$3:$S$667) -> 0.21804511 | C3: =SUM('Raw Material Stock status'!$N$3:$N$264)/COUNT('Raw Material Stock status'!$N$3:$N$264) -> 0.54580153 | D3: =SUM('Packiging Materila Stock Status'!$O$3:$O$185)/COUNT('Packiging Materila Stock Status'!$O$3:$O$185) -> 0.53005464 | E3: =SUM('Consumables Stock Status'!$O$3:$O$149)/COUNT('Consumables Stock Status'!$O$3:$O$149) -> 0.41496599
A4: Shortage Item | B4: =1-B3 -> 0.78195489 | C4: =1-C3 -> 0.45419847 | D4: =1-D3 -> 0.46994536 | E4: =1-E3 -> 0.58503401
E18: ,

Sheet Urgent Items - Procurment
H1: Monthly Demand | M1: Critical Items
B2: Category | C2: Item Code | D2: Item Description | E2: Packing | F2: UOM | G2: Conversion | H2: QTY in Pack | I2: QTY in Unit | J2: Lead Time | K2: Reordering Point | L2: WH Stocks | M2: Coverage/Day | N2: 0rder Status | O2: Criticality | P2: Category | Q2: Date Added
A3: 440 | B3: FROZEN ITEMS - منتجات مجمدة | C3: RM-00109 | D3: Sour cream | كريمة حامضة | E3: 1 box x 10 pcs x 1 kg | F3: Box | G3: 0.1 | H3: 30 | I3: =H3/G3 -> 300 | J3: =VLOOKUP(C3,'Master File June-26'!C:J,8,0) -> 14 | K3: =I3*(J3/25) -> 168 | L3: =VLOOKUP(C3,'Master File June-26'!C:L,10,0) -> 0 | M3: =IFERROR((L3/I3*30),0) -> 0 | N3: =IF(M3<J3,"ORDER NOW","IN STOCK") -> ORDER NOW | O3: =IF(M3<J3,"CRITICAL","FOLLOW UP DELIVERY") -> CRITICAL | Q3: =VLOOKUP(C3,[2]Sheet1!$C$3:$P$524,14,0) -> #N/A
A4: 432 | B4: Dry Goods - منتجات جافة | C4: RM-00490 | D4: Sasa Salt ملح ساسا | E4: 1 Box X 24 Pcs X 700 Grm | F4: Box | G4: 0.05952381 | H4: 16 | I4: =H4/G4 -> 268.8 | J4: =VLOOKUP(C4,'Master File June-26'!C:J,8,0) -> 14 | K4: =I4*(J4/25) -> 150.528 | L4: =VLOOKUP(C4,'Master File June-26'!C:L,10,0) -> 0 | M4: =IFERROR((L4/I4*30),0) -> 0 | N4: =IF(M4<J4,"ORDER NOW","IN STOCK") -> ORDER NOW | O4: =IF(M4<J4,"CRITICAL","FOLLOW UP DELIVERY") -> CRITICAL | Q4: =VLOOKUP(C4,'Master File June-26'!$C$3:$S$670,17,0) -> 46141.526
A5: 433 | B5: Dry Goods - منتجات جافة | C5: RM-00203 | D5: Bicarbonate Gethai بيكربونات الصوديوم | E5: 1 Box X 72 Pcs X 100 Grm | F5: Box | G5: 0.13888889 | H5: 38 | I5: =H5/G5 -> 273.6 | J5: =VLOOKUP(C5,'Master File June-26'!C:J,8,0) -> 14 | K5: =I5*(J5/25) -> 153.216 | L5: =VLOOKUP(C5,'Master File June-26'!C:L,10,0) -> 0 | M5: =IFERROR((L5/I5*30),0) -> 0 | N5: =IF(M5<J5,"ORDER NOW","IN STOCK") -> ORDER NOW | O5: =IF(M5<J5,"CRITICAL","FOLLOW UP DELIVERY") -> CRITICAL | Q5: =VLOOKUP(C5,[2]Sheet1!$C$3:$P$524,14,0) -> #N/A
A6: 362 | B6: Beverage - مشروبات | C6: RM-00509 | D6: Syrup Raspberry Polot توت أحمر سيروب - بولوت | E6: 1 Box X 6 Bottle X 700 ml | F6: Box | G6: 0.23809524 | H6: 90.5 | I6: =H6/G6 -> 380.1 | J6: =VLOOKUP(C6,'Master File June-26'!C:J,8,0) -> 14 | K6: =I6*(J6/25) -> 212.856 | L6: =VLOOKUP(C6,'Master File June-26'!C:L,10,0) -> 0 | M6: =IFERROR((L6/I6*30),0) -> 0 | N6: =IF(M6<J6,"ORDER NOW","IN STOCK") -> ORDER NOW | O6: =IF(M6<J6,"CRITICAL","FOLLOW UP DELIVERY") -> CRITICAL | Q6: =VLOOKUP(C6,[2]Sheet1!$C$3:$P$524,14,0) -> #N/A
A7: 401 | B7: Beverage - مشروبات / Dairy | C7: RM-00508 | D7: Condensed milkحليب مكثف | E7: 1 Box X 24 Pcs. X 1 Kilo | F7: Box | G7: 0.041666667 | H7: =VLOOKUP(C7,'Master File June-26'!$C$3:$I$670,6,0) -> 56 | I7: =VLOOKUP(C7,'Master File June-26'!$C$3:$I$670,7,0) -> 1344 | J7: =VLOOKUP(C7,'Master File June-26'!C:J,8,0) -> 14 | K7: =I7*(J7/25) -> 752.64 | L7: =VLOOKUP(C7,'Master File June-26'!C:L,10,0) -> 5884.8 | M7: =IFERROR((L7/I7*30),0) -> 131.35714 | N7: =IF(M7<J7,"ORDER NOW","IN STOCK") -> IN STOCK | O7: =IF(M7<J7,"CRITICAL","FOLLOW UP DELIVERY") -> FOLLOW UP DELIVERY | Q7: =VLOOKUP(C7,'Master File June-26'!$C$3:$S$670,17,0) -> 46138.438
A8: 371 | B8: Beverage - مشروبات | C8: RM-00569 | D8: Syrup Pomegranate Teisseire سيروب تيسير رمان | E8: 1 Box X 6 Bottle X 1 Ltr | F8: Box | G8: 0.16666667 | H8: =VLOOKUP(C8,'Master File June-26'!$C$3:$I$670,6,0) -> 30.5 | I8: =VLOOKUP(C8,'Master File June-26'!$C$3:$I$670,7,0) -> 183 | J8: =VLOOKUP(C8,'Master File June-26'!C:J,8,0) -> 14 | K8: =I8*(J8/25) -> 102.48 | L8: =VLOOKUP(C8,'Master File June-26'!C:L,10,0) -> 0 | M8: =IFERROR((L8/I8*30),0) -> 0 | N8: =IF(M8<J8,"ORDER NOW","IN STOCK") -> ORDER NOW | O8: =IF(M8<J8,"CRITICAL","FOLLOW UP DELIVERY") -> CRITICAL | Q8: =VLOOKUP(C8,'Master File June-26'!$C$3:$S$670,17,0) -> 46128.695
A9: 474 | B9: Dry Goods - منتجات جافة | C9: RM-00243 | D9: Biscuit Filling With Crunchy Pieces Ripieno | حشوة البسكويت مع كسر | E9: 1 box x 2 tin x 5 kg | F9: Box | G9: 0.1 | H9: 80 | I9: =H9/G9 -> 800 | J9: =VLOOKUP(C9,'Master File June-26'!C:J,8,0) -> 14 | K9: =I9*(J9/25) -> 448 | L9: =VLOOKUP(C9,'Master File June-26'!C:L,10,0) -> 0 | M9: =IFERROR((L9/I9*30),0) -> 0 | N9: =IF(M9<J9,"ORDER NOW","IN STOCK") -> ORDER NOW | O9: =IF(M9<J9,"CRITICAL","FOLLOW UP DELIVERY") -> CRITICAL | Q9: =VLOOKUP(C9,[2]Sheet1!$C$3:$P$524,14,0) -> #N/A
A10: 370 | B10: Beverage - مشروبات | C10: RM-00563 | D10: Syrup Pomegranate 1883 سيروب 1883 رمان | E10: 1 Box X 6 Bottle X 1 Ltr | F10: Box | G10: 0.16666667 | H10: 50 | I10: =H10/G10 -> 300 | J10: =VLOOKUP(C10,'Master File June-26'!C:J,8,0) -> 14 | K10: =I10*(J10/25) -> 168 | L10: =VLOOKUP(C10,'Master File June-26'!C:L,10,0) -> 390 | M10: =IFERROR((L10/I10*30),0) -> 39 | N10: =IF(M10<J10,"ORDER NOW","IN STOCK") -> IN STOCK | O10: =IF(M10<J10,"CRITICAL","FOLLOW UP DELIVERY") -> FOLLOW UP DELIVERY | Q10: =VLOOKUP(C10,[2]Sheet1!$C$3:$P$524,14,0) -> #N/A
A11: 455 | B11: Beverage - مشروبات | C11: RM-00449 | D11: Sunflower Oil Sabrina | زيت دوار الشمس | E11: 1 Pcs X 18 Ltr | F11: Pcs | G11: 0.055555556 | H11: 190 | I11: =H11/G11 -> 3420 | J11: =VLOOKUP(C11,'Master File June-26'!C:J,8,0) -> 14 | K11: =I11*(J11/25) -> 1915.2 | L11: =VLOOKUP(C11,'Master File June-26'!C:L,10,0) -> 0 | M11: =IFERROR((L11/I11*30),0) -> 0 | N11: =IF(M11<J11,"ORDER NOW","IN STOCK") -> ORDER NOW | O11: =IF(M11<J11,"CRITICAL","FOLLOW UP DELIVERY") -> CRITICAL | Q11: =VLOOKUP(C11,[2]Sheet1!$C$3:$P$524,14,0) -> #N/A
A12: 469 | B12: Dry Goods - منتجات جافة | C12: RM-00048 | D12: CT 0314/G Drops 15KG Bag شوكلاته اقراص CT 0314/G ( هوت تشوكلت ) | E12: 1 Bag X 15 KG | F12: bag | G12: 0.066666667 | H12: =VLOOKUP(C12,'Master File June-26'!$C$3:$I$670,6,0) -> 80 | I12: =VLOOKUP(C12,'Master File June-26'!$C$3:$I$670,7,0) -> 1200 | J12: =VLOOKUP(C12,'Master File June-26'!C:J,8,0) -> 14 | K12: =I12*(J12/25) -> 672 | L12: =VLOOKUP(C12,'Master File June-26'!C:L,10,0) -> 750 | M12: =IFERROR((L12/I12*30),0) -> 18.75 | N12: =IF(M12<J12,"ORDER NOW","IN STOCK") -> IN STOCK | O12: =IF(M12<J12,"CRITICAL","FOLLOW UP DELIVERY") -> FOLLOW UP DELIVERY | Q12: =VLOOKUP(C12,'Master File June-26'!$C$3:$S$670,17,0) -> 46118.498
A13: 357 | B13: Dry Goods - منتجات جافة | C13: RM-00039 | D13: Nutella Hazelnut نوتيلا | E13: 1 Box X 2 Pail X 3 Kg | F13: Box | G13: 0.16666667 | H13: =VLOOKUP(C13,'Master File June-26'!$C$3:$I$670,6,0) -> 75.5 | I13: =VLOOKUP(C13,'Master File June-26'!$C$3:$I$670,7,0) -> 453 | J13: =VLOOKUP(C13,'Master File June-26'!C:J,8,0) -> 14 | K13: =I13*(J13/25) -> 253.68 | L13: =VLOOKUP(C13,'Master File June-26'!C:L,10,0) -> 0 | M13: =IFERROR((L13/I13*30),0) -> 0 | N13: =IF(M13<J13,"ORDER NOW","IN STOCK") -> ORDER NOW | O13: =IF(M13<J13,"CRITICAL","FOLLOW UP DELIVERY") -> CRITICAL | Q13: 46113.431
A14: 360 | B14: Beverage - مشروبات | C14: RM-00568 | D14: Syrup lemon Teisseire سيروب تيسير ليمون | E14: 1 Box X 6 Bottle X 1 Ltr | F14: Box | G14: 0.16666667 | H14: =VLOOKUP(C14,'Master File June-26'!$C$3:$I$670,6,0) -> 21 | I14: =VLOOKUP(C14,'Master File June-26'!$C$3:$I$670,7,0) -> 126 | J14: =VLOOKUP(C14,'Master File June-26'!C:J,8,0) -> 14 | K14: =I14*(J14/25) -> 70.56 | L14: =VLOOKUP(C14,'Master File June-26'!C:L,10,0) -> 25 | M14: =IFERROR((L14/I14*30),0) -> 5.952381 | N14: =IF(M14<J14,"ORDER NOW","IN STOCK") -> ORDER NOW | O14: =IF(M14<J14,"CRITICAL","FOLLOW UP DELIVERY") -> CRITICAL | Q14: =VLOOKUP(C14,'Master File June-26'!$C$3:$S$670,17,0) -> 46131.52
A15: 541 | B15: Dry Goods - منتجات جافة | C15: RM-00304 | D15: Tamrind Freshly تمر هندي فرشلي | E15: Box | F15: Box | G15: 0.1 | H15: 1 | I15: =H15/G15 -> 10 | J15: =VLOOKUP(C15,'Master File June-26'!C:J,8,0) -> 14 | K15: =I15*(J15/25) -> 5.6 | L15: =VLOOKUP(C15,'Master File June-26'!C:L,10,0) -> 0 | M15: =IFERROR((L15/I15*30),0) -> 0 | N15: =IF(M15<J15,"ORDER NOW","IN STOCK") -> ORDER NOW | O15: =IF(M15<J15,"CRITICAL","FOLLOW UP DELIVERY") -> CRITICAL | Q15: =VLOOKUP(C15,[2]Sheet1!$C$3:$P$524,14,0) -> #N/A
A16: 163 | B16: طباعة وتغليف - Packaging | C16: PM-00509 | D16: قاعدة كيك بريهانت المطبوعة 28سم Breehant Cake Base 28cm | E16: 1 Box x 100 | F16: Box | G16: 0.01 | H16: 13 | I16: =H16/G16 -> 1300 | J16: =VLOOKUP(C16,'Master File June-26'!C:J,8,0) -> 14 | K16: =I16*(J16/25) -> 728 | L16: =VLOOKUP(C16,'Master File June-26'!C:L,10,0) -> 1505 | M16: =IFERROR((L16/I16*30),0) -> 34.730769 | N16: =IF(M16<J16,"ORDER NOW","IN STOCK") -> IN STOCK | O16: =IF(M16<J16,"CRITICAL","FOLLOW UP DELIVERY") -> FOLLOW UP DELIVERY | Q16: =VLOOKUP(C16,'Master File June-26'!$C$3:$S$670,17,0) -> 46128.695
A17: 138 | B17: Consumables | C17: PM-00060 | D17: Golden Cake Plate قاعدة كيك ذهبية 13*4.5 سم | E17: box x 1000 pcs | F17: Pcs | G17: =1/1000 -> 0.001 | H17: 25 | I17: =H17/G17 -> 25000 | J17: =VLOOKUP(C17,'Master File June-26'!C:J,8,0) -> 14 | K17: =I17*(J17/25) -> 14000 | L17: =VLOOKUP(C17,'Master File June-26'!C:L,10,0) -> 0 | M17: =IFERROR((L17/I17*30),0) -> 0 | N17: =IF(M17<J17,"ORDER NOW","IN STOCK") -> ORDER NOW | O17: =IF(M17<J17,"CRITICAL","FOLLOW UP DELIVERY") -> CRITICAL | P17: A | Q17: =VLOOKUP(C17,[2]Sheet1!$C$3:$P$524,14,0) -> #N/A
A18: 218 | B18: Tools - ادوات | C18: CO-00377 | D18: فرشاة تنظيف ايسبزولا مقاس 58 | E18: 1 Pcs | F18: Pcs | G18: 1 | H18: 5.5 | I18: =H18/G18 -> 5.5 | J18: =VLOOKUP(C18,'Master File June-26'!C:J,8,0) -> 14 | K18: =I18*(J18/25) -> 3.08 | L18: =VLOOKUP(C18,'Master File June-26'!C:L,10,0) -> 3 | M18: =IFERROR((L18/I18*30),0) -> 16.363636 | N18: =IF(M18<J18,"ORDER NOW","IN STOCK") -> IN STOCK | O18: =IF(M18<J18,"CRITICAL","FOLLOW UP DELIVERY") -> FOLLOW UP DELIVERY | Q18: =VLOOKUP(C18,[2]Sheet1!$C$3:$P$524,14,0) -> #N/A
A19: 344 | B19: Dry Goods - منتجات جافة | C19: RM-00515 | D19: Mango filling & Topping FRUTTOSE 85% حشوة مانجو | E19: 1 Pcs X 610 G | F19: Pcs | G19: 1.6393443 | H19: =VLOOKUP(C19,'Master File June-26'!$C$3:$I$670,6,0) -> 82.5 | I19: =VLOOKUP(C19,'Master File June-26'!$C$3:$I$670,7,0) -> 50.325 | J19: =VLOOKUP(C19,'Master File June-26'!C:J,8,0) -> 14 | K19: =I19*(J19/25) -> 28.182 | L19: =VLOOKUP(C19,'Master File June-26'!C:L,10,0) -> 140 | M19: =IFERROR((L19/I19*30),0) -> 83.457526 | N19: =IF(M19<J19,"ORDER NOW","IN STOCK") -> IN STOCK | O19: =IF(M19<J19,"CRITICAL","FOLLOW UP DELIVERY") -> FOLLOW UP DELIVERY | Q19: =VLOOKUP(C19,'Master File June-26'!$C$3:$S$670,17,0) -> 46113.431
A20: 387 | B20: FROZEN ITEMS - منتجات مجمدة | C20: RM-00016 | D20: Parmesan Italian Cheese جبن بارميزان | E20: KG | F20: Pcs | G20: 1 | H20: 27.5 | I20: =H20/G20 -> 27.5 | J20: =VLOOKUP(C20,'Master File June-26'!C:J,8,0) -> 14 | K20: =I20*(J20/25) -> 15.4 | L20: =VLOOKUP(C20,'Master File June-26'!C:L,10,0) -> 5 | M20: =IFERROR((L20/I20*30),0) -> 5.4545455 | N20: =IF(M20<J20,"ORDER NOW","IN STOCK") -> ORDER NOW | O20: =IF(M20<J20,"CRITICAL","FOLLOW UP DELIVERY") -> CRITICAL | Q20: =VLOOKUP(C20,[2]Sheet1!$C$3:$P$524,14,0) -> #N/A
A21: 48 | B21: Tools - ادوات | C21: PM-00242 | D21: Cafec V60 Filter 02 Coffee Filter كافيك فلاتر ترشيح ورقية - مقاس 02 | E21: 1 Box X 80 Case X 100 PCS | F21: Box | G21: =1/8000 -> 0.000125 | H21: 25 | I21: =H21/G21 -> 200000 | J21: =VLOOKUP(C21,'Master File June-26'!C:J,8,0) -> 14 | K21: =I21*(J21/25) -> 112000 | L21: =VLOOKUP(C21,'Master File June-26'!C:L,10,0) -> 119900 | M21: =IFERROR((L21/I21*30),0) -> 17.985 | N21: =IF(M21<J21,"ORDER NOW","IN STOCK") -> IN STOCK | O21: =IF(M21<J21,"CRITICAL","FOLLOW UP DELIVERY") -> FOLLOW UP DELIVERY | P21: A | Q21: =VLOOKUP(C21,'Master File June-26'!$C$3:$S$670,17,0) -> 46141.526
A22: 102 | B22: طباعة وتغليف - Packaging | C22: PM-00357 | D22: Pomegranate Iced Tea Sticker ( breehant ) ستيكر شاي مثلج بالرمان (بريهانت) | E22: 1 bundle X 500 PCS | F22: bundel | G22: 0.002 | H22: =VLOOKUP(C22,'Master File June-26'!$C$3:$I$670,6,0) -> 16 | I22: =VLOOKUP(C22,'Master File June-26'!$C$3:$I$670,7,0) -> 8000 | J22: =VLOOKUP(C22,'Master File June-26'!C:J,8,0) -> 14 | K22: =I22*(J22/25) -> 4480 | L22: =VLOOKUP(C22,'Master File June-26'!C:L,10,0) -> 3000 | M22: =IFERROR((L22/I22*30),0) -> 11.25 | N22: =IF(M22<J22,"ORDER NOW","IN STOCK") -> ORDER NOW | O22: =IF(M22<J22,"CRITICAL","FOLLOW UP DELIVERY") -> CRITICAL | P22: A | Q22: =VLOOKUP(C22,'Master File June-26'!$C$3:$S$670,17,0) -> 46118.498
A23: 129 | B23: طباعة وتغليف - Packaging | C23: PM-00105 | D23: Crunchy Chocolate box (BREEHANT) بوكس كرانشي شوكلت ( بريهانت ) | E23: 1 Box X 200 Pcs | F23: Box | G23: =1/200 -> 0.005 | H23: =VLOOKUP(C23,'Master File June-26'!$C$3:$I$670,6,0) -> 50 | I23: =VLOOKUP(C23,'Master File June-26'!$C$3:$I$670,7,0) -> 10000 | J23: =VLOOKUP(C23,'Master File June-26'!C:J,8,0) -> 14 | K23: =I23*(J23/25) -> 5600 | L23: =VLOOKUP(C23,'Master File June-26'!C:L,10,0) -> 0 | M23: =IFERROR((L23/I23*30),0) -> 0 | N23: =IF(M23<J23,"ORDER NOW","IN STOCK") -> ORDER NOW | O23: =IF(M23<J23,"CRITICAL","FOLLOW UP DELIVERY") -> CRITICAL | P23: A | Q23: =VLOOKUP(C23,'Master File June-26'!$C$3:$S$670,17,0) -> 46113.431
A24: 353 | B24: Dry Goods - منتجات جافة | C24: RM-00050 | D24: Happy cao Cocoa powder بودرة كاكاو هابي كاو | E24: 1 Bag X 10 Kg | F24: bag | G24: 0.1 | H24: 30.25 | I24: =H24/G24 -> 302.5 | J24: =VLOOKUP(C24,'Master File June-26'!C:J,8,0) -> 14 | K24: =I24*(J24/25) -> 169.4 | L24: =VLOOKUP(C24,'Master File June-26'!C:L,10,0) -> 10 | M24: =IFERROR((L24/I24*30),0) -> 0.99173554 | N24: =IF(M24<J24,"ORDER NOW","IN STOCK") -> ORDER NOW | O24: =IF(M24<J24,"CRITICAL","FOLLOW UP DELIVERY") -> CRITICAL | Q24: =VLOOKUP(C24,'Master File June-26'!$C$3:$S$670,17,0) -> 46131.432
A25: 3 | B25: طباعة وتغليف - Packaging | C25: PM-00255 | D25: Namq Straw شفاط نمق | E25: 1 Box X 30 Pack X 100 Pcs | F25: Box | G25: 0.00033333333 | H25: 83.5 | I25: =H25/G25 -> 250500 | J25: =VLOOKUP(C25,'Master File June-26'!C:J,8,0) -> 14 | K25: =I25*(J25/25) -> 140280 | L25: =VLOOKUP(C25,'Master File June-26'!C:L,10,0) -> 149000 | M25: =IFERROR((L25/I25*30),0) -> 17.844311 | N25: =IF(M25<J25,"ORDER NOW","IN STOCK") -> IN STOCK | O25: =IF(M25<J25,"CRITICAL","FOLLOW UP DELIVERY") -> FOLLOW UP DELIVERY | P25: A | Q25: =VLOOKUP(C25,[2]Sheet1!$C$3:$P$524,14,0) -> #N/A
A26: 269 | B26: Tools - ادوات | C26: CO-00493 | D26: Retina Diffuser Screw For La Marzocco IMS Shower Screen مسمار شاور سكرين لامارزوكو - 6 فتحات | E26: Pcs. | F26: Pcs | G26: 1 | H26: =VLOOKUP(C26,'Master File June-26'!$C$3:$I$670,6,0) -> 99 | I26: =VLOOKUP(C26,'Master File June-26'!$C$3:$I$670,7,0) -> 99 | J26: =VLOOKUP(C26,'Master File June-26'!C:J,8,0) -> 14 | K26: =I26*(J26/25) -> 55.44 | L26: =VLOOKUP(C26,'Master File June-26'!C:L,10,0) -> 0 | M26: =IFERROR((L26/I26*30),0) -> 0 | N26: =IF(M26<J26,"ORDER NOW","IN STOCK") -> ORDER NOW | O26: =IF(M26<J26,"CRITICAL","FOLLOW UP DELIVERY") -> CRITICAL | Q26: =VLOOKUP(C26,'Master File June-26'!$C$3:$S$670,17,0) -> 46128.695
A27: 96 | B27: طباعة وتغليف - Packaging | C27: PM-00287 | D27: lids Cups Brehehant 6.5 Oz 80 ml اغطية اكواب القهوة - بريهانت 6.5 اونصه | E27: 1 Box X 20 Pack X 50 Pcs | F27: Box | G27: 0.001 | H27: =VLOOKUP(C27,'Master File June-26'!$C$3:$I$670,6,0) -> 18 | I27: =VLOOKUP(C27,'Master File June-26'!$C$3:$I$670,7,0) -> 18000 | J27: =VLOOKUP(C27,'Master File June-26'!C:J,8,0) -> 14 | K27: =I27*(J27/25) -> 10080 | L27: =VLOOKUP(C27,'Master File June-26'!C:L,10,0) -> 0 | M27: =IFERROR((L27/I27*30),0) -> 0 | N27: =IF(M27<J27,"ORDER NOW","IN STOCK") -> ORDER NOW | O27: =IF(M27<J27,"CRITICAL","FOLLOW UP DELIVERY") -> CRITICAL | P27: A | Q27: =VLOOKUP(C27,'Master File June-26'!$C$3:$S$670,17,0) -> 46141.525
A28: 420 | B28: Dry Goods - منتجات جافة | C28: RM-00111 | D28: FINAH Premium white flour 45 kg دقيق ابيض فاخر - طحين للمعمل | E28: 1 Bag X 45 Kg | F28: bag | G28: 0.022222222 | H28: =VLOOKUP(C28,'Master File June-26'!$C$3:$I$670,6,0) -> 160 | I28: =VLOOKUP(C28,'Master File June-26'!$C$3:$I$670,7,0) -> 7200 | J28: =VLOOKUP(C28,'Master File June-26'!C:J,8,0) -> 14 | K28: =I28*(J28/25) -> 4032 | L28: =VLOOKUP(C28,'Master File June-26'!C:L,10,0) -> 4840 | M28: =IFERROR((L28/I28*30),0) -> 20.166667 | N28: =IF(M28<J28,"ORDER NOW","IN STOCK") -> IN STOCK | O28: =IF(M28<J28,"CRITICAL","FOLLOW UP DELIVERY") -> FOLLOW UP DELIVERY | Q28: 46113.431
A29: 286 | B29: Consumables | C29: CO-00158 | D29: تايقر فيتنامي بخور - Bokhur Tiger | E29: Pcs. | F29: Pcs | G29: 1 | H29: =VLOOKUP(C29,'Master File June-26'!$C$3:$I$670,6,0) -> 44 | I29: =VLOOKUP(C29,'Master File June-26'!$C$3:$I$670,7,0) -> 44 | J29: =VLOOKUP(C29,'Master File June-26'!C:J,8,0) -> 14 | K29: =I29*(J29/25) -> 24.64 | L29: =VLOOKUP(C29,'Master File June-26'!C:L,10,0) -> 0 | M29: =IFERROR((L29/I29*30),0) -> 0 | N29: =IF(M29<J29,"ORDER NOW","IN STOCK") -> ORDER NOW | O29: =IF(M29<J29,"CRITICAL","FOLLOW UP DELIVERY") -> CRITICAL | Q29: =VLOOKUP(C29,'Master File June-26'!$C$3:$S$670,17,0) -> 46113.431
A30: 101 | B30: طباعة وتغليف - Packaging | C30: PM-00503 | D30: Sunset Passion Drink Sticker - استيكر مشروب سنسيت باشن محتاج | E30: 1 Box X 500 | F30: Box | G30: 0.002 | H30: =VLOOKUP(C30,'Master File June-26'!$C$3:$I$670,6,0) -> 24 | I30: =VLOOKUP(C30,'Master File June-26'!$C$3:$I$670,7,0) -> 12000 | J30: =VLOOKUP(C30,'Master File June-26'!C:J,8,0) -> 14 | K30: =I30*(J30/25) -> 6720 | L30: =VLOOKUP(C30,'Master File June-26'!C:L,10,0) -> 3000 | M30: =IFERROR((L30/I30*30),0) -> 7.5 | N30: =IF(M30<J30,"ORDER NOW","IN STOCK") -> ORDER NOW | O30: =IF(M30<J30,"CRITICAL","FOLLOW UP DELIVERY") -> CRITICAL | P30: A | Q30: =VLOOKUP(C30,'Master File June-26'!$C$3:$S$670,17,0) -> 46128.696
A31: 34 | B31: طباعة وتغليف - Packaging | C31: PM-00197 | D31: Plastic cup Full Printed 14oz كوب بلاستيك مطبوعه 14 اونصه | E31: 1 Box X 500 Pcs. | F31: Box | G31: 0.002 | H31: =VLOOKUP(C31,'Master File June-26'!$C$3:$I$670,6,0) -> 192.5 | I31: =VLOOKUP(C31,'Master File June-26'!$C$3:$I$670,7,0) -> 96250 | J31: =VLOOKUP(C31,'Master File June-26'!C:J,8,0) -> 60 | K31: =I31*(J31/25) -> 231000 | L31: =VLOOKUP(C31,'Master File June-26'!C:L,10,0) -> 0 | M31: =IFERROR((L31/I31*30),0) -> 0 | N31: =IF(M31<J31,"ORDER NOW","IN STOCK") -> ORDER NOW | O31: =IF(M31<J31,"CRITICAL","FOLLOW UP DELIVERY") -> CRITICAL | P31: A | Q31: =VLOOKUP(C31,'Master File June-26'!$C$3:$S$670,17,0) -> 46128.695
A32: 192 | B32: Tools - ادوات | C32: CO-00490 | D32: Toddy Timerمؤقت تودي | E32: Pcs. | F32: Pcs | G32: 1 | H32: =VLOOKUP(C32,'Master File June-26'!$C$3:$I$670,6,0) -> 134 | I32: =VLOOKUP(C32,'Master File June-26'!$C$3:$I$670,7,0) -> 134 | J32: =VLOOKUP(C32,'Master File June-26'!C:J,8,0) -> 14 | K32: =I32*(J32/25) -> 75.04 | L32: =VLOOKUP(C32,'Master File June-26'!C:L,10,0) -> 0 | M32: =IFERROR((L32/I32*30),0) -> 0 | N32: =IF(M32<J32,"ORDER NOW","IN STOCK") -> ORDER NOW | O32: =IF(M32<J32,"CRITICAL","FOLLOW UP DELIVERY") -> CRITICAL | Q32: =VLOOKUP(C32,'Master File June-26'!$C$3:$S$670,17,0) -> 46113.431
A33: 384 | B33: Dry Goods - منتجات جافة | C33: RM-00673 | D33: Valrhona Javira 40% / شوكولاته فالرهونا | E33: 1 Box X 3 x 3 KG | F33: Box | G33: =1/9 -> 0.11111111 | H33: =VLOOKUP(C33,'Master File June-26'!$C$3:$I$670,6,0) -> 22 | I33: =VLOOKUP(C33,'Master File June-26'!$C$3:$I$670,7,0) -> 198 | J33: =VLOOKUP(C33,'Master File June-26'!C:J,8,0) -> 14 | K33: =I33*(J33/25) -> 110.88 | L33: =VLOOKUP(C33,'Master File June-26'!C:L,10,0) -> 0 | M33: =IFERROR((L33/I33*30),0) -> 0 | N33: =IF(M33<J33,"ORDER NOW","IN STOCK") -> ORDER NOW | O33: =IF(M33<J33,"CRITICAL","FOLLOW UP DELIVERY") -> CRITICAL | Q33: =VLOOKUP(C33,'Master File June-26'!$C$3:$S$670,17,0) -> 46128.686
A34: 52 | B34: طباعة وتغليف - Packaging | C34: PM-00660 | D34: سليف صحن البروكيز | tray sleeve for brokes | E34: 1 Bundle X 1000 Pcs | F34: Box | G34: =1/1000 -> 0.001 | H34: 10 | I34: =H34/G34 -> 10000 | J34: =VLOOKUP(C34,'Master File June-26'!C:J,8,0) -> 14 | K34: =I34*(J34/25) -> 5600 | L34: =VLOOKUP(C34,'Master File June-26'!C:L,10,0) -> 0 | M34: =IFERROR((L34/I34*30),0) -> 0 | N34: =IF(M34<J34,"ORDER NOW","IN STOCK") -> ORDER NOW | O34: =IF(M34<J34,"CRITICAL","FOLLOW UP DELIVERY") -> CRITICAL | P34: A | Q34: =VLOOKUP(C34,[2]Sheet1!$C$3:$P$524,14,0) -> #N/A
A35: 11 | B35: طباعة وتغليف - Packaging | C35: PM-00568 | D35: كيس مخبوزات مطبوع مقاس 10 × 14.5 cm (نمق)-Printed Bakery Paper Bag, 10 × 14.5 cm(Namq) | E35: 1Box X 8000 | F35: Box | G35: =1/8000 -> 0.000125 | H35: =VLOOKUP(C35,'Master File June-26'!$C$3:$I$670,6,0) -> 8 | I35: =VLOOKUP(C35,'Master File June-26'!$C$3:$I$670,7,0) -> 64000 | J35: =VLOOKUP(C35,'Master File June-26'!C:J,8,0) -> 14 | K35: =I35*(J35/25) -> 35840 | L35: =VLOOKUP(C35,'Master File June-26'!C:L,10,0) -> 150 | M35: =IFERROR((L35/I35*30),0) -> 0.0703125 | N35: =IF(M35<J35,"ORDER NOW","IN STOCK") -> ORDER NOW | O35: =IF(M35<J35,"CRITICAL","FOLLOW UP DELIVERY") -> CRITICAL | P35: A | Q35: =VLOOKUP(C35,'Master File June-26'!$C$3:$S$670,17,0) -> 46141.525
A36: 97 | B36: طباعة وتغليف - Packaging | C36: PM-00270 | D36: lids Cups Brehehant with stick اغطية اكواب القهوة - بريهانت | E36: 1 Box X 20 Pack X 50 Pcs | F36: Box | G36: 0.001 | H36: =VLOOKUP(C36,'Master File June-26'!$C$3:$I$670,6,0) -> 400 | I36: =VLOOKUP(C36,'Master File June-26'!$C$3:$I$670,7,0) -> 400000 | J36: =VLOOKUP(C36,'Master File June-26'!C:J,8,0) -> 14 | K36: =I36*(J36/25) -> 224000 | L36: =VLOOKUP(C36,'Master File June-26'!C:L,10,0) -> 0 | M36: =IFERROR((L36/I36*30),0) -> 0 | N36: =IF(M36<J36,"ORDER NOW","IN STOCK") -> ORDER NOW | O36: =IF(M36<J36,"CRITICAL","FOLLOW UP DELIVERY") -> CRITICAL | P36: A | Q36: =VLOOKUP(C36,'Master File June-26'!$C$3:$S$670,17,0) -> 46128.686
A37: 539 | B37: Dry Goods - منتجات جافة | C37: RM-00502 | D37: Sugar Jaggery Vijay سكر جاجيري مدور | E37: Box | F37: Box | G37: 1 | H37: 2 | I37: =H37/G37 -> 2 | J37: =VLOOKUP(C37,'Master File June-26'!C:J,8,0) -> 14 | K37: =I37*(J37/25) -> 1.12 | L37: =VLOOKUP(C37,'Master File June-26'!C:L,10,0) -> 0 | M37: =IFERROR((L37/I37*30),0) -> 0 | N37: =IF(M37<J37,"ORDER NOW","IN STOCK") -> ORDER NOW | O37: =IF(M37<J37,"CRITICAL","FOLLOW UP DELIVERY") -> CRITICAL | Q37: =VLOOKUP(C37,[2]Sheet1!$C$3:$P$524,14,0) -> #N/A
A38: 158 | B38: Consumables | C38: PM-00281 | D38: Roll packing machine رول مكينة تغليف | E38: Pcs. | F38: Pcs | G38: 1 | H38: =VLOOKUP(C38,'Master File June-26'!$C$3:$I$670,6,0) -> 80 | I38: =VLOOKUP(C38,'Master File June-26'!$C$3:$I$670,7,0) -> 80 | J38: =VLOOKUP(C38,'Master File June-26'!C:J,8,0) -> 14 | K38: =I38*(J38/25) -> 44.8 | L38: =VLOOKUP(C38,'Master File June-26'!C:L,10,0) -> 0 | M38: =IFERROR((L38/I38*30),0) -> 0 | N38: =IF(M38<J38,"ORDER NOW","IN STOCK") -> ORDER NOW | O38: =IF(M38<J38,"CRITICAL","FOLLOW UP DELIVERY") -> CRITICAL | Q38: =VLOOKUP(C38,'Master File June-26'!$C$3:$S$670,17,0) -> 46113.431
A39: 53 | B39: طباعة وتغليف - Packaging | C39: PM-00655 | D39: سليف زجاجة ايس تي | Glass sleeve for iced | E39: 1 Box X 600 Pcs | F39: Box | G39: =1/600 -> 0.0016666667 | H39: =VLOOKUP(C39,'Master File June-26'!$C$3:$I$670,6,0) -> 20 | I39: =VLOOKUP(C39,'Master File June-26'!$C$3:$I$670,7,0) -> 12000 | J39: =VLOOKUP(C39,'Master File June-26'!C:J,8,0) -> 14 | K39: =I39*(J39/25) -> 6720 | L39: =VLOOKUP(C39,'Master File June-26'!C:L,10,0) -> 0 | M39: =IFERROR((L39/I39*30),0) -> 0 | N39: =IF(M39<J39,"ORDER NOW","IN STOCK") -> ORDER NOW | O39: =IF(M39<J39,"CRITICAL","FOLLOW UP DELIVERY") -> CRITICAL | P39: A | Q39: =VLOOKUP(C39,'Master File June-26'!$C$3:$S$670,17,0) -> 46128.688
A40: 160 | B40: طباعة وتغليف - Packaging | C40: PM-00606 | D40: Round aluminum plate 110 ml with cover | صحن دائري مع غطاء 110 مل | E40: Pcs. | F40: Pcs | G40: 1 | H40: =VLOOKUP(C40,'Master File June-26'!$C$3:$I$670,6,0) -> 60000 | I40: =VLOOKUP(C40,'Master File June-26'!$C$3:$I$670,7,0) -> 60000 | J40: =VLOOKUP(C40,'Master File June-26'!C:J,8,0) -> 14 | K40: =I40*(J40/25) -> 33600 | L40: =VLOOKUP(C40,'Master File June-26'!C:L,10,0) -> 0 | M40: =IFERROR((L40/I40*30),0) -> 0 | N40: =IF(M40<J40,"ORDER NOW","IN STOCK") -> ORDER NOW | O40: =IF(M40<J40,"CRITICAL","FOLLOW UP DELIVERY") -> CRITICAL | Q40: =VLOOKUP(C40,'Master File June-26'!$C$3:$S$670,17,0) -> 46138.481
A41: 46 | B41: طباعة وتغليف - Packaging | C41: PM-00436 | D41: استيكر هوت شوكلت Hot chocolate sticker | F41: Box | G41: 1 | H41: =VLOOKUP(C41,'Master File June-26'!$C$3:$I$670,6,0) -> 5.5 | I41: =VLOOKUP(C41,'Master File June-26'!$C$3:$I$670,7,0) -> 5.5 | J41: =VLOOKUP(C41,'Master File June-26'!C:J,8,0) -> 14 | K41: =I41*(J41/25) -> 3.08 | L41: =VLOOKUP(C41,'Master File June-26'!C:L,10,0) -> 0 | M41: =IFERROR((L41/I41*30),0) -> 0 | N41: =IF(M41<J41,"ORDER NOW","IN STOCK") -> ORDER NOW | O41: =IF(M41<J41,"CRITICAL","FOLLOW UP DELIVERY") -> CRITICAL | P41: A | Q41: =VLOOKUP(C41,'Master File June-26'!$C$3:$S$670,17,0) -> 46113.431
A42: 50 | B42: Consumables | C42: PM-00240 | D42: Cold Brew Filter فلتر كولد برو خفيف | E42: 1 Pcs | F42: Pcs | G42: 1 | H42: =VLOOKUP(C42,'Master File June-26'!$C$3:$I$670,6,0) -> 44 | I42: =VLOOKUP(C42,'Master File June-26'!$C$3:$I$670,7,0) -> 44 | J42: =VLOOKUP(C42,'Master File June-26'!C:J,8,0) -> 14 | K42: =I42*(J42/25) -> 24.64 | L42: =VLOOKUP(C42,'Master File June-26'!C:L,10,0) -> 0 | M42: =IFERROR((L42/I42*30),0) -> 0 | N42: =IF(M42<J42,"ORDER NOW","IN STOCK") -> ORDER NOW | O42: =IF(M42<J42,"CRITICAL","FOLLOW UP DELIVERY") -> CRITICAL | P42: A | Q42: =VLOOKUP(C42,'Master File June-26'!$C$3:$S$670,17,0) -> 46113.431
A43: 66 | B43: طباعة وتغليف - Packaging | C43: PM-00276 | D43: Tape شطرطون | E43: 1 Box X 24 Pcs | F43: Box | G43: 0.041666667 | H43: =VLOOKUP(C43,'Master File June-26'!$C$3:$I$670,6,0) -> 5.5 | I43: =VLOOKUP(C43,'Master File June-26'!$C$3:$I$670,7,0) -> 132 | J43: =VLOOKUP(C43,'Master File June-26'!C:J,8,0) -> 14 | K43: =I43*(J43/25) -> 73.92 | L43: =VLOOKUP(C43,'Master File June-26'!C:L,10,0) -> 0 | M43: =IFERROR((L43/I43*30),0) -> 0 | N43: =IF(M43<J43,"ORDER NOW","IN STOCK") -> ORDER NOW | O43: =IF(M43<J43,"CRITICAL","FOLLOW UP DELIVERY") -> CRITICAL | P43: A | Q43: =VLOOKUP(C43,'Master File June-26'!$C$3:$S$670,17,0) -> 46113.431
A44: 69 | B44: طباعة وتغليف - Packaging | C44: PM-00448 | D44: Sticker Date ستيكر التاريخ | G44: 1 | H44: =VLOOKUP(C44,'Master File June-26'!$C$3:$I$670,6,0) -> 5.5 | I44: =VLOOKUP(C44,'Master File June-26'!$C$3:$I$670,7,0) -> 5.5 | J44: =VLOOKUP(C44,'Master File June-26'!C:J,8,0) -> 14 | K44: =I44*(J44/25) -> 3.08 | L44: =VLOOKUP(C44,'Master File June-26'!C:L,10,0) -> 0 | M44: =IFERROR((L44/I44*30),0) -> 0 | N44: =IF(M44<J44,"ORDER NOW","IN STOCK") -> ORDER NOW | O44: =IF(M44<J44,"CRITICAL","FOLLOW UP DELIVERY") -> CRITICAL | P44: A | Q44: =VLOOKUP(C44,'Master File June-26'!$C$3:$S$670,17,0) -> 46113.431
A45: 72 | B45: طباعة وتغليف - Packaging | C45: PM-00341 | D45: Point of sale roll - رول نقاط البيع | E45: 1 Box X 50 Pcs | F45: Box | G45: =1/50 -> 0.02 | H45: =VLOOKUP(C45,'Master File June-26'!$C$3:$I$670,6,0) -> 11 | I45: =VLOOKUP(C45,'Master File June-26'!$C$3:$I$670,7,0) -> 550 | J45: =VLOOKUP(C45,'Master File June-26'!C:J,8,0) -> 14 | K45: =I45*(J45/25) -> 308 | L45: =VLOOKUP(C45,'Master File June-26'!C:L,10,0) -> 0 | M45: =IFERROR((L45/I45*30),0) -> 0 | N45: =IF(M45<J45,"ORDER NOW","IN STOCK") -> ORDER NOW | O45: =IF(M45<J45,"CRITICAL","FOLLOW UP DELIVERY") -> CRITICAL | P45: A | Q45: =VLOOKUP(C45,'Master File June-26'!$C$3:$S$670,17,0) -> 46114.517
A46: 107 | B46: طباعة وتغليف - Packaging | C46: PM-00268 | D46: Breehant CANSعلبة بريهانت الباردة | E46: 1 Box X 200 Pcs | F46: Box | G46: 0.005 | H46: =VLOOKUP(C46,'Master File June-26'!$C$3:$I$670,6,0) -> 25 | I46: =VLOOKUP(C46,'Master File June-26'!$C$3:$I$670,7,0) -> 5000 | J46: =VLOOKUP(C46,'Master File June-26'!C:J,8,0) -> 14 | K46: =I46*(J46/25) -> 2800 | L46: =VLOOKUP(C46,'Master File June-26'!C:L,10,0) -> 0 | M46: =IFERROR((L46/I46*30),0) -> 0 | N46: =IF(M46<J46,"ORDER NOW","IN STOCK") -> ORDER NOW | O46: =IF(M46<J46,"CRITICAL","FOLLOW UP DELIVERY") -> CRITICAL | P46: A | Q46: =VLOOKUP(C46,'Master File June-26'!$C$3:$S$670,17,0) -> 46113.431
A47: 112 | B47: طباعة وتغليف - Packaging | C47: PM-00369 | D47: Saudi coffee sticker roll رول استيكر القهوه السعوديه | E47: 1 Box X 1000 Pcs | F47: Box | G47: =1/1000 -> 0.001 | H47: =VLOOKUP(C47,'Master File June-26'!$C$3:$I$670,6,0) -> 15 | I47: =VLOOKUP(C47,'Master File June-26'!$C$3:$I$670,7,0) -> 15000 | J47: =VLOOKUP(C47,'Master File June-26'!C:J,8,0) -> 14 | K47: =I47*(J47/25) -> 8400 | L47: =VLOOKUP(C47,'Master File June-26'!C:L,10,0) -> 0 | M47: =IFERROR((L47/I47*30),0) -> 0 | N47: =IF(M47<J47,"ORDER NOW","IN STOCK") -> ORDER NOW | O47: =IF(M47<J47,"CRITICAL","FOLLOW UP DELIVERY") -> CRITICAL | P47: A | Q47: =VLOOKUP(C47,'Master File June-26'!$C$3:$S$670,17,0) -> 46113.431
A48: 116 | B48: طباعة وتغليف - Packaging | C48: PM-00445 | D48: Caramel Bites Sticker Bar (Nmaq) ستيكر بار كراميل بايتس ( نمق ) | E48: 1 Roll X 1000 Pcs. | F48: Box | G48: 0.001 | H48: =VLOOKUP(C48,'Master File June-26'!$C$3:$I$670,6,0) -> 8 | I48: =VLOOKUP(C48,'Master File June-26'!$C$3:$I$670,7,0) -> 8000 | J48: =VLOOKUP(C48,'Master File June-26'!C:J,8,0) -> 14 | K48: =I48*(J48/25) -> 4480 | L48: =VLOOKUP(C48,'Master File June-26'!C:L,10,0) -> 0 | M48: =IFERROR((L48/I48*30),0) -> 0 | N48: =IF(M48<J48,"ORDER NOW","IN STOCK") -> ORDER NOW | O48: =IF(M48<J48,"CRITICAL","FOLLOW UP DELIVERY") -> CRITICAL | P48: A | Q48: =VLOOKUP(C48,'Master File June-26'!$C$3:$S$670,17,0) -> 46113.431
A49: 127 | B49: طباعة وتغليف - Packaging | C49: PM-00076 | D49: Salted caramel box بوكس كراميل مملح | E49: 1 bundle X 100 PCS | F49: bundel | G49: 0.01 | H49: =VLOOKUP(C49,'Master File June-26'!$C$3:$I$670,6,0) -> 300 | I49: =VLOOKUP(C49,'Master File June-26'!$C$3:$I$670,7,0) -> 30000 | J49: =VLOOKUP(C49,'Master File June-26'!C:J,8,0) -> 14 | K49: =I49*(J49/25) -> 16800 | L49: =VLOOKUP(C49,'Master File June-26'!C:L,10,0) -> 0 | M49: =IFERROR((L49/I49*30),0) -> 0 | N49: =IF(M49<J49,"ORDER NOW","IN STOCK") -> ORDER NOW | O49: =IF(M49<J49,"CRITICAL","FOLLOW UP DELIVERY") -> CRITICAL | P49: A | Q49: =VLOOKUP(C49,'Master File June-26'!$C$3:$S$670,17,0) -> 46113.431
A50: 136 | B50: طباعة وتغليف - Packaging | C50: PM-00330 | D50: Transfer Chocolate Paper ( Breehant ) ورق ترانسفير التشوكلت ( بريهانت ) | E50: 1 Bundle X 50 Pcs. | F50: bundel | G50: 0.02 | H50: =VLOOKUP(C50,'Master File June-26'!$C$3:$I$670,6,0) -> 0 | I50: =VLOOKUP(C50,'Master File June-26'!$C$3:$I$670,7,0) -> 0 | J50: =VLOOKUP(C50,'Master File June-26'!C:J,8,0) -> 14 | K50: =I50*(J50/25) -> 0 | L50: =VLOOKUP(C50,'Master File June-26'!C:L,10,0) -> 0 | M50: =IFERROR((L50/I50*30),0) -> 0 | N50: =IF(M50<J50,"ORDER NOW","IN STOCK") -> ORDER NOW | O50: =IF(M50<J50,"CRITICAL","FOLLOW UP DELIVERY") -> CRITICAL | P50: A | Q50: =VLOOKUP(C50,'Master File June-26'!$C$3:$S$670,17,0) -> 46113.431
A51: 144 | B51: طباعة وتغليف - Packaging | C51: PM-00688 | D51: سليف مارشميلو كراميل||Marshmallow Caramel Sleeve | E51: Pcs | F51: Pcs | G51: 1 | H51: =VLOOKUP(C51,'Master File June-26'!$C$3:$I$670,6,0) -> 0 | I51: =VLOOKUP(C51,'Master File June-26'!$C$3:$I$670,7,0) -> 200 | J51: =VLOOKUP(C51,'Master File June-26'!C:J,8,0) -> 14 | K51: =I51*(J51/25) -> 112 | L51: =VLOOKUP(C51,'Master File June-26'!C:L,10,0) -> 0 | M51: =IFERROR((L51/I51*30),0) -> 0 | N51: =IF(M51<J51,"ORDER NOW","IN STOCK") -> ORDER NOW | O51: =IF(M51<J51,"CRITICAL","FOLLOW UP DELIVERY") -> CRITICAL | P51: A | Q51: =VLOOKUP(C51,'Master File June-26'!$C$3:$S$670,17,0) -> 46113.431
A52: 150 | B52: طباعة وتغليف - Packaging | C52: PM-00038 | D52: Tiramisu Cover (breehant) غلاف تيراميسو (بريهانت) | E52: 1 Bundle X 500 PCS | F52: bundel | G52: =1/500 -> 0.002 | H52: =VLOOKUP(C52,'Master File June-26'!$C$3:$I$670,6,0) -> 6 | I52: =VLOOKUP(C52,'Master File June-26'!$C$3:$I$670,7,0) -> 3000 | J52: =VLOOKUP(C52,'Master File June-26'!C:J,8,0) -> 14 | K52: =I52*(J52/25) -> 1680 | L52: =VLOOKUP(C52,'Master File June-26'!C:L,10,0) -> 0 | M52: =IFERROR((L52/I52*30),0) -> 0 | N52: =IF(M52<J52,"ORDER NOW","IN STOCK") -> ORDER NOW | O52: =IF(M52<J52,"CRITICAL","FOLLOW UP DELIVERY") -> CRITICAL | P52: A | Q52: =VLOOKUP(C52,'Master File June-26'!$C$3:$S$670,17,0) -> 46113.431
A53: 157 | B53: طباعة وتغليف - Packaging | C53: PM-00347 | D53: ورق ترانسفير الكوكيز مقاس 10سم (بريهانت)Transfer cookies Paper(BREEHANT ) | E53: Sheet 25pcs | F53: Pcs | G53: =1/25 -> 0.04 | H53: =VLOOKUP(C53,'Master File June-26'!$C$3:$I$670,6,0) -> 400 | I53: =VLOOKUP(C53,'Master File June-26'!$C$3:$I$670,7,0) -> 10000 | J53: =VLOOKUP(C53,'Master File June-26'!C:J,8,0) -> 14 | K53: =I53*(J53/25) -> 5600 | L53: =VLOOKUP(C53,'Master File June-26'!C:L,10,0) -> 0 | M53: =IFERROR((L53/I53*30),0) -> 0 | N53: =IF(M53<J53,"ORDER NOW","IN STOCK") -> ORDER NOW | O53: =IF(M53<J53,"CRITICAL","FOLLOW UP DELIVERY") -> CRITICAL | Q53: =VLOOKUP(C53,'Master File June-26'!$C$3:$S$670,17,0) -> 46113.431
A54: 170 | B54: طباعة وتغليف - Packaging | C54: PM-00643 | D54: Pudding box 12 oz.(Breehant)-علبة بودنق 12 أونص (بريهانت) | E54: 1 Box X 150 | F54: Box | G54: 0.0066666667 | H54: =VLOOKUP(C54,'Master File June-26'!$C$3:$I$670,6,0) -> 50 | I54: =VLOOKUP(C54,'Master File June-26'!$C$3:$I$670,7,0) -> 7500 | J54: =VLOOKUP(C54,'Master File June-26'!C:J,8,0) -> 14 | K54: =I54*(J54/25) -> 4200 | L54: =VLOOKUP(C54,'Master File June-26'!C:L,10,0) -> 0 | M54: =IFERROR((L54/I54*30),0) -> 0 | N54: =IF(M54<J54,"ORDER NOW","IN STOCK") -> ORDER NOW | O54: =IF(M54<J54,"CRITICAL","FOLLOW UP DELIVERY") -> CRITICAL | Q54: =VLOOKUP(C54,'Master File June-26'!$C$3:$S$670,17,0) -> 46113.431
A55: 173 | B55: طباعة وتغليف - Packaging | C55: PM-00296 | D55: Aluminium foil قصدير | E55: Box | F55: Box | G55: 1 | H55: 2 | I55: =H55/G55 -> 2 | J55: =VLOOKUP(C55,'Master File June-26'!C:J,8,0) -> 14 | K55: =I55*(J55/25) -> 1.12 | L55: =VLOOKUP(C55,'Master File June-26'!C:L,10,0) -> 0 | M55: =IFERROR((L55/I55*30),0) -> 0 | N55: =IF(M55<J55,"ORDER NOW","IN STOCK") -> ORDER NOW | O55: =IF(M55<J55,"CRITICAL","FOLLOW UP DELIVERY") -> CRITICAL | Q55: =VLOOKUP(C55,[2]Sheet1!$C$3:$P$524,14,0) -> #N/A
A56: 177 | B56: طباعة وتغليف - Packaging | C56: PM-00036 | D56: HD BAG PRINTED 2+2 COLORS SIZE كيس التاندو مطبوع | E56: Box | F56: Box | G56: 0.003125 | H56: =VLOOKUP(C56,'Master File June-26'!$C$3:$I$670,6,0) -> 10 | I56: =VLOOKUP(C56,'Master File June-26'!$C$3:$I$670,7,0) -> 3200 | J56: =VLOOKUP(C56,'Master File June-26'!C:J,8,0) -> 14 | K56: =I56*(J56/25) -> 1792 | L56: =VLOOKUP(C56,'Master File June-26'!C:L,10,0) -> 0 | M56: =IFERROR((L56/I56*30),0) -> 0 | N56: =IF(M56<J56,"ORDER NOW","IN STOCK") -> ORDER NOW | O56: =IF(M56<J56,"CRITICAL","FOLLOW UP DELIVERY") -> CRITICAL | Q56: =VLOOKUP(C56,'Master File June-26'!$C$3:$S$670,17,0) -> 46113.431
C57: PM-00004 | D57: Coffee Beans Bags 250 Grmاكياس بن 250ج بريهانت | H57: =VLOOKUP(C57,'Master File June-26'!$C$3:$I$670,6,0) -> 70 | I57: =VLOOKUP(C57,'Master File June-26'!$C$3:$I$670,7,0) -> 56000 | J57: =VLOOKUP(C57,'Master File June-26'!C:J,8,0) -> 60 | K57: =I57*(J57/25) -> 134400 | L57: =VLOOKUP(C57,'Master File June-26'!C:L,10,0) -> 16000 | M57: =IFERROR((L57/I57*30),0) -> 8.5714286 | N57: =IF(M57<J57,"ORDER NOW","IN STOCK") -> ORDER NOW | O57: =IF(M57<J57,"CRITICAL","FOLLOW UP DELIVERY") -> CRITICAL | Q57: =VLOOKUP(C57,[2]Sheet1!$C$3:$P$524,14,0) -> #N/A
C58: PM-00005 | D58: Coffee Beans Bags 500 Grmاكياس بن 500ج بريهانت | H58: =VLOOKUP(C58,'Master File June-26'!$C$3:$I$670,6,0) -> 10 | I58: =VLOOKUP(C58,'Master File June-26'!$C$3:$I$670,7,0) -> 6000 | J58: =VLOOKUP(C58,'Master File June-26'!C:J,8,0) -> 60 | K58: =I58*(J58/25) -> 14400 | L58: =VLOOKUP(C58,'Master File June-26'!C:L,10,0) -> 0 | M58: =IFERROR((L58/I58*30),0) -> 0 | N58: =IF(M58<J58,"ORDER NOW","IN STOCK") -> ORDER NOW | O58: =IF(M58<J58,"CRITICAL","FOLLOW UP DELIVERY") -> CRITICAL | Q58: =VLOOKUP(C58,[2]Sheet1!$C$3:$P$524,14,0) -> #N/A
A59: 194 | B59: Consumables | C59: CO-00498 | D59: "Syscall GP -101R 10c (set) Digital Coaster pager +charger base with power supply" جهاز بيجر سانكول لنمق | E59: 1 Box X 10 Pcs | F59: Box | G59: 0.1 | H59: =VLOOKUP(C59,'Master File June-26'!$C$3:$I$670,6,0) -> 33 | I59: =VLOOKUP(C59,'Master File June-26'!$C$3:$I$670,7,0) -> 330 | J59: =VLOOKUP(C59,'Master File June-26'!C:J,8,0) -> 14 | K59: =I59*(J59/25) -> 184.8 | L59: =VLOOKUP(C59,'Master File June-26'!C:L,10,0) -> 0 | M59: =IFERROR((L59/I59*30),0) -> 0 | N59: =IF(M59<J59,"ORDER NOW","IN STOCK") -> ORDER NOW | O59: =IF(M59<J59,"CRITICAL","FOLLOW UP DELIVERY") -> CRITICAL | Q59: =VLOOKUP(C59,'Master File June-26'!$C$3:$S$670,17,0) -> 46113.431
A60: 195 | B60: طباعة وتغليف - Packaging | C60: CO-00523 | D60: Turner Spoon Full Steel ملعقة ستيل | E60: 1 Pcs | F60: Pcs | G60: 1 | H60: =VLOOKUP(C60,'Master File June-26'!$C$3:$I$670,6,0) -> 11 | I60: =VLOOKUP(C60,'Master File June-26'!$C$3:$I$670,7,0) -> 11 | J60: =VLOOKUP(C60,'Master File June-26'!C:J,8,0) -> 14 | K60: =I60*(J60/25) -> 6.16 | L60: =VLOOKUP(C60,'Master File June-26'!C:L,10,0) -> 0 | M60: =IFERROR((L60/I60*30),0) -> 0 | N60: =IF(M60<J60,"ORDER NOW","IN STOCK") -> ORDER NOW | O60: =IF(M60<J60,"CRITICAL","FOLLOW UP DELIVERY") -> CRITICAL | Q60: =VLOOKUP(C60,'Master File June-26'!$C$3:$S$670,17,0) -> 46138.481
